Workbook
Name Despesas_Administrativas: #REF!
Name Despesas_Com_RH: #REF!
Name Despesas_Comerciais: #REF!
Name Despesas_Endividamentos: #REF!
Name Despesas_Impostos: #REF!
Name Despesas_Investimentos: #REF!
Name Despesas_N_Operacionais: #REF!
Name Despesas_Operacionais: #REF!
Name LISTA_CLIENTES: OFFSET(#REF!,0,0,COUNTA(#REF!),1)
Name LISTA_FORNECEDORES: OFFSET(#REF!,0,0,COUNTA(#REF!),1)
Name Plano_de_contas: #REF!
Name Receitas_N_Operacionais: #REF!
Name Receitas_Operacionais: #REF!

Sheet FC
A1: FLUXO DE CAIXA MENSAL
A2: - | B2: JANEIRO | C2: FEVEREIRO | D2: MARÇO | E2: ABRIL | F2: MAIO | G2: JUNHO | H2: JULHO | I2: AGOSTO | J2: SETEMBRO | K2: OUTUBRO | L2: NOVEMBRO | M2: DEZEMBRO | N2: TOTAL
A3: ( + ) Disponíveis | B3: =B4+B13+B20 -> 0 | C3: =C4+C13+C20 -> 0 | D3: =D4+D13+D20 -> 0 | E3: =E4+E13+E20 -> 0 | F3: =F4+F13+F20 -> 0 | G3: =G4+G13+G20 -> 0 | H3: =H4+H13+H20 -> 0 | I3: =I4+I13+I20 -> 0 | ... N3: =N4+N13+N20 -> 0
A4: Bancos | B4: =SUM(B5:B12) -> 0 | C4: =SUM(C5:C12) -> 0 | D4: =SUM(D5:D12) -> 0 | E4: =SUM(E5:E12) -> 0 | F4: =SUM(F5:F12) -> 0 | G4: =SUM(G5:G12) -> 0 | H4: =SUM(H5:H12) -> 0 | I4: =SUM(I5:I12) -> 0 | ... N4: =SUM(N5:N12) -> 0
A5: Banco 1 (ag / cc ) | N5: =SUM(FCJAN[[#This Row],[JANEIRO]:[DEZEMBRO]]) -> 0
A6: Banco 2 (ag / cc ) | N6: =SUM(FCJAN[[#This Row],[JANEIRO]:[DEZEMBRO]]) -> 0
A7: Banco 3 (ag / cc ) | N7: =SUM(FCJAN[[#This Row],[JANEIRO]:[DEZEMBRO]]) -> 0
N8: =SUM(FCJAN[[#This Row],[JANEIRO]:[DEZEMBRO]]) -> 0
N9: =SUM(FCJAN[[#This Row],[JANEIRO]:[DEZEMBRO]]) -> 0
N10: =SUM(FCJAN[[#This Row],[JANEIRO]:[DEZEMBRO]]) -> 0
N11: =SUM(FCJAN[[#This Row],[JANEIRO]:[DEZEMBRO]]) -> 0
N12: =SUM(FCJAN[[#This Row],[JANEIRO]:[DEZEMBRO]]) -> 0
A13: Dinheiro/Caixa/Cofre | B13: =SUM(B14:B19) -> 0 | C13: =SUM(C14:C19) -> 0 | D13: =SUM(D14:D19) -> 0 | E13: =SUM(E14:E19) -> 0 | F13: =SUM(F14:F19) -> 0 | G13: =SUM(G14:G19) -> 0 | H13: =SUM(H14:H19) -> 0 | I13: =SUM(I14:I19) -> 0 | ... N13: =SUM(N14:N19) -> 0
A14: Aplicação 1 | N14: =SUM(FCJAN[[#This Row],[JANEIRO]:[DEZEMBRO]]) -> 0
A15: Aplicação 2 | N15: =SUM(FCJAN[[#This Row],[JANEIRO]:[DEZEMBRO]]) -> 0
A16: Aplicação 3 | N16: =SUM(FCJAN[[#This Row],[JANEIRO]:[DEZEMBRO]]) -> 0
N17: =SUM(FCJAN[[#This Row],[JANEIRO]:[DEZEMBRO]]) -> 0
N18: =SUM(FCJAN[[#This Row],[JANEIRO]:[DEZEMBRO]]) -> 0
N19: =SUM(FCJAN[[#This Row],[JANEIRO]:[DEZEMBRO]]) -> 0
A20: Aplicações | B20: =SUM(B21:B26) -> 0 | C20: =SUM(C21:C26) -> 0 | D20: =SUM(D21:D26) -> 0 | E20: =SUM(E21:E26) -> 0 | F20: =SUM(F21:F26) -> 0 | G20: =SUM(G21:G26) -> 0 | H20: =SUM(H21:H26) -> 0 | I20: =SUM(I21:I26) -> 0 | ... N20: =SUM(N21:N26) -> 0
A21: Aplicação 1 | N21: =SUM(FCJAN[[#This Row],[JANEIRO]:[DEZEMBRO]]) -> 0
A22: Aplicação 2 | N22: =SUM(FCJAN[[#This Row],[JANEIRO]:[DEZEMBRO]]) -> 0
A23: Aplicação 3 | N23: =SUM(FCJAN[[#This Row],[JANEIRO]:[DEZEMBRO]]) -> 0
N24: =SUM(FCJAN[[#This Row],[JANEIRO]:[DEZEMBRO]]) -> 0
N25: =SUM(FCJAN[[#This Row],[JANEIRO]:[DEZEMBRO]]) -> 0
N26: =SUM(FCJAN[[#This Row],[JANEIRO]:[DEZEMBRO]]) -> 0
A28: ( + ) Entradas | B28: =SUM(B29:B39) -> 0 | C28: =SUM(C29:C39) -> 0 | D28: =SUM(D29:D39) -> 0 | E28: =SUM(E29:E39) -> 0 | F28: =SUM(F29:F39) -> 0 | G28: =SUM(G29:G39) -> 0 | H28: =SUM(H29:H39) -> 0 | I28: =SUM(I29:I39) -> 0 | ... N28: =SUM(N29:N39) -> 0
A29: Recebimento de Pix | N29: =SUM(FCJAN[[#This Row],[JANEIRO]:[DEZEMBRO]]) -> 0
A30: Recebimento de Dinheiro | N30: =SUM(FCJAN[[#This Row],[JANEIRO]:[DEZEMBRO]]) -> 0
A31: Recebimento de Cartão de Débito | N31: =SUM(FCJAN[[#This Row],[JANEIRO]:[DEZEMBRO]]) -> 0
A32: Recebimento de Cartão de Crédito | N32: =SUM(FCJAN[[#This Row],[JANEIRO]:[DEZEMBRO]]) -> 0
A33: Recebimento via Link de Pagamento | N33: =SUM(FCJAN[[#This Row],[JANEIRO]:[DEZEMBRO]]) -> 0
A34: Aporte Financeiro de Sócios | N34: =SUM(FCJAN[[#This Row],[JANEIRO]:[DEZEMBRO]]) -> 0
A35: Emprestimos bancários | N35: =SUM(FCJAN[[#This Row],[JANEIRO]:[DEZEMBRO]]) -> 0
A36: Outras Receitas não operacionais | N36: =SUM(FCJAN[[#This Row],[JANEIRO]:[DEZEMBRO]]) -> 0
N37: =SUM(FCJAN[[#This Row],[JANEIRO]:[DEZEMBRO]]) -> 0
N38: =SUM(FCJAN[[#This Row],[JANEIRO]:[DEZEMBRO]]) -> 0
N39: =SUM(FCJAN[[#This Row],[JANEIRO]:[DEZEMBRO]]) -> 0
A40: ( - ) Saídas | B40: =SUM(B41:B122) -> 0 | C40: =SUM(C41:C122) -> 0 | D40: =SUM(D41:D122) -> 0 | E40: =SUM(E41:E122) -> 0 | F40: =SUM(F41:F122) -> 0 | G40: =SUM(G41:G122) -> 0 | H40: =SUM(H41:H122) -> 0 | I40: =SUM(I41:I122) -> 0 | ... N40: =SUM(N41:N122) -> 0
A41: 13º 1ª Parcela | N41: =SUM(FCJAN[[#This Row],[JANEIRO]:[DEZEMBRO]]) -> 0
A42: 13º 2ª Parcela | N42: =SUM(FCJAN[[#This Row],[JANEIRO]:[DEZEMBRO]]) -> 0
A43: Adiantamento 40% Do Salário | N43: =SUM(FCJAN[[#This Row],[JANEIRO]:[DEZEMBRO]]) -> 0
A44: Água | N44: =SUM(FCJAN[[#This Row],[JANEIRO]:[DEZEMBRO]]) -> 0
A45: Alimentação | N45: =SUM(FCJAN[[#This Row],[JANEIRO]:[DEZEMBRO]]) -> 0
A46: Aluguel | N46: =SUM(FCJAN[[#This Row],[JANEIRO]:[DEZEMBRO]]) -> 0
A47: Alvará De Inspenção Sanitária | N47: =SUM(FCJAN[[#This Row],[JANEIRO]:[DEZEMBRO]]) -> 0
A48: Aplicações | N48: =SUM(FCJAN[[#This Row],[JANEIRO]:[DEZEMBRO]]) -> 0
A49: Assessoria / Consultoria | N49: =SUM(FCJAN[[#This Row],[JANEIRO]:[DEZEMBRO]]) -> 0
A50: Assiduidade | N50: =SUM(FCJAN[[#This Row],[JANEIRO]:[DEZEMBRO]]) -> 0
A51: Assinaturas | N51: =SUM(FCJAN[[#This Row],[JANEIRO]:[DEZEMBRO]]) -> 0
A52: Beneficios | N52: =SUM(FCJAN[[#This Row],[JANEIRO]:[DEZEMBRO]]) -> 0
... A121: Uniforme | N121: =SUM(FCJAN[[#This Row],[JANEIRO]:[DEZEMBRO]]) -> 0
N122: =SUM(FCJAN[[#This Row],[JANEIRO]:[DEZEMBRO]]) -> 0
A123: ( +/- ) Transferência Internas | B123: =SUM(B124:B132) -> 0 | C123: =SUM(C124:C132) -> 0 | D123: =SUM(D124:D132) -> 0 | E123: =SUM(E124:E132) -> 0 | F123: =SUM(F124:F132) -> 0 | G123: =SUM(G124:G132) -> 0 | H123: =SUM(H124:H132) -> 0 | I123: =SUM(I124:I132) -> 0 | ... N123: =SUM(N124:N132) -> 0
A124: Transferência Entre Contas | B124: 0 | N124: =SUM(FCJAN[[#This Row],[JANEIRO]:[DEZEMBRO]]) -> 0
N125: =SUM(FCJAN[[#This Row],[JANEIRO]:[DEZEMBRO]]) -> 0
N126: =SUM(FCJAN[[#This Row],[JANEIRO]:[DEZEMBRO]]) -> 0
N127: =SUM(FCJAN[[#This Row],[JANEIRO]:[DEZEMBRO]]) -> 0
N128: =SUM(FCJAN[[#This Row],[JANEIRO]:[DEZEMBRO]]) -> 0
N129: =SUM(FCJAN[[#This Row],[JANEIRO]:[DEZEMBRO]]) -> 0
N130: =SUM(FCJAN[[#This Row],[JANEIRO]:[DEZEMBRO]]) -> 0
N131: =SUM(FCJAN[[#This Row],[JANEIRO]:[DEZEMBRO]]) -> 0
N132: =SUM(FCJAN[[#This Row],[JANEIRO]:[DEZEMBRO]]) -> 0
A133: ( = ) Geração de Caixa | B133: =B28-B40 -> 0 | C133: =C28-C40 -> 0 | D133: =D28-D40 -> 0 | E133: =E28-E40 -> 0 | F133: =F28-F40 -> 0 | G133: =G28-G40 -> 0 | H133: =H28-H40 -> 0 | I133: =I28-I40 -> 0 | ... N133: =N28-N40 -> 0
A134: ( + ) Saldo Inicial | B134: =B3 -> 0 | C134: =B135 -> 0 | D134: =C135 -> 0 | E134: =D135 -> 0 | F134: =E135 -> 0 | G134: =F135 -> 0 | H134: =G135 -> 0 | I134: =H135 -> 0 | J134: =I135 -> 0 | ... N134: =M135 -> 0
A135: ( = ) Saldo Final | B135: =B123+B133+B134 -> 0 | C135: =C123+C133+C134 -> 0 | D135: =D123+D133+D134 -> 0 | E135: =E123+E133+E134 -> 0 | F135: =F123+F133+F134 -> 0 | G135: =G123+G133+G134 -> 0 | H135: =H123+H133+H134 -> 0 | I135: =I123+I133+I134 -> 0 | ... N135: =N123+N133+N134 -> 0

Sheet DRE
A1: DEMONSTRAÇÃO DE RESULTADO DE EXERCÍCIO
A2: DRE | B2: JANEIRO | C2: AV % JAN | D2: FEVEREIRO | E2: AV % FEV | F2: AH % FEV | G2: MARÇO | H2: AV % MAR | I2: AH % MAR | J2: ABRIL | K2: AV % ABR | L2: AH % ABR | M2: MAIO | N2: AV % MAI | O2: AH % MAI | P2: JUNHO | Q2: AV % JU | R2: AH % JUN | S2: JULHO | T2: AV % JUL | U2: AH % JUL | V2: AGOSTO | W2: AV % AGO | X2: AH % AGO | Y2: SETEMBRO | Z2: AV % SET | AA2: AH % SET | AB2: OUTUBRO | AC2: AV % OUT | AD2: AH % OUT | AE2: NOVEMBRO | AF2: AV % NOV | AG2: AH % NOV | AH2: DEZEMBRO | AI2: AV % DEZ | AJ2: AH % DEZ | AK2: TOTAL | AL2: AV % TT | AM2: MÉDIA
A3: (+) RECEITA TOTAL DE VENDAS | B3: =B4+B9+B14+B19+B24+B28 -> 0 | C3: =IFERROR(B3/$B$3,"") | D3: =D4+D9+D14+D19+D24+D28 -> 0 | E3: =IFERROR(D3/$D$3,"") | F3: =IFERROR((D3-B3)/B3,"") | G3: =G4+G9+G14+G19+G24+G28 -> 0 | H3: =IFERROR(G3/$G$3,"") | I3: =IFERROR((G3-D3)/D3,"") | J3: =J4+J9+J14+J19+J24+J28 -> 0 | K3: =IFERROR(J3/$J$3,"") | L3: =IFERROR((J3-G3)/G3,"") | M3: =M4+M9+M14+M19+M24+M28 -> 0 | N3: =IFERROR(M3/$M$3,"") | O3: =IFERROR((M3-J3)/J3,"") | P3: =P4+P9+P14+P19+P24+P28 -> 0 | Q3: =IFERROR(P3/$P$3,"") | R3: =IFERROR((P3-M3)/M3,"") | S3: =S4+S9+S14+S19+S24+S28 -> 0 | T3: =IFERROR(S3/$S$3,"") | U3: =IFERROR((S3-P3)/P3,"") | V3: =V4+V9+V14+V19+V24+V28 -> 0 | W3: =IFERROR(V3/$V$3,"") | X3: =IFERROR((V3-S3)/S3,"") | Y3: =Y4+Y9+Y14+Y19+Y24+Y28 -> 0 | Z3: =IFERROR(Y3/$Y$3,"") | AA3: =IFERROR((Y3-V3)/V3,"") | AB3: =AB4+AB9+AB14+AB19+AB24+AB28 -> 0 | AC3: =IFERROR(AB3/$AB$3,"") | AD3: =IFERROR((AB3-Y3)/Y3,"") | AE3: =AE4+AE9+AE14+AE19+AE24+AE28 -> 0 | AF3: =IFERROR(AE3/$AE$3,"") | AG3: =IFERROR((AE3-AB3)/AB3,"") | AH3: =AH4+AH9+AH14+AH19+AH24+AH28 -> 0 | AI3: =IFERROR(AH3/$AH$3,"") | AJ3: =IFERROR((AH3-AE3)/AE3,"") | AK3: =SUM(Tabela373[[#This Row],[JANEIRO]]+Tabela373[[#This Row],[FEVEREIRO]]+Tabela373[[#This Row],[MARÇO]]+Tabela373[[#This Row],[ABRIL]]+Tabela373[[#This Row],[MAIO]]+Tabela373[[#This Row],[JUNHO]]+Tabela373[[#This Row],[JULHO]]+Tabela373[[#This Row],[AGOSTO]]+Tabela373[[#This Row],[SETEMBRO]]+Tabela373[[#This Row],[NOVEMBRO]]+Tabela373[[#This Row],[DEZEMBRO]]) -> 0 | AL3: =IFERROR(AK3/$AK$3,"") | AM3: =AVERAGE(Tabela373[[#This Row],[JANEIRO]],Tabela373[[#This Row],[FEVEREIRO]],Tabela373[[#This Row],[MARÇO]],Tabela373[[#This Row],[ABRIL]],Tabela373[[#This Row],[MAIO]],Tabela373[[#This Row],[JUNHO]],Tabela373[[#This Row],[JULHO]],Tabela373[[#This Row],[AGOSTO]],Tabela373[[#This Row],[SETEMBRO]],Tabela373[[#This Row],[OUTUBRO]],Tabela373[[#This Row],[NOVEMBRO]],Tabela373[[#This Row],[DEZEMBRO]]) -> 0
A4: PRODUTOS | B4: =SUM(B5:B8) -> 0 | C4: =IFERROR(B4/$B$3,"") | D4: =SUM(D5:D8) -> 0 | E4: =IFERROR(D4/$D$3,"") | F4: =IFERROR((D4-B4)/B4,"") | G4: =SUM(G5:G8) -> 0 | H4: =IFERROR(G4/$G$3,"") | I4: =IFERROR((G4-D4)/D4,"") | J4: =SUM(J5:J8) -> 0 | K4: =IFERROR(J4/$J$3,"") | L4: =IFERROR((J4-G4)/G4,"") | M4: =SUM(M5:M8) -> 0 | N4: =IFERROR(M4/$M$3,"") | O4: =IFERROR((M4-J4)/J4,"") | P4: =SUM(P5:P8) -> 0 | Q4: =IFERROR(P4/$P$3,"") | R4: =IFERROR((P4-M4)/M4,"") | S4: =SUM(S5:S8) -> 0 | T4: =IFERROR(S4/$S$3,"") | U4: =IFERROR((S4-P4)/P4,"") | V4: =SUM(V5:V8) -> 0 | W4: =IFERROR(V4/$V$3,"") | X4: =IFERROR((V4-S4)/S4,"") | Y4: =SUM(Y5:Y8) -> 0 | Z4: =IFERROR(Y4/$Y$3,"") | AA4: =IFERROR((Y4-V4)/V4,"") | AB4: =SUM(AB5:AB8) -> 0 | AC4: =IFERROR(AB4/$AB$3,"") | AD4: =IFERROR((AB4-Y4)/Y4,"") | AE4: =SUM(AE5:AE8) -> 0 | AF4: =IFERROR(AE4/$AE$3,"") | AG4: =IFERROR((AE4-AB4)/AB4,"") | AH4: =SUM(AH5:AH8) -> 0 | AI4: =IFERROR(AH4/$AH$3,"") | AJ4: =IFERROR((AH4-AE4)/AE4,"") | AK4: =SUM(Tabela373[[#This Row],[JANEIRO]]+Tabela373[[#This Row],[FEVEREIRO]]+Tabela373[[#This Row],[MARÇO]]+Tabela373[[#This Row],[ABRIL]]+Tabela373[[#This Row],[MAIO]]+Tabela373[[#This Row],[JUNHO]]+Tabela373[[#This Row],[JULHO]]+Tabela373[[#This Row],[AGOSTO]]+Tabela373[[#This Row],[SETEMBRO]]+Tabela373[[#This Row],[NOVEMBRO]]+Tabela373[[#This Row],[DEZEMBRO]]) -> 0 | AL4: =IFERROR(AK4/$AK$3,"") | AM4: =AVERAGE(Tabela373[[#This Row],[JANEIRO]],Tabela373[[#This Row],[FEVEREIRO]],Tabela373[[#This Row],[MARÇO]],Tabela373[[#This Row],[ABRIL]],Tabela373[[#This Row],[MAIO]],Tabela373[[#This Row],[JUNHO]],Tabela373[[#This Row],[JULHO]],Tabela373[[#This Row],[AGOSTO]],Tabela373[[#This Row],[SETEMBRO]],Tabela373[[#This Row],[OUTUBRO]],Tabela373[[#This Row],[NOVEMBRO]],Tabela373[[#This Row],[DEZEMBRO]]) -> 0
A5: PRODUTO 1 | C5: =IFERROR(B5/$B$3,"") | E5: =IFERROR(D5/$D$3,"") | F5: =IFERROR((D5-B5)/B5,"") | H5: =IFERROR(G5/$G$3,"") | I5: =IFERROR((G5-D5)/D5,"") | K5: =IFERROR(J5/$J$3,"") | L5: =IFERROR((J5-G5)/G5,"") | N5: =IFERROR(M5/$M$3,"") | O5: =IFERROR((M5-J5)/J5,"") | Q5: =IFERROR(P5/$P$3,"") | R5: =IFERROR((P5-M5)/M5,"") | T5: =IFERROR(S5/$S$3,"") | U5: =IFERROR((S5-P5)/P5,"") | W5: =IFERROR(V5/$V$3,"") | X5: =IFERROR((V5-S5)/S5,"") | Z5: =IFERROR(Y5/$Y$3,"") | AA5: =IFERROR((Y5-V5)/V5,"") | AC5: =IFERROR(AB5/$AB$3,"") | AD5: =IFERROR((AB5-Y5)/Y5,"") | AF5: =IFERROR(AE5/$AE$3,"") | AG5: =IFERROR((AE5-AB5)/AB5,"") | AI5: =IFERROR(AH5/$AH$3,"") | AJ5: =IFERROR((AH5-AE5)/AE5,"") | AK5: =SUM(Tabela373[[#This Row],[JANEIRO]]+Tabela373[[#This Row],[FEVEREIRO]]+Tabela373[[#This Row],[MARÇO]]+Tabela373[[#This Row],[ABRIL]]+Tabela373[[#This Row],[MAIO]]+Tabela373[[#This Row],[JUNHO]]+Tabela373[[#This Row],[JULHO]]+Tabela373[[#This Row],[AGOSTO]]+Tabela373[[#This Row],[SETEMBRO]]+Tabela373[[#This Row],[NOVEMBRO]]+Tabela373[[#This Row],[DEZEMBRO]]) -> 0 | AL5: =IFERROR(AK5/$AK$3,"") | AM5: =AVERAGE(Tabela373[[#This Row],[JANEIRO]],Tabela373[[#This Row],[FEVEREIRO]],Tabela373[[#This Row],[MARÇO]],Tabela373[[#This Row],[ABRIL]],Tabela373[[#This Row],[MAIO]],Tabela373[[#This Row],[JUNHO]],Tabela373[[#This Row],[JULHO]],Tabela373[[#This Row],[AGOSTO]],Tabela373[[#This Row],[SETEMBRO]],Tabela373[[#This Row],[OUTUBRO]],Tabela373[[#This Row],[NOVEMBRO]],Tabela373[[#This Row],[DEZEMBRO]]) -> #DIV/0!
A6: PRODUTO 2 | C6: =IFERROR(B6/$B$3,"") | E6: =IFERROR(D6/$D$3,"") | F6: =IFERROR((D6-B6)/B6,"") | H6: =IFERROR(G6/$G$3,"") | I6: =IFERROR((G6-D6)/D6,"") | K6: =IFERROR(J6/$J$3,"") | L6: =IFERROR((J6-G6)/G6,"") | N6: =IFERROR(M6/$M$3,"") | O6: =IFERROR((M6-J6)/J6,"") | Q6: =IFERROR(P6/$P$3,"") | R6: =IFERROR((P6-M6)/M6,"") | T6: =IFERROR(S6/$S$3,"") | U6: =IFERROR((S6-P6)/P6,"") | W6: =IFERROR(V6/$V$3,"") | X6: =IFERROR((V6-S6)/S6,"") | Z6: =IFERROR(Y6/$Y$3,"") | AA6: =IFERROR((Y6-V6)/V6,"") | AC6: =IFERROR(AB6/$AB$3,"") | AD6: =IFERROR((AB6-Y6)/Y6,"") | AF6: =IFERROR(AE6/$AE$3,"") | AG6: =IFERROR((AE6-AB6)/AB6,"") | AI6: =IFERROR(AH6/$AH$3,"") | AJ6: =IFERROR((AH6-AE6)/AE6,"") | AK6: =SUM(Tabela373[[#This Row],[JANEIRO]]+Tabela373[[#This Row],[FEVEREIRO]]+Tabela373[[#This Row],[MARÇO]]+Tabela373[[#This Row],[ABRIL]]+Tabela373[[#This Row],[MAIO]]+Tabela373[[#This Row],[JUNHO]]+Tabela373[[#This Row],[JULHO]]+Tabela373[[#This Row],[AGOSTO]]+Tabela373[[#This Row],[SETEMBRO]]+Tabela373[[#This Row],[NOVEMBRO]]+Tabela373[[#This Row],[DEZEMBRO]]) -> 0 | AL6: =IFERROR(AK6/$AK$3,"") | AM6: =AVERAGE(Tabela373[[#This Row],[JANEIRO]],Tabela373[[#This Row],[FEVEREIRO]],Tabela373[[#This Row],[MARÇO]],Tabela373[[#This Row],[ABRIL]],Tabela373[[#This Row],[MAIO]],Tabela373[[#This Row],[JUNHO]],Tabela373[[#This Row],[JULHO]],Tabela373[[#This Row],[AGOSTO]],Tabela373[[#This Row],[SETEMBRO]],Tabela373[[#This Row],[OUTUBRO]],Tabela373[[#This Row],[NOVEMBRO]],Tabela373[[#This Row],[DEZEMBRO]]) -> #DIV/0!
A7: PRODUTO 3 | C7: =IFERROR(B7/$B$3,"") | E7: =IFERROR(D7/$D$3,"") | F7: =IFERROR((D7-B7)/B7,"") | H7: =IFERROR(G7/$G$3,"") | I7: =IFERROR((G7-D7)/D7,"") | K7: =IFERROR(J7/$J$3,"") | L7: =IFERROR((J7-G7)/G7,"") | N7: =IFERROR(M7/$M$3,"") | O7: =IFERROR((M7-J7)/J7,"") | Q7: =IFERROR(P7/$P$3,"") | R7: =IFERROR((P7-M7)/M7,"") | T7: =IFERROR(S7/$S$3,"") | U7: =IFERROR((S7-P7)/P7,"") | W7: =IFERROR(V7/$V$3,"") | X7: =IFERROR((V7-S7)/S7,"") | Z7: =IFERROR(Y7/$Y$3,"") | AA7: =IFERROR((Y7-V7)/V7,"") | AC7: =IFERROR(AB7/$AB$3,"") | AD7: =IFERROR((AB7-Y7)/Y7,"") | AF7: =IFERROR(AE7/$AE$3,"") | AG7: =IFERROR((AE7-AB7)/AB7,"") | AI7: =IFERROR(AH7/$AH$3,"") | AJ7: =IFERROR((AH7-AE7)/AE7,"") | AK7: =SUM(Tabela373[[#This Row],[JANEIRO]]+Tabela373[[#This Row],[FEVEREIRO]]+Tabela373[[#This Row],[MARÇO]]+Tabela373[[#This Row],[ABRIL]]+Tabela373[[#This Row],[MAIO]]+Tabela373[[#This Row],[JUNHO]]+Tabela373[[#This Row],[JULHO]]+Tabela373[[#This Row],[AGOSTO]]+Tabela373[[#This Row],[SETEMBRO]]+Tabela373[[#This Row],[NOVEMBRO]]+Tabela373[[#This Row],[DEZEMBRO]]) -> 0 | AL7: =IFERROR(AK7/$AK$3,"") | AM7: =AVERAGE(Tabela373[[#This Row],[JANEIRO]],Tabela373[[#This Row],[FEVEREIRO]],Tabela373[[#This Row],[MARÇO]],Tabela373[[#This Row],[ABRIL]],Tabela373[[#This Row],[MAIO]],Tabela373[[#This Row],[JUNHO]],Tabela373[[#This Row],[JULHO]],Tabela373[[#This Row],[AGOSTO]],Tabela373[[#This Row],[SETEMBRO]],Tabela373[[#This Row],[OUTUBRO]],Tabela373[[#This Row],[NOVEMBRO]],Tabela373[[#This Row],[DEZEMBRO]]) -> #DIV/0!
C8: =IFERROR(B8/$B$3,"") | E8: =IFERROR(D8/$D$3,"") | F8: =IFERROR((D8-B8)/B8,"") | H8: =IFERROR(G8/$G$3,"") | I8: =IFERROR((G8-D8)/D8,"") | K8: =IFERROR(J8/$J$3,"") | L8: =IFERROR((J8-G8)/G8,"") | N8: =IFERROR(M8/$M$3,"") | O8: =IFERROR((M8-J8)/J8,"") | Q8: =IFERROR(P8/$P$3,"") | R8: =IFERROR((P8-M8)/M8,"") | T8: =IFERROR(S8/$S$3,"") | U8: =IFERROR((S8-P8)/P8,"") | W8: =IFERROR(V8/$V$3,"") | X8: =IFERROR((V8-S8)/S8,"") | Z8: =IFERROR(Y8/$Y$3,"") | AA8: =IFERROR((Y8-V8)/V8,"") | AC8: =IFERROR(AB8/$AB$3,"") | AD8: =IFERROR((AB8-Y8)/Y8,"") | AF8: =IFERROR(AE8/$AE$3,"") | AG8: =IFERROR((AE8-AB8)/AB8,"") | AI8: =IFERROR(AH8/$AH$3,"") | AJ8: =IFERROR((AH8-AE8)/AE8,"") | AK8: =SUM(Tabela373[[#This Row],[JANEIRO]]+Tabela373[[#This Row],[FEVEREIRO]]+Tabela373[[#This Row],[MARÇO]]+Tabela373[[#This Row],[ABRIL]]+Tabela373[[#This Row],[MAIO]]+Tabela373[[#This Row],[JUNHO]]+Tabela373[[#This Row],[JULHO]]+Tabela373[[#This Row],[AGOSTO]]+Tabela373[[#This Row],[SETEMBRO]]+Tabela373[[#This Row],[NOVEMBRO]]+Tabela373[[#This Row],[DEZEMBRO]]) -> 0 | AL8: =IFERROR(AK8/$AK$3,"") | AM8: =AVERAGE(Tabela373[[#This Row],[JANEIRO]],Tabela373[[#This Row],[FEVEREIRO]],Tabela373[[#This Row],[MARÇO]],Tabela373[[#This Row],[ABRIL]],Tabela373[[#This Row],[MAIO]],Tabela373[[#This Row],[JUNHO]],Tabela373[[#This Row],[JULHO]],Tabela373[[#This Row],[AGOSTO]],Tabela373[[#This Row],[SETEMBRO]],Tabela373[[#This Row],[OUTUBRO]],Tabela373[[#This Row],[NOVEMBRO]],Tabela373[[#This Row],[DEZEMBRO]]) -> #DIV/0!
A9: LINHA DE PRODUTOS | B9: =SUM(B10:B13) -> 0 | C9: =IFERROR(B9/$B$3,"") | D9: =SUM(D10:D13) -> 0 | E9: =IFERROR(D9/$D$3,"") | F9: =IFERROR((D9-B9)/B9,"") | G9: =SUM(G10:G13) -> 0 | H9: =IFERROR(G9/$G$3,"") | I9: =IFERROR((G9-D9)/D9,"") | J9: =SUM(J10:J13) -> 0 | K9: =IFERROR(J9/$J$3,"") | L9: =IFERROR((J9-G9)/G9,"") | M9: =SUM(M10:M13) -> 0 | N9: =IFERROR(M9/$M$3,"") | O9: =IFERROR((M9-J9)/J9,"") | P9: =SUM(P10:P13) -> 0 | Q9: =IFERROR(P9/$P$3,"") | R9: =IFERROR((P9-M9)/M9,"") | S9: =SUM(S10:S13) -> 0 | T9: =IFERROR(S9/$S$3,"") | U9: =IFERROR((S9-P9)/P9,"") | V9: =SUM(V10:V13) -> 0 | W9: =IFERROR(V9/$V$3,"") | X9: =IFERROR((V9-S9)/S9,"") | Y9: =SUM(Y10:Y13) -> 0 | Z9: =IFERROR(Y9/$Y$3,"") | AA9: =IFERROR((Y9-V9)/V9,"") | AB9: =SUM(AB10:AB13) -> 0 | AC9: =IFERROR(AB9/$AB$3,"") | AD9: =IFERROR((AB9-Y9)/Y9,"") | AE9: =SUM(AE10:AE13) -> 0 | AF9: =IFERROR(AE9/$AE$3,"") | AG9: =IFERROR((AE9-AB9)/AB9,"") | AH9: =SUM(AH10:AH13) -> 0 | AI9: =IFERROR(AH9/$AH$3,"") | AJ9: =IFERROR((AH9-AE9)/AE9,"") | AK9: =SUM(Tabela373[[#This Row],[JANEIRO]]+Tabela373[[#This Row],[FEVEREIRO]]+Tabela373[[#This Row],[MARÇO]]+Tabela373[[#This Row],[ABRIL]]+Tabela373[[#This Row],[MAIO]]+Tabela373[[#This Row],[JUNHO]]+Tabela373[[#This Row],[JULHO]]+Tabela373[[#This Row],[AGOSTO]]+Tabela373[[#This Row],[SETEMBRO]]+Tabela373[[#This Row],[NOVEMBRO]]+Tabela373[[#This Row],[DEZEMBRO]]) -> 0 | AL9: =IFERROR(AK9/$AK$3,"") | AM9: =AVERAGE(Tabela373[[#This Row],[JANEIRO]],Tabela373[[#This Row],[FEVEREIRO]],Tabela373[[#This Row],[MARÇO]],Tabela373[[#This Row],[ABRIL]],Tabela373[[#This Row],[MAIO]],Tabela373[[#This Row],[JUNHO]],Tabela373[[#This Row],[JULHO]],Tabela373[[#This Row],[AGOSTO]],Tabela373[[#This Row],[SETEMBRO]],Tabela373[[#This Row],[OUTUBRO]],Tabela373[[#This Row],[NOVEMBRO]],Tabela373[[#This Row],[DEZEMBRO]]) -> 0
A10: LINHA 1 | C10: =IFERROR(B10/$B$3,"") | E10: =IFERROR(D10/$D$3,"") | F10: =IFERROR((D10-B10)/B10,"") | H10: =IFERROR(G10/$G$3,"") | I10: =IFERROR((G10-D10)/D10,"") | K10: =IFERROR(J10/$J$3,"") | L10: =IFERROR((J10-G10)/G10,"") | N10: =IFERROR(M10/$M$3,"") | O10: =IFERROR((M10-J10)/J10,"") | Q10: =IFERROR(P10/$P$3,"") | R10: =IFERROR((P10-M10)/M10,"") | T10: =IFERROR(S10/$S$3,"") | U10: =IFERROR((S10-P10)/P10,"") | W10: =IFERROR(V10/$V$3,"") | X10: =IFERROR((V10-S10)/S10,"") | Z10: =IFERROR(Y10/$Y$3,"") | AA10: =IFERROR((Y10-V10)/V10,"") | AC10: =IFERROR(AB10/$AB$3,"") | AD10: =IFERROR((AB10-Y10)/Y10,"") | AF10: =IFERROR(AE10/$AE$3,"") | AG10: =IFERROR((AE10-AB10)/AB10,"") | AI10: =IFERROR(AH10/$AH$3,"") | AJ10: =IFERROR((AH10-AE10)/AE10,"") | AK10: =SUM(Tabela373[[#This Row],[JANEIRO]]+Tabela373[[#This Row],[FEVEREIRO]]+Tabela373[[#This Row],[MARÇO]]+Tabela373[[#This Row],[ABRIL]]+Tabela373[[#This Row],[MAIO]]+Tabela373[[#This Row],[JUNHO]]+Tabela373[[#This Row],[JULHO]]+Tabela373[[#This Row],[AGOSTO]]+Tabela373[[#This Row],[SETEMBRO]]+Tabela373[[#This Row],[NOVEMBRO]]+Tabela373[[#This Row],[DEZEMBRO]]) -> 0 | AL10: =IFERROR(AK10/$AK$3,"") | AM10: =AVERAGE(Tabela373[[#This Row],[JANEIRO]],Tabela373[[#This Row],[FEVEREIRO]],Tabela373[[#This Row],[MARÇO]],Tabela373[[#This Row],[ABRIL]],Tabela373[[#This Row],[MAIO]],Tabela373[[#This Row],[JUNHO]],Tabela373[[#This Row],[JULHO]],Tabela373[[#This Row],[AGOSTO]],Tabela373[[#This Row],[SETEMBRO]],Tabela373[[#This Row],[OUTUBRO]],Tabela373[[#This Row],[NOVEMBRO]],Tabela373[[#This Row],[DEZEMBRO]]) -> #DIV/0!
A11: LINHA 2 | C11: =IFERROR(B11/$B$3,"") | E11: =IFERROR(D11/$D$3,"") | F11: =IFERROR((D11-B11)/B11,"") | H11: =IFERROR(G11/$G$3,"") | I11: =IFERROR((G11-D11)/D11,"") | K11: =IFERROR(J11/$J$3,"") | L11: =IFERROR((J11-G11)/G11,"") | N11: =IFERROR(M11/$M$3,"") | O11: =IFERROR((M11-J11)/J11,"") | Q11: =IFERROR(P11/$P$3,"") | R11: =IFERROR((P11-M11)/M11,"") | T11: =IFERROR(S11/$S$3,"") | U11: =IFERROR((S11-P11)/P11,"") | W11: =IFERROR(V11/$V$3,"") | X11: =IFERROR((V11-S11)/S11,"") | Z11: =IFERROR(Y11/$Y$3,"") | AA11: =IFERROR((Y11-V11)/V11,"") | AC11: =IFERROR(AB11/$AB$3,"") | AD11: =IFERROR((AB11-Y11)/Y11,"") | AF11: =IFERROR(AE11/$AE$3,"") | AG11: =IFERROR((AE11-AB11)/AB11,"") | AI11: =IFERROR(AH11/$AH$3,"") | AJ11: =IFERROR((AH11-AE11)/AE11,"") | AK11: =SUM(Tabela373[[#This Row],[JANEIRO]]+Tabela373[[#This Row],[FEVEREIRO]]+Tabela373[[#This Row],[MARÇO]]+Tabela373[[#This Row],[ABRIL]]+Tabela373[[#This Row],[MAIO]]+Tabela373[[#This Row],[JUNHO]]+Tabela373[[#This Row],[JULHO]]+Tabela373[[#This Row],[AGOSTO]]+Tabela373[[#This Row],[SETEMBRO]]+Tabela373[[#This Row],[NOVEMBRO]]+Tabela373[[#This Row],[DEZEMBRO]]) -> 0 | AL11: =IFERROR(AK11/$AK$3,"") | AM11: =AVERAGE(Tabela373[[#This Row],[JANEIRO]],Tabela373[[#This Row],[FEVEREIRO]],Tabela373[[#This Row],[MARÇO]],Tabela373[[#This Row],[ABRIL]],Tabela373[[#This Row],[MAIO]],Tabela373[[#This Row],[JUNHO]],Tabela373[[#This Row],[JULHO]],Tabela373[[#This Row],[AGOSTO]],Tabela373[[#This Row],[SETEMBRO]],Tabela373[[#This Row],[OUTUBRO]],Tabela373[[#This Row],[NOVEMBRO]],Tabela373[[#This Row],[DEZEMBRO]]) -> #DIV/0!
A12: LINHA 3 | C12: =IFERROR(B12/$B$3,"") | E12: =IFERROR(D12/$D$3,"") | F12: =IFERROR((D12-B12)/B12,"") | H12: =IFERROR(G12/$G$3,"") | I12: =IFERROR((G12-D12)/D12,"") | K12: =IFERROR(J12/$J$3,"") | L12: =IFERROR((J12-G12)/G12,"") | N12: =IFERROR(M12/$M$3,"") | O12: =IFERROR((M12-J12)/J12,"") | Q12: =IFERROR(P12/$P$3,"") | R12: =IFERROR((P12-M12)/M12,"") | T12: =IFERROR(S12/$S$3,"") | U12: =IFERROR((S12-P12)/P12,"") | W12: =IFERROR(V12/$V$3,"") | X12: =IFERROR((V12-S12)/S12,"") | Z12: =IFERROR(Y12/$Y$3,"") | AA12: =IFERROR((Y12-V12)/V12,"") | AC12: =IFERROR(AB12/$AB$3,"") | AD12: =IFERROR((AB12-Y12)/Y12,"") | AF12: =IFERROR(AE12/$AE$3,"") | AG12: =IFERROR((AE12-AB12)/AB12,"") | AI12: =IFERROR(AH12/$AH$3,"") | AJ12: =IFERROR((AH12-AE12)/AE12,"") | AK12: =SUM(Tabela373[[#This Row],[JANEIRO]]+Tabela373[[#This Row],[FEVEREIRO]]+Tabela373[[#This Row],[MARÇO]]+Tabela373[[#This Row],[ABRIL]]+Tabela373[[#This Row],[MAIO]]+Tabela373[[#This Row],[JUNHO]]+Tabela373[[#This Row],[JULHO]]+Tabela373[[#This Row],[AGOSTO]]+Tabela373[[#This Row],[SETEMBRO]]+Tabela373[[#This Row],[NOVEMBRO]]+Tabela373[[#This Row],[DEZEMBRO]]) -> 0 | AL12: =IFERROR(AK12/$AK$3,"") | AM12: =AVERAGE(Tabela373[[#This Row],[JANEIRO]],Tabela373[[#This Row],[FEVEREIRO]],Tabela373[[#This Row],[MARÇO]],Tabela373[[#This Row],[ABRIL]],Tabela373[[#This Row],[MAIO]],Tabela373[[#This Row],[JUNHO]],Tabela373[[#This Row],[JULHO]],Tabela373[[#This Row],[AGOSTO]],Tabela373[[#This Row],[SETEMBRO]],Tabela373[[#This Row],[OUTUBRO]],Tabela373[[#This Row],[NOVEMBRO]],Tabela373[[#This Row],[DEZEMBRO]]) -> #DIV/0!
C13: =IFERROR(B13/$B$3,"") | E13: =IFERROR(D13/$D$3,"") | F13: =IFERROR((D13-B13)/B13,"") | H13: =IFERROR(G13/$G$3,"") | I13: =IFERROR((G13-D13)/D13,"") | K13: =IFERROR(J13/$J$3,"") | L13: =IFERROR((J13-G13)/G13,"") | N13: =IFERROR(M13/$M$3,"") | O13: =IFERROR((M13-J13)/J13,"") | Q13: =IFERROR(P13/$P$3,"") | R13: =IFERROR((P13-M13)/M13,"") | T13: =IFERROR(S13/$S$3,"") | U13: =IFERROR((S13-P13)/P13,"") | W13: =IFERROR(V13/$V$3,"") | X13: =IFERROR((V13-S13)/S13,"") | Z13: =IFERROR(Y13/$Y$3,"") | AA13: =IFERROR((Y13-V13)/V13,"") | AC13: =IFERROR(AB13/$AB$3,"") | AD13: =IFERROR((AB13-Y13)/Y13,"") | AF13: =IFERROR(AE13/$AE$3,"") | AG13: =IFERROR((AE13-AB13)/AB13,"") | AI13: =IFERROR(AH13/$AH$3,"") | AJ13: =IFERROR((AH13-AE13)/AE13,"") | AK13: =SUM(Tabela373[[#This Row],[JANEIRO]]+Tabela373[[#This Row],[FEVEREIRO]]+Tabela373[[#This Row],[MARÇO]]+Tabela373[[#This Row],[ABRIL]]+Tabela373[[#This Row],[MAIO]]+Tabela373[[#This Row],[JUNHO]]+Tabela373[[#This Row],[JULHO]]+Tabela373[[#This Row],[AGOSTO]]+Tabela373[[#This Row],[SETEMBRO]]+Tabela373[[#This Row],[NOVEMBRO]]+Tabela373[[#This Row],[DEZEMBRO]]) -> 0 | AL13: =IFERROR(AK13/$AK$3,"") | AM13: =AVERAGE(Tabela373[[#This Row],[JANEIRO]],Tabela373[[#This Row],[FEVEREIRO]],Tabela373[[#This Row],[MARÇO]],Tabela373[[#This Row],[ABRIL]],Tabela373[[#This Row],[MAIO]],Tabela373[[#This Row],[JUNHO]],Tabela373[[#This Row],[JULHO]],Tabela373[[#This Row],[AGOSTO]],Tabela373[[#This Row],[SETEMBRO]],Tabela373[[#This Row],[OUTUBRO]],Tabela373[[#This Row],[NOVEMBRO]],Tabela373[[#This Row],[DEZEMBRO]]) -> #DIV/0!
A14: SERVIÇOS | B14: =SUM(B15:B18) -> 0 | C14: =IFERROR(B14/$B$3,"") | D14: =SUM(D15:D18) -> 0 | E14: =IFERROR(D14/$D$3,"") | F14: =IFERROR((D14-B14)/B14,"") | G14: =SUM(G15:G18) -> 0 | H14: =IFERROR(G14/$G$3,"") | I14: =IFERROR((G14-D14)/D14,"") | J14: =SUM(J15:J18) -> 0 | K14: =IFERROR(J14/$J$3,"") | L14: =IFERROR((J14-G14)/G14,"") | M14: =SUM(M15:M18) -> 0 | N14: =IFERROR(M14/$M$3,"") | O14: =IFERROR((M14-J14)/J14,"") | P14: =SUM(P15:P18) -> 0 | Q14: =IFERROR(P14/$P$3,"") | R14: =IFERROR((P14-M14)/M14,"") | S14: =SUM(S15:S18) -> 0 | T14: =IFERROR(S14/$S$3,"") | U14: =IFERROR((S14-P14)/P14,"") | V14: =SUM(V15:V18) -> 0 | W14: =IFERROR(V14/$V$3,"") | X14: =IFERROR((V14-S14)/S14,"") | Y14: =SUM(Y15:Y18) -> 0 | Z14: =IFERROR(Y14/$Y$3,"") | AA14: =IFERROR((Y14-V14)/V14,"") | AB14: =SUM(AB15:AB18) -> 0 | AC14: =IFERROR(AB14/$AB$3,"") | AD14: =IFERROR((AB14-Y14)/Y14,"") | AE14: =SUM(AE15:AE18) -> 0 | AF14: =IFERROR(AE14/$AE$3,"") | AG14: =IFERROR((AE14-AB14)/AB14,"") | AH14: =SUM(AH15:AH18) -> 0 | AI14: =IFERROR(AH14/$AH$3,"") | AJ14: =IFERROR((AH14-AE14)/AE14,"") | AK14: =SUM(Tabela373[[#This Row],[JANEIRO]]+Tabela373[[#This Row],[FEVEREIRO]]+Tabela373[[#This Row],[MARÇO]]+Tabela373[[#This Row],[ABRIL]]+Tabela373[[#This Row],[MAIO]]+Tabela373[[#This Row],[JUNHO]]+Tabela373[[#This Row],[JULHO]]+Tabela373[[#This Row],[AGOSTO]]+Tabela373[[#This Row],[SETEMBRO]]+Tabela373[[#This Row],[NOVEMBRO]]+Tabela373[[#This Row],[DEZEMBRO]]) -> 0 | AL14: =IFERROR(AK14/$AK$3,"") | AM14: =AVERAGE(Tabela373[[#This Row],[JANEIRO]],Tabela373[[#This Row],[FEVEREIRO]],Tabela373[[#This Row],[MARÇO]],Tabela373[[#This Row],[ABRIL]],Tabela373[[#This Row],[MAIO]],Tabela373[[#This Row],[JUNHO]],Tabela373[[#This Row],[JULHO]],Tabela373[[#This Row],[AGOSTO]],Tabela373[[#This Row],[SETEMBRO]],Tabela373[[#This Row],[OUTUBRO]],Tabela373[[#This Row],[NOVEMBRO]],Tabela373[[#This Row],[DEZEMBRO]]) -> 0
A15: SERVIÇO 1 | C15: =IFERROR(B15/$B$3,"") | E15: =IFERROR(D15/$D$3,"") | F15: =IFERROR((D15-B15)/B15,"") | H15: =IFERROR(G15/$G$3,"") | I15: =IFERROR((G15-D15)/D15,"") | K15: =IFERROR(J15/$J$3,"") | L15: =IFERROR((J15-G15)/G15,"") | N15: =IFERROR(M15/$M$3,"") | O15: =IFERROR((M15-J15)/J15,"") | Q15: =IFERROR(P15/$P$3,"") | R15: =IFERROR((P15-M15)/M15,"") | T15: =IFERROR(S15/$S$3,"") | U15: =IFERROR((S15-P15)/P15,"") | W15: =IFERROR(V15/$V$3,"") | X15: =IFERROR((V15-S15)/S15,"") | Z15: =IFERROR(Y15/$Y$3,"") | AA15: =IFERROR((Y15-V15)/V15,"") | AC15: =IFERROR(AB15/$AB$3,"") | AD15: =IFERROR((AB15-Y15)/Y15,"") | AF15: =IFERROR(AE15/$AE$3,"") | AG15: =IFERROR((AE15-AB15)/AB15,"") | AI15: =IFERROR(AH15/$AH$3,"") | AJ15: =IFERROR((AH15-AE15)/AE15,"") | AK15: =SUM(Tabela373[[#This Row],[JANEIRO]]+Tabela373[[#This Row],[FEVEREIRO]]+Tabela373[[#This Row],[MARÇO]]+Tabela373[[#This Row],[ABRIL]]+Tabela373[[#This Row],[MAIO]]+Tabela373[[#This Row],[JUNHO]]+Tabela373[[#This Row],[JULHO]]+Tabela373[[#This Row],[AGOSTO]]+Tabela373[[#This Row],[SETEMBRO]]+Tabela373[[#This Row],[NOVEMBRO]]+Tabela373[[#This Row],[DEZEMBRO]]) -> 0 | AL15: =IFERROR(AK15/$AK$3,"") | AM15: =AVERAGE(Tabela373[[#This Row],[JANEIRO]],Tabela373[[#This Row],[FEVEREIRO]],Tabela373[[#This Row],[MARÇO]],Tabela373[[#This Row],[ABRIL]],Tabela373[[#This Row],[MAIO]],Tabela373[[#This Row],[JUNHO]],Tabela373[[#This Row],[JULHO]],Tabela373[[#This Row],[AGOSTO]],Tabela373[[#This Row],[SETEMBRO]],Tabela373[[#This Row],[OUTUBRO]],Tabela373[[#This Row],[NOVEMBRO]],Tabela373[[#This Row],[DEZEMBRO]]) -> #DIV/0!
A16: SERVIÇO 2 | C16: =IFERROR(B16/$B$3,"") | E16: =IFERROR(D16/$D$3,"") | F16: =IFERROR((D16-B16)/B16,"") | H16: =IFERROR(G16/$G$3,"") | I16: =IFERROR((G16-D16)/D16,"") | K16: =IFERROR(J16/$J$3,"") | L16: =IFERROR((J16-G16)/G16,"") | N16: =IFERROR(M16/$M$3,"") | O16: =IFERROR((M16-J16)/J16,"") | Q16: =IFERROR(P16/$P$3,"") | R16: =IFERROR((P16-M16)/M16,"") | T16: =IFERROR(S16/$S$3,"") | U16: =IFERROR((S16-P16)/P16,"") | W16: =IFERROR(V16/$V$3,"") | X16: =IFERROR((V16-S16)/S16,"") | Z16: =IFERROR(Y16/$Y$3,"") | AA16: =IFERROR((Y16-V16)/V16,"") | AC16: =IFERROR(AB16/$AB$3,"") | AD16: =IFERROR((AB16-Y16)/Y16,"") | AF16: =IFERROR(AE16/$AE$3,"") | AG16: =IFERROR((AE16-AB16)/AB16,"") | AI16: =IFERROR(AH16/$AH$3,"") | AJ16: =IFERROR((AH16-AE16)/AE16,"") | AK16: =SUM(Tabela373[[#This Row],[JANEIRO]]+Tabela373[[#This Row],[FEVEREIRO]]+Tabela373[[#This Row],[MARÇO]]+Tabela373[[#This Row],[ABRIL]]+Tabela373[[#This Row],[MAIO]]+Tabela373[[#This Row],[JUNHO]]+Tabela373[[#This Row],[JULHO]]+Tabela373[[#This Row],[AGOSTO]]+Tabela373[[#This Row],[SETEMBRO]]+Tabela373[[#This Row],[NOVEMBRO]]+Tabela373[[#This Row],[DEZEMBRO]]) -> 0 | AL16: =IFERROR(AK16/$AK$3,"") | AM16: =AVERAGE(Tabela373[[#This Row],[JANEIRO]],Tabela373[[#This Row],[FEVEREIRO]],Tabela373[[#This Row],[MARÇO]],Tabela373[[#This Row],[ABRIL]],Tabela373[[#This Row],[MAIO]],Tabela373[[#This Row],[JUNHO]],Tabela373[[#This Row],[JULHO]],Tabela373[[#This Row],[AGOSTO]],Tabela373[[#This Row],[SETEMBRO]],Tabela373[[#This Row],[OUTUBRO]],Tabela373[[#This Row],[NOVEMBRO]],Tabela373[[#This Row],[DEZEMBRO]]) -> #DIV/0!
A17: SERVIÇO 3 | C17: =IFERROR(B17/$B$3,"") | E17: =IFERROR(D17/$D$3,"") | F17: =IFERROR((D17-B17)/B17,"") | H17: =IFERROR(G17/$G$3,"") | I17: =IFERROR((G17-D17)/D17,"") | K17: =IFERROR(J17/$J$3,"") | L17: =IFERROR((J17-G17)/G17,"") | N17: =IFERROR(M17/$M$3,"") | O17: =IFERROR((M17-J17)/J17,"") | Q17: =IFERROR(P17/$P$3,"") | R17: =IFERROR((P17-M17)/M17,"") | T17: =IFERROR(S17/$S$3,"") | U17: =IFERROR((S17-P17)/P17,"") | W17: =IFERROR(V17/$V$3,"") | X17: =IFERROR((V17-S17)/S17,"") | Z17: =IFERROR(Y17/$Y$3,"") | AA17: =IFERROR((Y17-V17)/V17,"") | AC17: =IFERROR(AB17/$AB$3,"") | AD17: =IFERROR((AB17-Y17)/Y17,"") | AF17: =IFERROR(AE17/$AE$3,"") | AG17: =IFERROR((AE17-AB17)/AB17,"") | AI17: =IFERROR(AH17/$AH$3,"") | AJ17: =IFERROR((AH17-AE17)/AE17,"") | AK17: =SUM(Tabela373[[#This Row],[JANEIRO]]+Tabela373[[#This Row],[FEVEREIRO]]+Tabela373[[#This Row],[MARÇO]]+Tabela373[[#This Row],[ABRIL]]+Tabela373[[#This Row],[MAIO]]+Tabela373[[#This Row],[JUNHO]]+Tabela373[[#This Row],[JULHO]]+Tabela373[[#This Row],[AGOSTO]]+Tabela373[[#This Row],[SETEMBRO]]+Tabela373[[#This Row],[NOVEMBRO]]+Tabela373[[#This Row],[DEZEMBRO]]) -> 0 | AL17: =IFERROR(AK17/$AK$3,"") | AM17: =AVERAGE(Tabela373[[#This Row],[JANEIRO]],Tabela373[[#This Row],[FEVEREIRO]],Tabela373[[#This Row],[MARÇO]],Tabela373[[#This Row],[ABRIL]],Tabela373[[#This Row],[MAIO]],Tabela373[[#This Row],[JUNHO]],Tabela373[[#This Row],[JULHO]],Tabela373[[#This Row],[AGOSTO]],Tabela373[[#This Row],[SETEMBRO]],Tabela373[[#This Row],[OUTUBRO]],Tabela373[[#This Row],[NOVEMBRO]],Tabela373[[#This Row],[DEZEMBRO]]) -> #DIV/0!
C18: =IFERROR(B18/$B$3,"") | E18: =IFERROR(D18/$D$3,"") | F18: =IFERROR((D18-B18)/B18,"") | H18: =IFERROR(G18/$G$3,"") | I18: =IFERROR((G18-D18)/D18,"") | K18: =IFERROR(J18/$J$3,"") | L18: =IFERROR((J18-G18)/G18,"") | N18: =IFERROR(M18/$M$3,"") | O18: =IFERROR((M18-J18)/J18,"") | Q18: =IFERROR(P18/$P$3,"") | R18: =IFERROR((P18-M18)/M18,"") | T18: =IFERROR(S18/$S$3,"") | U18: =IFERROR((S18-P18)/P18,"") | W18: =IFERROR(V18/$V$3,"") | X18: =IFERROR((V18-S18)/S18,"") | Z18: =IFERROR(Y18/$Y$3,"") | AA18: =IFERROR((Y18-V18)/V18,"") | AC18: =IFERROR(AB18/$AB$3,"") | AD18: =IFERROR((AB18-Y18)/Y18,"") | AF18: =IFERROR(AE18/$AE$3,"") | AG18: =IFERROR((AE18-AB18)/AB18,"") | AI18: =IFERROR(AH18/$AH$3,"") | AJ18: =IFERROR((AH18-AE18)/AE18,"") | AK18: =SUM(Tabela373[[#This Row],[JANEIRO]]+Tabela373[[#This Row],[FEVEREIRO]]+Tabela373[[#This Row],[MARÇO]]+Tabela373[[#This Row],[ABRIL]]+Tabela373[[#This Row],[MAIO]]+Tabela373[[#This Row],[JUNHO]]+Tabela373[[#This Row],[JULHO]]+Tabela373[[#This Row],[AGOSTO]]+Tabela373[[#This Row],[SETEMBRO]]+Tabela373[[#This Row],[NOVEMBRO]]+Tabela373[[#This Row],[DEZEMBRO]]) -> 0 | AL18: =IFERROR(AK18/$AK$3,"") | AM18: =AVERAGE(Tabela373[[#This Row],[JANEIRO]],Tabela373[[#This Row],[FEVEREIRO]],Tabela373[[#This Row],[MARÇO]],Tabela373[[#This Row],[ABRIL]],Tabela373[[#This Row],[MAIO]],Tabela373[[#This Row],[JUNHO]],Tabela373[[#This Row],[JULHO]],Tabela373[[#This Row],[AGOSTO]],Tabela373[[#This Row],[SETEMBRO]],Tabela373[[#This Row],[OUTUBRO]],Tabela373[[#This Row],[NOVEMBRO]],Tabela373[[#This Row],[DEZEMBRO]]) -> #DIV/0!
A19: CANAL DE VENDAS | B19: =SUM(B20:B23) -> 0 | C19: =IFERROR(B19/$B$3,"") | D19: =SUM(D20:D23) -> 0 | E19: =IFERROR(D19/$D$3,"") | F19: =IFERROR((D19-B19)/B19,"") | G19: =SUM(G20:G23) -> 0 | H19: =IFERROR(G19/$G$3,"") | I19: =IFERROR((G19-D19)/D19,"") | J19: =SUM(J20:J23) -> 0 | K19: =IFERROR(J19/$J$3,"") | L19: =IFERROR((J19-G19)/G19,"") | M19: =SUM(M20:M23) -> 0 | N19: =IFERROR(M19/$M$3,"") | O19: =IFERROR((M19-J19)/J19,"") | P19: =SUM(P20:P23) -> 0 | Q19: =IFERROR(P19/$P$3,"") | R19: =IFERROR((P19-M19)/M19,"") | S19: =SUM(S20:S23) -> 0 | T19: =IFERROR(S19/$S$3,"") | U19: =IFERROR((S19-P19)/P19,"") | V19: =SUM(V20:V23) -> 0 | W19: =IFERROR(V19/$V$3,"") | X19: =IFERROR((V19-S19)/S19,"") | Y19: =SUM(Y20:Y23) -> 0 | Z19: =IFERROR(Y19/$Y$3,"") | AA19: =IFERROR((Y19-V19)/V19,"") | AB19: =SUM(AB20:AB23) -> 0 | AC19: =IFERROR(AB19/$AB$3,"") | AD19: =IFERROR((AB19-Y19)/Y19,"") | AE19: =SUM(AE20:AE23) -> 0 | AF19: =IFERROR(AE19/$AE$3,"") | AG19: =IFERROR((AE19-AB19)/AB19,"") | AH19: =SUM(AH20:AH23) -> 0 | AI19: =IFERROR(AH19/$AH$3,"") | AJ19: =IFERROR((AH19-AE19)/AE19,"") | AK19: =SUM(Tabela373[[#This Row],[JANEIRO]]+Tabela373[[#This Row],[FEVEREIRO]]+Tabela373[[#This Row],[MARÇO]]+Tabela373[[#This Row],[ABRIL]]+Tabela373[[#This Row],[MAIO]]+Tabela373[[#This Row],[JUNHO]]+Tabela373[[#This Row],[JULHO]]+Tabela373[[#This Row],[AGOSTO]]+Tabela373[[#This Row],[SETEMBRO]]+Tabela373[[#This Row],[NOVEMBRO]]+Tabela373[[#This Row],[DEZEMBRO]]) -> 0 | AL19: =IFERROR(AK19/$AK$3,"") | AM19: =AVERAGE(Tabela373[[#This Row],[JANEIRO]],Tabela373[[#This Row],[FEVEREIRO]],Tabela373[[#This Row],[MARÇO]],Tabela373[[#This Row],[ABRIL]],Tabela373[[#This Row],[MAIO]],Tabela373[[#This Row],[JUNHO]],Tabela373[[#This Row],[JULHO]],Tabela373[[#This Row],[AGOSTO]],Tabela373[[#This Row],[SETEMBRO]],Tabela373[[#This Row],[OUTUBRO]],Tabela373[[#This Row],[NOVEMBRO]],Tabela373[[#This Row],[DEZEMBRO]]) -> 0
A20: LOJA FISICA | C20: =IFERROR(B20/$B$3,"") | E20: =IFERROR(D20/$D$3,"") | F20: =IFERROR((D20-B20)/B20,"") | H20: =IFERROR(G20/$G$3,"") | I20: =IFERROR((G20-D20)/D20,"") | K20: =IFERROR(J20/$J$3,"") | L20: =IFERROR((J20-G20)/G20,"") | N20: =IFERROR(M20/$M$3,"") | O20: =IFERROR((M20-J20)/J20,"") | Q20: =IFERROR(P20/$P$3,"") | R20: =IFERROR((P20-M20)/M20,"") | T20: =IFERROR(S20/$S$3,"") | U20: =IFERROR((S20-P20)/P20,"") | W20: =IFERROR(V20/$V$3,"") | X20: =IFERROR((V20-S20)/S20,"") | Z20: =IFERROR(Y20/$Y$3,"") | AA20: =IFERROR((Y20-V20)/V20,"") | AC20: =IFERROR(AB20/$AB$3,"") | AD20: =IFERROR((AB20-Y20)/Y20,"") | AF20: =IFERROR(AE20/$AE$3,"") | AG20: =IFERROR((AE20-AB20)/AB20,"") | AI20: =IFERROR(AH20/$AH$3,"") | AJ20: =IFERROR((AH20-AE20)/AE20,"") | AK20: =SUM(Tabela373[[#This Row],[JANEIRO]]+Tabela373[[#This Row],[FEVEREIRO]]+Tabela373[[#This Row],[MARÇO]]+Tabela373[[#This Row],[ABRIL]]+Tabela373[[#This Row],[MAIO]]+Tabela373[[#This Row],[JUNHO]]+Tabela373[[#This Row],[JULHO]]+Tabela373[[#This Row],[AGOSTO]]+Tabela373[[#This Row],[SETEMBRO]]+Tabela373[[#This Row],[NOVEMBRO]]+Tabela373[[#This Row],[DEZEMBRO]]) -> 0 | AL20: =IFERROR(AK20/$AK$3,"") | AM20: =AVERAGE(Tabela373[[#This Row],[JANEIRO]],Tabela373[[#This Row],[FEVEREIRO]],Tabela373[[#This Row],[MARÇO]],Tabela373[[#This Row],[ABRIL]],Tabela373[[#This Row],[MAIO]],Tabela373[[#This Row],[JUNHO]],Tabela373[[#This Row],[JULHO]],Tabela373[[#This Row],[AGOSTO]],Tabela373[[#This Row],[SETEMBRO]],Tabela373[[#This Row],[OUTUBRO]],Tabela373[[#This Row],[NOVEMBRO]],Tabela373[[#This Row],[DEZEMBRO]]) -> #DIV/0!
A21: MARKETPLACE | C21: =IFERROR(B21/$B$3,"") | E21: =IFERROR(D21/$D$3,"") | F21: =IFERROR((D21-B21)/B21,"") | H21: =IFERROR(G21/$G$3,"") | I21: =IFERROR((G21-D21)/D21,"") | K21: =IFERROR(J21/$J$3,"") | L21: =IFERROR((J21-G21)/G21,"") | N21: =IFERROR(M21/$M$3,"") | O21: =IFERROR((M21-J21)/J21,"") | Q21: =IFERROR(P21/$P$3,"") | R21: =IFERROR((P21-M21)/M21,"") | T21: =IFERROR(S21/$S$3,"") | U21: =IFERROR((S21-P21)/P21,"") | W21: =IFERROR(V21/$V$3,"") | X21: =IFERROR((V21-S21)/S21,"") | Z21: =IFERROR(Y21/$Y$3,"") | AA21: =IFERROR((Y21-V21)/V21,"") | AC21: =IFERROR(AB21/$AB$3,"") | AD21: =IFERROR((AB21-Y21)/Y21,"") | AF21: =IFERROR(AE21/$AE$3,"") | AG21: =IFERROR((AE21-AB21)/AB21,"") | AI21: =IFERROR(AH21/$AH$3,"") | AJ21: =IFERROR((AH21-AE21)/AE21,"") | AK21: =SUM(Tabela373[[#This Row],[JANEIRO]]+Tabela373[[#This Row],[FEVEREIRO]]+Tabela373[[#This Row],[MARÇO]]+Tabela373[[#This Row],[ABRIL]]+Tabela373[[#This Row],[MAIO]]+Tabela373[[#This Row],[JUNHO]]+Tabela373[[#This Row],[JULHO]]+Tabela373[[#This Row],[AGOSTO]]+Tabela373[[#This Row],[SETEMBRO]]+Tabela373[[#This Row],[NOVEMBRO]]+Tabela373[[#This Row],[DEZEMBRO]]) -> 0 | AL21: =IFERROR(AK21/$AK$3,"") | AM21: =AVERAGE(Tabela373[[#This Row],[JANEIRO]],Tabela373[[#This Row],[FEVEREIRO]],Tabela373[[#This Row],[MARÇO]],Tabela373[[#This Row],[ABRIL]],Tabela373[[#This Row],[MAIO]],Tabela373[[#This Row],[JUNHO]],Tabela373[[#This Row],[JULHO]],Tabela373[[#This Row],[AGOSTO]],Tabela373[[#This Row],[SETEMBRO]],Tabela373[[#This Row],[OUTUBRO]],Tabela373[[#This Row],[NOVEMBRO]],Tabela373[[#This Row],[DEZEMBRO]]) -> #DIV/0!
A22: SITE PRÓPRIO | C22: =IFERROR(B22/$B$3,"") | E22: =IFERROR(D22/$D$3,"") | F22: =IFERROR((D22-B22)/B22,"") | H22: =IFERROR(G22/$G$3,"") | I22: =IFERROR((G22-D22)/D22,"") | K22: =IFERROR(J22/$J$3,"") | L22: =IFERROR((J22-G22)/G22,"") | N22: =IFERROR(M22/$M$3,"") | O22: =IFERROR((M22-J22)/J22,"") | Q22: =IFERROR(P22/$P$3,"") | R22: =IFERROR((P22-M22)/M22,"") | T22: =IFERROR(S22/$S$3,"") | U22: =IFERROR((S22-P22)/P22,"") | W22: =IFERROR(V22/$V$3,"") | X22: =IFERROR((V22-S22)/S22,"") | Z22: =IFERROR(Y22/$Y$3,"") | AA22: =IFERROR((Y22-V22)/V22,"") | AC22: =IFERROR(AB22/$AB$3,"") | AD22: =IFERROR((AB22-Y22)/Y22,"") | AF22: =IFERROR(AE22/$AE$3,"") | AG22: =IFERROR((AE22-AB22)/AB22,"") | AI22: =IFERROR(AH22/$AH$3,"") | AJ22: =IFERROR((AH22-AE22)/AE22,"") | AK22: =SUM(Tabela373[[#This Row],[JANEIRO]]+Tabela373[[#This Row],[FEVEREIRO]]+Tabela373[[#This Row],[MARÇO]]+Tabela373[[#This Row],[ABRIL]]+Tabela373[[#This Row],[MAIO]]+Tabela373[[#This Row],[JUNHO]]+Tabela373[[#This Row],[JULHO]]+Tabela373[[#This Row],[AGOSTO]]+Tabela373[[#This Row],[SETEMBRO]]+Tabela373[[#This Row],[NOVEMBRO]]+Tabela373[[#This Row],[DEZEMBRO]]) -> 0 | AL22: =IFERROR(AK22/$AK$3,"") | AM22: =AVERAGE(Tabela373[[#This Row],[JANEIRO]],Tabela373[[#This Row],[FEVEREIRO]],Tabela373[[#This Row],[MARÇO]],Tabela373[[#This Row],[ABRIL]],Tabela373[[#This Row],[MAIO]],Tabela373[[#This Row],[JUNHO]],Tabela373[[#This Row],[JULHO]],Tabela373[[#This Row],[AGOSTO]],Tabela373[[#This Row],[SETEMBRO]],Tabela373[[#This Row],[OUTUBRO]],Tabela373[[#This Row],[NOVEMBRO]],Tabela373[[#This Row],[DEZEMBRO]]) -> #DIV/0!
C23: =IFERROR(B23/$B$3,"") | E23: =IFERROR(D23/$D$3,"") | F23: =IFERROR((D23-B23)/B23,"") | H23: =IFERROR(G23/$G$3,"") | I23: =IFERROR((G23-D23)/D23,"") | K23: =IFERROR(J23/$J$3,"") | L23: =IFERROR((J23-G23)/G23,"") | N23: =IFERROR(M23/$M$3,"") | O23: =IFERROR((M23-J23)/J23,"") | Q23: =IFERROR(P23/$P$3,"") | R23: =IFERROR((P23-M23)/M23,"") | T23: =IFERROR(S23/$S$3,"") | U23: =IFERROR((S23-P23)/P23,"") | W23: =IFERROR(V23/$V$3,"") | X23: =IFERROR((V23-S23)/S23,"") | Z23: =IFERROR(Y23/$Y$3,"") | AA23: =IFERROR((Y23-V23)/V23,"") | AC23: =IFERROR(AB23/$AB$3,"") | AD23: =IFERROR((AB23-Y23)/Y23,"") | AF23: =IFERROR(AE23/$AE$3,"") | AG23: =IFERROR((AE23-AB23)/AB23,"") | AI23: =IFERROR(AH23/$AH$3,"") | AJ23: =IFERROR((AH23-AE23)/AE23,"") | AK23: =SUM(Tabela373[[#This Row],[JANEIRO]]+Tabela373[[#This Row],[FEVEREIRO]]+Tabela373[[#This Row],[MARÇO]]+Tabela373[[#This Row],[ABRIL]]+Tabela373[[#This Row],[MAIO]]+Tabela373[[#This Row],[JUNHO]]+Tabela373[[#This Row],[JULHO]]+Tabela373[[#This Row],[AGOSTO]]+Tabela373[[#This Row],[SETEMBRO]]+Tabela373[[#This Row],[NOVEMBRO]]+Tabela373[[#This Row],[DEZEMBRO]]) -> 0 | AL23: =IFERROR(AK23/$AK$3,"") | AM23: =AVERAGE(Tabela373[[#This Row],[JANEIRO]],Tabela373[[#This Row],[FEVEREIRO]],Tabela373[[#This Row],[MARÇO]],Tabela373[[#This Row],[ABRIL]],Tabela373[[#This Row],[MAIO]],Tabela373[[#This Row],[JUNHO]],Tabela373[[#This Row],[JULHO]],Tabela373[[#This Row],[AGOSTO]],Tabela373[[#This Row],[SETEMBRO]],Tabela373[[#This Row],[OUTUBRO]],Tabela373[[#This Row],[NOVEMBRO]],Tabela373[[#This Row],[DEZEMBRO]]) -> #DIV/0!
A24: FORMA DE VENDA | B24: =SUM(B25:B27) -> 0 | C24: =IFERROR(B24/$B$3,"") | D24: =SUM(D25:D27) -> 0 | E24: =IFERROR(D24/$D$3,"") | F24: =IFERROR((D24-B24)/B24,"") | G24: =SUM(G25:G27) -> 0 | H24: =IFERROR(G24/$G$3,"") | I24: =IFERROR((G24-D24)/D24,"") | J24: =SUM(J25:J27) -> 0 | K24: =IFERROR(J24/$J$3,"") | L24: =IFERROR((J24-G24)/G24,"") | M24: =SUM(M25:M27) -> 0 | N24: =IFERROR(M24/$M$3,"") | O24: =IFERROR((M24-J24)/J24,"") | P24: =SUM(P25:P27) -> 0 | Q24: =IFERROR(P24/$P$3,"") | R24: =IFERROR((P24-M24)/M24,"") | S24: =SUM(S25:S27) -> 0 | T24: =IFERROR(S24/$S$3,"") | U24: =IFERROR((S24-P24)/P24,"") | V24: =SUM(V25:V27) -> 0 | W24: =IFERROR(V24/$V$3,"") | X24: =IFERROR((V24-S24)/S24,"") | Y24: =SUM(Y25:Y27) -> 0 | Z24: =IFERROR(Y24/$Y$3,"") | AA24: =IFERROR((Y24-V24)/V24,"") | AB24: =SUM(AB25:AB27) -> 0 | AC24: =IFERROR(AB24/$AB$3,"") | AD24: =IFERROR((AB24-Y24)/Y24,"") | AE24: =SUM(AE25:AE27) -> 0 | AF24: =IFERROR(AE24/$AE$3,"") | AG24: =IFERROR((AE24-AB24)/AB24,"") | AH24: =SUM(AH25:AH27) -> 0 | AI24: =IFERROR(AH24/$AH$3,"") | AJ24: =IFERROR((AH24-AE24)/AE24,"") | AK24: =SUM(Tabela373[[#This Row],[JANEIRO]]+Tabela373[[#This Row],[FEVEREIRO]]+Tabela373[[#This Row],[MARÇO]]+Tabela373[[#This Row],[ABRIL]]+Tabela373[[#This Row],[MAIO]]+Tabela373[[#This Row],[JUNHO]]+Tabela373[[#This Row],[JULHO]]+Tabela373[[#This Row],[AGOSTO]]+Tabela373[[#This Row],[SETEMBRO]]+Tabela373[[#This Row],[NOVEMBRO]]+Tabela373[[#This Row],[DEZEMBRO]]) -> 0 | AL24: =IFERROR(AK24/$AK$3,"") | AM24: =AVERAGE(Tabela373[[#This Row],[JANEIRO]],Tabela373[[#This Row],[FEVEREIRO]],Tabela373[[#This Row],[MARÇO]],Tabela373[[#This Row],[ABRIL]],Tabela373[[#This Row],[MAIO]],Tabela373[[#This Row],[JUNHO]],Tabela373[[#This Row],[JULHO]],Tabela373[[#This Row],[AGOSTO]],Tabela373[[#This Row],[SETEMBRO]],Tabela373[[#This Row],[OUTUBRO]],Tabela373[[#This Row],[NOVEMBRO]],Tabela373[[#This Row],[DEZEMBRO]]) -> 0
A25: ATACADO | C25: =IFERROR(B25/$B$3,"") | E25: =IFERROR(D25/$D$3,"") | F25: =IFERROR((D25-B25)/B25,"") | H25: =IFERROR(G25/$G$3,"") | I25: =IFERROR((G25-D25)/D25,"") | K25: =IFERROR(J25/$J$3,"") | L25: =IFERROR((J25-G25)/G25,"") | N25: =IFERROR(M25/$M$3,"") | O25: =IFERROR((M25-J25)/J25,"") | Q25: =IFERROR(P25/$P$3,"") | R25: =IFERROR((P25-M25)/M25,"") | T25: =IFERROR(S25/$S$3,"") | U25: =IFERROR((S25-P25)/P25,"") | W25: =IFERROR(V25/$V$3,"") | X25: =IFERROR((V25-S25)/S25,"") | Z25: =IFERROR(Y25/$Y$3,"") | AA25: =IFERROR((Y25-V25)/V25,"") | AC25: =IFERROR(AB25/$AB$3,"") | AD25: =IFERROR((AB25-Y25)/Y25,"") | AF25: =IFERROR(AE25/$AE$3,"") | AG25: =IFERROR((AE25-AB25)/AB25,"") | AI25: =IFERROR(AH25/$AH$3,"") | AJ25: =IFERROR((AH25-AE25)/AE25,"") | AK25: =SUM(Tabela373[[#This Row],[JANEIRO]]+Tabela373[[#This Row],[FEVEREIRO]]+Tabela373[[#This Row],[MARÇO]]+Tabela373[[#This Row],[ABRIL]]+Tabela373[[#This Row],[MAIO]]+Tabela373[[#This Row],[JUNHO]]+Tabela373[[#This Row],[JULHO]]+Tabela373[[#This Row],[AGOSTO]]+Tabela373[[#This Row],[SETEMBRO]]+Tabela373[[#This Row],[NOVEMBRO]]+Tabela373[[#This Row],[DEZEMBRO]]) -> 0 | AL25: =IFERROR(AK25/$AK$3,"") | AM25: =AVERAGE(Tabela373[[#This Row],[JANEIRO]],Tabela373[[#This Row],[FEVEREIRO]],Tabela373[[#This Row],[MARÇO]],Tabela373[[#This Row],[ABRIL]],Tabela373[[#This Row],[MAIO]],Tabela373[[#This Row],[JUNHO]],Tabela373[[#This Row],[JULHO]],Tabela373[[#This Row],[AGOSTO]],Tabela373[[#This Row],[SETEMBRO]],Tabela373[[#This Row],[OUTUBRO]],Tabela373[[#This Row],[NOVEMBRO]],Tabela373[[#This Row],[DEZEMBRO]]) -> #DIV/0!
A26: VAREJO | C26: =IFERROR(B26/$B$3,"") | E26: =IFERROR(D26/$D$3,"") | F26: =IFERROR((D26-B26)/B26,"") | H26: =IFERROR(G26/$G$3,"") | I26: =IFERROR((G26-D26)/D26,"") | K26: =IFERROR(J26/$J$3,"") | L26: =IFERROR((J26-G26)/G26,"") | N26: =IFERROR(M26/$M$3,"") | O26: =IFERROR((M26-J26)/J26,"") | Q26: =IFERROR(P26/$P$3,"") | R26: =IFERROR((P26-M26)/M26,"") | T26: =IFERROR(S26/$S$3,"") | U26: =IFERROR((S26-P26)/P26,"") | W26: =IFERROR(V26/$V$3,"") | X26: =IFERROR((V26-S26)/S26,"") | Z26: =IFERROR(Y26/$Y$3,"") | AA26: =IFERROR((Y26-V26)/V26,"") | AC26: =IFERROR(AB26/$AB$3,"") | AD26: =IFERROR((AB26-Y26)/Y26,"") | AF26: =IFERROR(AE26/$AE$3,"") | AG26: =IFERROR((AE26-AB26)/AB26,"") | AI26: =IFERROR(AH26/$AH$3,"") | AJ26: =IFERROR((AH26-AE26)/AE26,"") | AK26: =SUM(Tabela373[[#This Row],[JANEIRO]]+Tabela373[[#This Row],[FEVEREIRO]]+Tabela373[[#This Row],[MARÇO]]+Tabela373[[#This Row],[ABRIL]]+Tabela373[[#This Row],[MAIO]]+Tabela373[[#This Row],[JUNHO]]+Tabela373[[#This Row],[JULHO]]+Tabela373[[#This Row],[AGOSTO]]+Tabela373[[#This Row],[SETEMBRO]]+Tabela373[[#This Row],[NOVEMBRO]]+Tabela373[[#This Row],[DEZEMBRO]]) -> 0 | AL26: =IFERROR(AK26/$AK$3,"") | AM26: =AVERAGE(Tabela373[[#This Row],[JANEIRO]],Tabela373[[#This Row],[FEVEREIRO]],Tabela373[[#This Row],[MARÇO]],Tabela373[[#This Row],[ABRIL]],Tabela373[[#This Row],[MAIO]],Tabela373[[#This Row],[JUNHO]],Tabela373[[#This Row],[JULHO]],Tabela373[[#This Row],[AGOSTO]],Tabela373[[#This Row],[SETEMBRO]],Tabela373[[#This Row],[OUTUBRO]],Tabela373[[#This Row],[NOVEMBRO]],Tabela373[[#This Row],[DEZEMBRO]]) -> #DIV/0!
C27: =IFERROR(B27/$B$3,"") | E27: =IFERROR(D27/$D$3,"") | F27: =IFERROR((D27-B27)/B27,"") | H27: =IFERROR(G27/$G$3,"") | I27: =IFERROR((G27-D27)/D27,"") | K27: =IFERROR(J27/$J$3,"") | L27: =IFERROR((J27-G27)/G27,"") | N27: =IFERROR(M27/$M$3,"") | O27: =IFERROR((M27-J27)/J27,"") | Q27: =IFERROR(P27/$P$3,"") | R27: =IFERROR((P27-M27)/M27,"") | T27: =IFERROR(S27/$S$3,"") | U27: =IFERROR((S27-P27)/P27,"") | W27: =IFERROR(V27/$V$3,"") | X27: =IFERROR((V27-S27)/S27,"") | Z27: =IFERROR(Y27/$Y$3,"") | AA27: =IFERROR((Y27-V27)/V27,"") | AC27: =IFERROR(AB27/$AB$3,"") | AD27: =IFERROR((AB27-Y27)/Y27,"") | AF27: =IFERROR(AE27/$AE$3,"") | AG27: =IFERROR((AE27-AB27)/AB27,"") | AI27: =IFERROR(AH27/$AH$3,"") | AJ27: =IFERROR((AH27-AE27)/AE27,"") | AK27: =SUM(Tabela373[[#This Row],[JANEIRO]]+Tabela373[[#This Row],[FEVEREIRO]]+Tabela373[[#This Row],[MARÇO]]+Tabela373[[#This Row],[ABRIL]]+Tabela373[[#This Row],[MAIO]]+Tabela373[[#This Row],[JUNHO]]+Tabela373[[#This Row],[JULHO]]+Tabela373[[#This Row],[AGOSTO]]+Tabela373[[#This Row],[SETEMBRO]]+Tabela373[[#This Row],[NOVEMBRO]]+Tabela373[[#This Row],[DEZEMBRO]]) -> 0 | AL27: =IFERROR(AK27/$AK$3,"") | AM27: =AVERAGE(Tabela373[[#This Row],[JANEIRO]],Tabela373[[#This Row],[FEVEREIRO]],Tabela373[[#This Row],[MARÇO]],Tabela373[[#This Row],[ABRIL]],Tabela373[[#This Row],[MAIO]],Tabela373[[#This Row],[JUNHO]],Tabela373[[#This Row],[JULHO]],Tabela373[[#This Row],[AGOSTO]],Tabela373[[#This Row],[SETEMBRO]],Tabela373[[#This Row],[OUTUBRO]],Tabela373[[#This Row],[NOVEMBRO]],Tabela373[[#This Row],[DEZEMBRO]]) -> #DIV/0!
A28: RECEITAS DIVERSAS | B28: =SUM(B29:B30) -> 0 | C28: =IFERROR(B28/$B$3,"") | D28: =SUM(D29:D30) -> 0 | E28: =IFERROR(D28/$D$3,"") | F28: =IFERROR((D28-B28)/B28,"") | G28: =SUM(G29:G30) -> 0 | H28: =IFERROR(G28/$G$3,"") | I28: =IFERROR((G28-D28)/D28,"") | J28: =SUM(J29:J30) -> 0 | K28: =IFERROR(J28/$J$3,"") | L28: =IFERROR((J28-G28)/G28,"") | M28: =SUM(M29:M30) -> 0 | N28: =IFERROR(M28/$M$3,"") | O28: =IFERROR((M28-J28)/J28,"") | P28: =SUM(P29:P30) -> 0 | Q28: =IFERROR(P28/$P$3,"") | R28: =IFERROR((P28-M28)/M28,"") | S28: =SUM(S29:S30) -> 0 | T28: =IFERROR(S28/$S$3,"") | U28: =IFERROR((S28-P28)/P28,"") | V28: =SUM(V29:V30) -> 0 | W28: =IFERROR(V28/$V$3,"") | X28: =IFERROR((V28-S28)/S28,"") | Y28: =SUM(Y29:Y30) -> 0 | Z28: =IFERROR(Y28/$Y$3,"") | AA28: =IFERROR((Y28-V28)/V28,"") | AB28: =SUM(AB29:AB30) -> 0 | AC28: =IFERROR(AB28/$AB$3,"") | AD28: =IFERROR((AB28-Y28)/Y28,"") | AE28: =SUM(AE29:AE30) -> 0 | AF28: =IFERROR(AE28/$AE$3,"") | AG28: =IFERROR((AE28-AB28)/AB28,"") | AH28: =SUM(AH29:AH30) -> 0 | AI28: =IFERROR(AH28/$AH$3,"") | AJ28: =IFERROR((AH28-AE28)/AE28,"") | AK28: =SUM(Tabela373[[#This Row],[JANEIRO]]+Tabela373[[#This Row],[FEVEREIRO]]+Tabela373[[#This Row],[MARÇO]]+Tabela373[[#This Row],[ABRIL]]+Tabela373[[#This Row],[MAIO]]+Tabela373[[#This Row],[JUNHO]]+Tabela373[[#This Row],[JULHO]]+Tabela373[[#This Row],[AGOSTO]]+Tabela373[[#This Row],[SETEMBRO]]+Tabela373[[#This Row],[NOVEMBRO]]+Tabela373[[#This Row],[DEZEMBRO]]) -> 0 | AL28: =IFERROR(AK28/$AK$3,"") | AM28: =AVERAGE(Tabela373[[#This Row],[JANEIRO]],Tabela373[[#This Row],[FEVEREIRO]],Tabela373[[#This Row],[MARÇO]],Tabela373[[#This Row],[ABRIL]],Tabela373[[#This Row],[MAIO]],Tabela373[[#This Row],[JUNHO]],Tabela373[[#This Row],[JULHO]],Tabela373[[#This Row],[AGOSTO]],Tabela373[[#This Row],[SETEMBRO]],Tabela373[[#This Row],[OUTUBRO]],Tabela373[[#This Row],[NOVEMBRO]],Tabela373[[#This Row],[DEZEMBRO]]) -> 0
A29: RECEITAS DE VENDAS DIVERSAS | C29: =IFERROR(B29/$B$3,"") | E29: =IFERROR(D29/$D$3,"") | F29: =IFERROR((D29-B29)/B29,"") | H29: =IFERROR(G29/$G$3,"") | I29: =IFERROR((G29-D29)/D29,"") | K29: =IFERROR(J29/$J$3,"") | L29: =IFERROR((J29-G29)/G29,"") | N29: =IFERROR(M29/$M$3,"") | O29: =IFERROR((M29-J29)/J29,"") | Q29: =IFERROR(P29/$P$3,"") | R29: =IFERROR((P29-M29)/M29,"") | T29: =IFERROR(S29/$S$3,"") | U29: =IFERROR((S29-P29)/P29,"") | W29: =IFERROR(V29/$V$3,"") | X29: =IFERROR((V29-S29)/S29,"") | Z29: =IFERROR(Y29/$Y$3,"") | AA29: =IFERROR((Y29-V29)/V29,"") | AC29: =IFERROR(AB29/$AB$3,"") | AD29: =IFERROR((AB29-Y29)/Y29,"") | AF29: =IFERROR(AE29/$AE$3,"") | AG29: =IFERROR((AE29-AB29)/AB29,"") | AI29: =IFERROR(AH29/$AH$3,"") | AJ29: =IFERROR((AH29-AE29)/AE29,"") | AK29: =SUM(Tabela373[[#This Row],[JANEIRO]]+Tabela373[[#This Row],[FEVEREIRO]]+Tabela373[[#This Row],[MARÇO]]+Tabela373[[#This Row],[ABRIL]]+Tabela373[[#This Row],[MAIO]]+Tabela373[[#This Row],[JUNHO]]+Tabela373[[#This Row],[JULHO]]+Tabela373[[#This Row],[AGOSTO]]+Tabela373[[#This Row],[SETEMBRO]]+Tabela373[[#This Row],[NOVEMBRO]]+Tabela373[[#This Row],[DEZEMBRO]]) -> 0 | AL29: =IFERROR(AK29/$AK$3,"") | AM29: =AVERAGE(Tabela373[[#This Row],[JANEIRO]],Tabela373[[#This Row],[FEVEREIRO]],Tabela373[[#This Row],[MARÇO]],Tabela373[[#This Row],[ABRIL]],Tabela373[[#This Row],[MAIO]],Tabela373[[#This Row],[JUNHO]],Tabela373[[#This Row],[JULHO]],Tabela373[[#This Row],[AGOSTO]],Tabela373[[#This Row],[SETEMBRO]],Tabela373[[#This Row],[OUTUBRO]],Tabela373[[#This Row],[NOVEMBRO]],Tabela373[[#This Row],[DEZEMBRO]]) -> #DIV/0!
C30: =IFERROR(B30/$B$3,"") | E30: =IFERROR(D30/$D$3,"") | F30: =IFERROR((D30-B30)/B30,"") | H30: =IFERROR(G30/$G$3,"") | I30: =IFERROR((G30-D30)/D30,"") | K30: =IFERROR(J30/$J$3,"") | L30: =IFERROR((J30-G30)/G30,"") | N30: =IFERROR(M30/$M$3,"") | O30: =IFERROR((M30-J30)/J30,"") | Q30: =IFERROR(P30/$P$3,"") | R30: =IFERROR((P30-M30)/M30,"") | T30: =IFERROR(S30/$S$3,"") | U30: =IFERROR((S30-P30)/P30,"") | W30: =IFERROR(V30/$V$3,"") | X30: =IFERROR((V30-S30)/S30,"") | Z30: =IFERROR(Y30/$Y$3,"") | AA30: =IFERROR((Y30-V30)/V30,"") | AC30: =IFERROR(AB30/$AB$3,"") | AD30: =IFERROR((AB30-Y30)/Y30,"") | AF30: =IFERROR(AE30/$AE$3,"") | AG30: =IFERROR((AE30-AB30)/AB30,"") | AI30: =IFERROR(AH30/$AH$3,"") | AJ30: =IFERROR((AH30-AE30)/AE30,"") | AK30: =SUM(Tabela373[[#This Row],[JANEIRO]]+Tabela373[[#This Row],[FEVEREIRO]]+Tabela373[[#This Row],[MARÇO]]+Tabela373[[#This Row],[ABRIL]]+Tabela373[[#This Row],[MAIO]]+Tabela373[[#This Row],[JUNHO]]+Tabela373[[#This Row],[JULHO]]+Tabela373[[#This Row],[AGOSTO]]+Tabela373[[#This Row],[SETEMBRO]]+Tabela373[[#This Row],[NOVEMBRO]]+Tabela373[[#This Row],[DEZEMBRO]]) -> 0 | AL30: =IFERROR(AK30/$AK$3,"") | AM30: =AVERAGE(Tabela373[[#This Row],[JANEIRO]],Tabela373[[#This Row],[FEVEREIRO]],Tabela373[[#This Row],[MARÇO]],Tabela373[[#This Row],[ABRIL]],Tabela373[[#This Row],[MAIO]],Tabela373[[#This Row],[JUNHO]],Tabela373[[#This Row],[JULHO]],Tabela373[[#This Row],[AGOSTO]],Tabela373[[#This Row],[SETEMBRO]],Tabela373[[#This Row],[OUTUBRO]],Tabela373[[#This Row],[NOVEMBRO]],Tabela373[[#This Row],[DEZEMBRO]]) -> #DIV/0!
A31: (-) DEDUÇÕES | B31: =B32+B39 -> 0 | C31: =IFERROR(B31/$B$3,"") | D31: =D32+D39 -> 0 | E31: =IFERROR(D31/$D$3,"") | F31: =IFERROR((D31-B31)/B31,"") | G31: =G32+G39 -> 0 | H31: =IFERROR(G31/$G$3,"") | I31: =IFERROR((G31-D31)/D31,"") | J31: =J32+J39 -> 0 | K31: =IFERROR(J31/$J$3,"") | L31: =IFERROR((J31-G31)/G31,"") | M31: =M32+M39 -> 0 | N31: =IFERROR(M31/$M$3,"") | O31: =IFERROR((M31-J31)/J31,"") | P31: =P32+P39 -> 0 | Q31: =IFERROR(P31/$P$3,"") | R31: =IFERROR((P31-M31)/M31,"") | S31: =S32+S39 -> 0 | T31: =IFERROR(S31/$S$3,"") | U31: =IFERROR((S31-P31)/P31,"") | V31: =V32+V39 -> 0 | W31: =IFERROR(V31/$V$3,"") | X31: =IFERROR((V31-S31)/S31,"") | Y31: =Y32+Y39 -> 0 | Z31: =IFERROR(Y31/$Y$3,"") | AA31: =IFERROR((Y31-V31)/V31,"") | AB31: =AB32+AB39 -> 0 | AC31: =IFERROR(AB31/$AB$3,"") | AD31: =IFERROR((AB31-Y31)/Y31,"") | AE31: =AE32+AE39 -> 0 | AF31: =IFERROR(AE31/$AE$3,"") | AG31: =IFERROR((AE31-AB31)/AB31,"") | AH31: =AH32+AH39 -> 0 | AI31: =IFERROR(AH31/$AH$3,"") | AJ31: =IFERROR((AH31-AE31)/AE31,"") | AK31: =SUM(Tabela373[[#This Row],[JANEIRO]]+Tabela373[[#This Row],[FEVEREIRO]]+Tabela373[[#This Row],[MARÇO]]+Tabela373[[#This Row],[ABRIL]]+Tabela373[[#This Row],[MAIO]]+Tabela373[[#This Row],[JUNHO]]+Tabela373[[#This Row],[JULHO]]+Tabela373[[#This Row],[AGOSTO]]+Tabela373[[#This Row],[SETEMBRO]]+Tabela373[[#This Row],[NOVEMBRO]]+Tabela373[[#This Row],[DEZEMBRO]]) -> 0 | AL31: =IFERROR(AK31/$AK$3,"") | AM31: =AVERAGE(Tabela373[[#This Row],[JANEIRO]],Tabela373[[#This Row],[FEVEREIRO]],Tabela373[[#This Row],[MARÇO]],Tabela373[[#This Row],[ABRIL]],Tabela373[[#This Row],[MAIO]],Tabela373[[#This Row],[JUNHO]],Tabela373[[#This Row],[JULHO]],Tabela373[[#This Row],[AGOSTO]],Tabela373[[#This Row],[SETEMBRO]],Tabela373[[#This Row],[OUTUBRO]],Tabela373[[#This Row],[NOVEMBRO]],Tabela373[[#This Row],[DEZEMBRO]]) -> 0
A32: IMPOSTOS S/VENDAS | B32: =SUM(B33:B38) -> 0 | C32: =IFERROR(B32/$B$3,"") | D32: =SUM(D33:D38) -> 0 | E32: =IFERROR(D32/$D$3,"") | F32: =IFERROR((D32-B32)/B32,"") | G32: =SUM(G33:G38) -> 0 | H32: =IFERROR(G32/$G$3,"") | I32: =IFERROR((G32-D32)/D32,"") | J32: =SUM(J33:J38) -> 0 | K32: =IFERROR(J32/$J$3,"") | L32: =IFERROR((J32-G32)/G32,"") | M32: =SUM(M33:M38) -> 0 | N32: =IFERROR(M32/$M$3,"") | O32: =IFERROR((M32-J32)/J32,"") | P32: =SUM(P33:P38) -> 0 | Q32: =IFERROR(P32/$P$3,"") | R32: =IFERROR((P32-M32)/M32,"") | S32: =SUM(S33:S38) -> 0 | T32: =IFERROR(S32/$S$3,"") | U32: =IFERROR((S32-P32)/P32,"") | V32: =SUM(V33:V38) -> 0 | W32: =IFERROR(V32/$V$3,"") | X32: =IFERROR((V32-S32)/S32,"") | Y32: =SUM(Y33:Y38) -> 0 | Z32: =IFERROR(Y32/$Y$3,"") | AA32: =IFERROR((Y32-V32)/V32,"") | AB32: =SUM(AB33:AB38) -> 0 | AC32: =IFERROR(AB32/$AB$3,"") | AD32: =IFERROR((AB32-Y32)/Y32,"") | AE32: =SUM(AE33:AE38) -> 0 | AF32: =IFERROR(AE32/$AE$3,"") | AG32: =IFERROR((AE32-AB32)/AB32,"") | AH32: =SUM(AH33:AH38) -> 0 | AI32: =IFERROR(AH32/$AH$3,"") | AJ32: =IFERROR((AH32-AE32)/AE32,"") | AK32: =SUM(Tabela373[[#This Row],[JANEIRO]]+Tabela373[[#This Row],[FEVEREIRO]]+Tabela373[[#This Row],[MARÇO]]+Tabela373[[#This Row],[ABRIL]]+Tabela373[[#This Row],[MAIO]]+Tabela373[[#This Row],[JUNHO]]+Tabela373[[#This Row],[JULHO]]+Tabela373[[#This Row],[AGOSTO]]+Tabela373[[#This Row],[SETEMBRO]]+Tabela373[[#This Row],[NOVEMBRO]]+Tabela373[[#This Row],[DEZEMBRO]]) -> 0 | AL32: =IFERROR(AK32/$AK$3,"") | AM32: =AVERAGE(Tabela373[[#This Row],[JANEIRO]],Tabela373[[#This Row],[FEVEREIRO]],Tabela373[[#This Row],[MARÇO]],Tabela373[[#This Row],[ABRIL]],Tabela373[[#This Row],[MAIO]],Tabela373[[#This Row],[JUNHO]],Tabela373[[#This Row],[JULHO]],Tabela373[[#This Row],[AGOSTO]],Tabela373[[#This Row],[SETEMBRO]],Tabela373[[#This Row],[OUTUBRO]],Tabela373[[#This Row],[NOVEMBRO]],Tabela373[[#This Row],[DEZEMBRO]]) -> 0
A33: ICMS S/VENDAS | C33: =IFERROR(B33/$B$3,"") | E33: =IFERROR(D33/$D$3,"") | F33: =IFERROR((D33-B33)/B33,"") | H33: =IFERROR(G33/$G$3,"") | I33: =IFERROR((G33-D33)/D33,"") | K33: =IFERROR(J33/$J$3,"") | L33: =IFERROR((J33-G33)/G33,"") | N33: =IFERROR(M33/$M$3,"") | O33: =IFERROR((M33-J33)/J33,"") | Q33: =IFERROR(P33/$P$3,"") | R33: =IFERROR((P33-M33)/M33,"") | T33: =IFERROR(S33/$S$3,"") | U33: =IFERROR((S33-P33)/P33,"") | W33: =IFERROR(V33/$V$3,"") | X33: =IFERROR((V33-S33)/S33,"") | Z33: =IFERROR(Y33/$Y$3,"") | AA33: =IFERROR((Y33-V33)/V33,"") | AC33: =IFERROR(AB33/$AB$3,"") | AD33: =IFERROR((AB33-Y33)/Y33,"") | AF33: =IFERROR(AE33/$AE$3,"") | AG33: =IFERROR((AE33-AB33)/AB33,"") | AI33: =IFERROR(AH33/$AH$3,"") | AJ33: =IFERROR((AH33-AE33)/AE33,"") | AK33: =SUM(Tabela373[[#This Row],[JANEIRO]]+Tabela373[[#This Row],[FEVEREIRO]]+Tabela373[[#This Row],[MARÇO]]+Tabela373[[#This Row],[ABRIL]]+Tabela373[[#This Row],[MAIO]]+Tabela373[[#This Row],[JUNHO]]+Tabela373[[#This Row],[JULHO]]+Tabela373[[#This Row],[AGOSTO]]+Tabela373[[#This Row],[SETEMBRO]]+Tabela373[[#This Row],[NOVEMBRO]]+Tabela373[[#This Row],[DEZEMBRO]]) -> 0 | AL33: =IFERROR(AK33/$AK$3,"") | AM33: =AVERAGE(Tabela373[[#This Row],[JANEIRO]],Tabela373[[#This Row],[FEVEREIRO]],Tabela373[[#This Row],[MARÇO]],Tabela373[[#This Row],[ABRIL]],Tabela373[[#This Row],[MAIO]],Tabela373[[#This Row],[JUNHO]],Tabela373[[#This Row],[JULHO]],Tabela373[[#This Row],[AGOSTO]],Tabela373[[#This Row],[SETEMBRO]],Tabela373[[#This Row],[OUTUBRO]],Tabela373[[#This Row],[NOVEMBRO]],Tabela373[[#This Row],[DEZEMBRO]]) -> #DIV/0!
A34: ISS S/VENDAS | C34: =IFERROR(B34/$B$3,"") | E34: =IFERROR(D34/$D$3,"") | F34: =IFERROR((D34-B34)/B34,"") | H34: =IFERROR(G34/$G$3,"") | I34: =IFERROR((G34-D34)/D34,"") | K34: =IFERROR(J34/$J$3,"") | L34: =IFERROR((J34-G34)/G34,"") | N34: =IFERROR(M34/$M$3,"") | O34: =IFERROR((M34-J34)/J34,"") | Q34: =IFERROR(P34/$P$3,"") | R34: =IFERROR((P34-M34)/M34,"") | T34: =IFERROR(S34/$S$3,"") | U34: =IFERROR((S34-P34)/P34,"") | W34: =IFERROR(V34/$V$3,"") | X34: =IFERROR((V34-S34)/S34,"") | Z34: =IFERROR(Y34/$Y$3,"") | AA34: =IFERROR((Y34-V34)/V34,"") | AC34: =IFERROR(AB34/$AB$3,"") | AD34: =IFERROR((AB34-Y34)/Y34,"") | AF34: =IFERROR(AE34/$AE$3,"") | AG34: =IFERROR((AE34-AB34)/AB34,"") | AI34: =IFERROR(AH34/$AH$3,"") | AJ34: =IFERROR((AH34-AE34)/AE34,"") | AK34: =SUM(Tabela373[[#This Row],[JANEIRO]]+Tabela373[[#This Row],[FEVEREIRO]]+Tabela373[[#This Row],[MARÇO]]+Tabela373[[#This Row],[ABRIL]]+Tabela373[[#This Row],[MAIO]]+Tabela373[[#This Row],[JUNHO]]+Tabela373[[#This Row],[JULHO]]+Tabela373[[#This Row],[AGOSTO]]+Tabela373[[#This Row],[SETEMBRO]]+Tabela373[[#This Row],[NOVEMBRO]]+Tabela373[[#This Row],[DEZEMBRO]]) -> 0 | AL34: =IFERROR(AK34/$AK$3,"") | AM34: =AVERAGE(Tabela373[[#This Row],[JANEIRO]],Tabela373[[#This Row],[FEVEREIRO]],Tabela373[[#This Row],[MARÇO]],Tabela373[[#This Row],[ABRIL]],Tabela373[[#This Row],[MAIO]],Tabela373[[#This Row],[JUNHO]],Tabela373[[#This Row],[JULHO]],Tabela373[[#This Row],[AGOSTO]],Tabela373[[#This Row],[SETEMBRO]],Tabela373[[#This Row],[OUTUBRO]],Tabela373[[#This Row],[NOVEMBRO]],Tabela373[[#This Row],[DEZEMBRO]]) -> #DIV/0!
A35: PIS S/VENDAS | C35: =IFERROR(B35/$B$3,"") | E35: =IFERROR(D35/$D$3,"") | F35: =IFERROR((D35-B35)/B35,"") | H35: =IFERROR(G35/$G$3,"") | I35: =IFERROR((G35-D35)/D35,"") | K35: =IFERROR(J35/$J$3,"") | L35: =IFERROR((J35-G35)/G35,"") | N35: =IFERROR(M35/$M$3,"") | O35: =IFERROR((M35-J35)/J35,"") | Q35: =IFERROR(P35/$P$3,"") | R35: =IFERROR((P35-M35)/M35,"") | T35: =IFERROR(S35/$S$3,"") | U35: =IFERROR((S35-P35)/P35,"") | W35: =IFERROR(V35/$V$3,"") | X35: =IFERROR((V35-S35)/S35,"") | Z35: =IFERROR(Y35/$Y$3,"") | AA35: =IFERROR((Y35-V35)/V35,"") | AC35: =IFERROR(AB35/$AB$3,"") | AD35: =IFERROR((AB35-Y35)/Y35,"") | AF35: =IFERROR(AE35/$AE$3,"") | AG35: =IFERROR((AE35-AB35)/AB35,"") | AI35: =IFERROR(AH35/$AH$3,"") | AJ35: =IFERROR((AH35-AE35)/AE35,"") | AK35: =SUM(Tabela373[[#This Row],[JANEIRO]]+Tabela373[[#This Row],[FEVEREIRO]]+Tabela373[[#This Row],[MARÇO]]+Tabela373[[#This Row],[ABRIL]]+Tabela373[[#This Row],[MAIO]]+Tabela373[[#This Row],[JUNHO]]+Tabela373[[#This Row],[JULHO]]+Tabela373[[#This Row],[AGOSTO]]+Tabela373[[#This Row],[SETEMBRO]]+Tabela373[[#This Row],[NOVEMBRO]]+Tabela373[[#This Row],[DEZEMBRO]]) -> 0 | AL35: =IFERROR(AK35/$AK$3,"") | AM35: =AVERAGE(Tabela373[[#This Row],[JANEIRO]],Tabela373[[#This Row],[FEVEREIRO]],Tabela373[[#This Row],[MARÇO]],Tabela373[[#This Row],[ABRIL]],Tabela373[[#This Row],[MAIO]],Tabela373[[#This Row],[JUNHO]],Tabela373[[#This Row],[JULHO]],Tabela373[[#This Row],[AGOSTO]],Tabela373[[#This Row],[SETEMBRO]],Tabela373[[#This Row],[OUTUBRO]],Tabela373[[#This Row],[NOVEMBRO]],Tabela373[[#This Row],[DEZEMBRO]]) -> #DIV/0!
A36: COFINS S/VENDAS | C36: =IFERROR(B36/$B$3,"") | E36: =IFERROR(D36/$D$3,"") | F36: =IFERROR((D36-B36)/B36,"") | H36: =IFERROR(G36/$G$3,"") | I36: =IFERROR((G36-D36)/D36,"") | K36: =IFERROR(J36/$J$3,"") | L36: =IFERROR((J36-G36)/G36,"") | N36: =IFERROR(M36/$M$3,"") | O36: =IFERROR((M36-J36)/J36,"") | Q36: =IFERROR(P36/$P$3,"") | R36: =IFERROR((P36-M36)/M36,"") | T36: =IFERROR(S36/$S$3,"") | U36: =IFERROR((S36-P36)/P36,"") | W36: =IFERROR(V36/$V$3,"") | X36: =IFERROR((V36-S36)/S36,"") | Z36: =IFERROR(Y36/$Y$3,"") | AA36: =IFERROR((Y36-V36)/V36,"") | AC36: =IFERROR(AB36/$AB$3,"") | AD36: =IFERROR((AB36-Y36)/Y36,"") | AF36: =IFERROR(AE36/$AE$3,"") | AG36: =IFERROR((AE36-AB36)/AB36,"") | AI36: =IFERROR(AH36/$AH$3,"") | AJ36: =IFERROR((AH36-AE36)/AE36,"") | AK36: =SUM(Tabela373[[#This Row],[JANEIRO]]+Tabela373[[#This Row],[FEVEREIRO]]+Tabela373[[#This Row],[MARÇO]]+Tabela373[[#This Row],[ABRIL]]+Tabela373[[#This Row],[MAIO]]+Tabela373[[#This Row],[JUNHO]]+Tabela373[[#This Row],[JULHO]]+Tabela373[[#This Row],[AGOSTO]]+Tabela373[[#This Row],[SETEMBRO]]+Tabela373[[#This Row],[NOVEMBRO]]+Tabela373[[#This Row],[DEZEMBRO]]) -> 0 | AL36: =IFERROR(AK36/$AK$3,"") | AM36: =AVERAGE(Tabela373[[#This Row],[JANEIRO]],Tabela373[[#This Row],[FEVEREIRO]],Tabela373[[#This Row],[MARÇO]],Tabela373[[#This Row],[ABRIL]],Tabela373[[#This Row],[MAIO]],Tabela373[[#This Row],[JUNHO]],Tabela373[[#This Row],[JULHO]],Tabela373[[#This Row],[AGOSTO]],Tabela373[[#This Row],[SETEMBRO]],Tabela373[[#This Row],[OUTUBRO]],Tabela373[[#This Row],[NOVEMBRO]],Tabela373[[#This Row],[DEZEMBRO]]) -> #DIV/0!
A37: SIMPLES NACIONAL | C37: =IFERROR(B37/$B$3,"") | E37: =IFERROR(D37/$D$3,"") | F37: =IFERROR((D37-B37)/B37,"") | H37: =IFERROR(G37/$G$3,"") | I37: =IFERROR((G37-D37)/D37,"") | K37: =IFERROR(J37/$J$3,"") | L37: =IFERROR((J37-G37)/G37,"") | N37: =IFERROR(M37/$M$3,"") | O37: =IFERROR((M37-J37)/J37,"") | Q37: =IFERROR(P37/$P$3,"") | R37: =IFERROR((P37-M37)/M37,"") | T37: =IFERROR(S37/$S$3,"") | U37: =IFERROR((S37-P37)/P37,"") | W37: =IFERROR(V37/$V$3,"") | X37: =IFERROR((V37-S37)/S37,"") | Z37: =IFERROR(Y37/$Y$3,"") | AA37: =IFERROR((Y37-V37)/V37,"") | AC37: =IFERROR(AB37/$AB$3,"") | AD37: =IFERROR((AB37-Y37)/Y37,"") | AF37: =IFERROR(AE37/$AE$3,"") | AG37: =IFERROR((AE37-AB37)/AB37,"") | AI37: =IFERROR(AH37/$AH$3,"") | AJ37: =IFERROR((AH37-AE37)/AE37,"") | AK37: =SUM(Tabela373[[#This Row],[JANEIRO]]+Tabela373[[#This Row],[FEVEREIRO]]+Tabela373[[#This Row],[MARÇO]]+Tabela373[[#This Row],[ABRIL]]+Tabela373[[#This Row],[MAIO]]+Tabela373[[#This Row],[JUNHO]]+Tabela373[[#This Row],[JULHO]]+Tabela373[[#This Row],[AGOSTO]]+Tabela373[[#This Row],[SETEMBRO]]+Tabela373[[#This Row],[NOVEMBRO]]+Tabela373[[#This Row],[DEZEMBRO]]) -> 0 | AL37: =IFERROR(AK37/$AK$3,"") | AM37: =AVERAGE(Tabela373[[#This Row],[JANEIRO]],Tabela373[[#This Row],[FEVEREIRO]],Tabela373[[#This Row],[MARÇO]],Tabela373[[#This Row],[ABRIL]],Tabela373[[#This Row],[MAIO]],Tabela373[[#This Row],[JUNHO]],Tabela373[[#This Row],[JULHO]],Tabela373[[#This Row],[AGOSTO]],Tabela373[[#This Row],[SETEMBRO]],Tabela373[[#This Row],[OUTUBRO]],Tabela373[[#This Row],[NOVEMBRO]],Tabela373[[#This Row],[DEZEMBRO]]) -> #DIV/0!
C38: =IFERROR(B38/$B$3,"") | E38: =IFERROR(D38/$D$3,"") | F38: =IFERROR((D38-B38)/B38,"") | H38: =IFERROR(G38/$G$3,"") | I38: =IFERROR((G38-D38)/D38,"") | K38: =IFERROR(J38/$J$3,"") | L38: =IFERROR((J38-G38)/G38,"") | N38: =IFERROR(M38/$M$3,"") | O38: =IFERROR((M38-J38)/J38,"") | Q38: =IFERROR(P38/$P$3,"") | R38: =IFERROR((P38-M38)/M38,"") | T38: =IFERROR(S38/$S$3,"") | U38: =IFERROR((S38-P38)/P38,"") | W38: =IFERROR(V38/$V$3,"") | X38: =IFERROR((V38-S38)/S38,"") | Z38: =IFERROR(Y38/$Y$3,"") | AA38: =IFERROR((Y38-V38)/V38,"") | AC38: =IFERROR(AB38/$AB$3,"") | AD38: =IFERROR((AB38-Y38)/Y38,"") | AF38: =IFERROR(AE38/$AE$3,"") | AG38: =IFERROR((AE38-AB38)/AB38,"") | AI38: =IFERROR(AH38/$AH$3,"") | AJ38: =IFERROR((AH38-AE38)/AE38,"") | AK38: =SUM(Tabela373[[#This Row],[JANEIRO]]+Tabela373[[#This Row],[FEVEREIRO]]+Tabela373[[#This Row],[MARÇO]]+Tabela373[[#This Row],[ABRIL]]+Tabela373[[#This Row],[MAIO]]+Tabela373[[#This Row],[JUNHO]]+Tabela373[[#This Row],[JULHO]]+Tabela373[[#This Row],[AGOSTO]]+Tabela373[[#This Row],[SETEMBRO]]+Tabela373[[#This Row],[NOVEMBRO]]+Tabela373[[#This Row],[DEZEMBRO]]) -> 0 | AL38: =IFERROR(AK38/$AK$3,"") | AM38: =AVERAGE(Tabela373[[#This Row],[JANEIRO]],Tabela373[[#This Row],[FEVEREIRO]],Tabela373[[#This Row],[MARÇO]],Tabela373[[#This Row],[ABRIL]],Tabela373[[#This Row],[MAIO]],Tabela373[[#This Row],[JUNHO]],Tabela373[[#This Row],[JULHO]],Tabela373[[#This Row],[AGOSTO]],Tabela373[[#This Row],[SETEMBRO]],Tabela373[[#This Row],[OUTUBRO]],Tabela373[[#This Row],[NOVEMBRO]],Tabela373[[#This Row],[DEZEMBRO]]) -> #DIV/0!
A39: OUTRAS DEDUÇÕES | B39: =SUM(B40:B42) -> 0 | C39: =IFERROR(B39/$B$3,"") | D39: =SUM(D40:D42) -> 0 | E39: =IFERROR(D39/$D$3,"") | F39: =IFERROR((D39-B39)/B39,"") | G39: =SUM(G40:G42) -> 0 | H39: =IFERROR(G39/$G$3,"") | I39: =IFERROR((G39-D39)/D39,"") | J39: =SUM(J40:J42) -> 0 | K39: =IFERROR(J39/$J$3,"") | L39: =IFERROR((J39-G39)/G39,"") | M39: =SUM(M40:M42) -> 0 | N39: =IFERROR(M39/$M$3,"") | O39: =IFERROR((M39-J39)/J39,"") | P39: =SUM(P40:P42) -> 0 | Q39: =IFERROR(P39/$P$3,"") | R39: =IFERROR((P39-M39)/M39,"") | S39: =SUM(S40:S42) -> 0 | T39: =IFERROR(S39/$S$3,"") | U39: =IFERROR((S39-P39)/P39,"") | V39: =SUM(V40:V42) -> 0 | W39: =IFERROR(V39/$V$3,"") | X39: =IFERROR((V39-S39)/S39,"") | Y39: =SUM(Y40:Y42) -> 0 | Z39: =IFERROR(Y39/$Y$3,"") | AA39: =IFERROR((Y39-V39)/V39,"") | AB39: =SUM(AB40:AB42) -> 0 | AC39: =IFERROR(AB39/$AB$3,"") | AD39: =IFERROR((AB39-Y39)/Y39,"") | AE39: =SUM(AE40:AE42) -> 0 | AF39: =IFERROR(AE39/$AE$3,"") | AG39: =IFERROR((AE39-AB39)/AB39,"") | AH39: =SUM(AH40:AH42) -> 0 | AI39: =IFERROR(AH39/$AH$3,"") | AJ39: =IFERROR((AH39-AE39)/AE39,"") | AK39: =SUM(Tabela373[[#This Row],[JANEIRO]]+Tabela373[[#This Row],[FEVEREIRO]]+Tabela373[[#This Row],[MARÇO]]+Tabela373[[#This Row],[ABRIL]]+Tabela373[[#This Row],[MAIO]]+Tabela373[[#This Row],[JUNHO]]+Tabela373[[#This Row],[JULHO]]+Tabela373[[#This Row],[AGOSTO]]+Tabela373[[#This Row],[SETEMBRO]]+Tabela373[[#This Row],[NOVEMBRO]]+Tabela373[[#This Row],[DEZEMBRO]]) -> 0 | AL39: =IFERROR(AK39/$AK$3,"") | AM39: =AVERAGE(Tabela373[[#This Row],[JANEIRO]],Tabela373[[#This Row],[FEVEREIRO]],Tabela373[[#This Row],[MARÇO]],Tabela373[[#This Row],[ABRIL]],Tabela373[[#This Row],[MAIO]],Tabela373[[#This Row],[JUNHO]],Tabela373[[#This Row],[JULHO]],Tabela373[[#This Row],[AGOSTO]],Tabela373[[#This Row],[SETEMBRO]],Tabela373[[#This Row],[OUTUBRO]],Tabela373[[#This Row],[NOVEMBRO]],Tabela373[[#This Row],[DEZEMBRO]]) -> 0
A40: DESCONTOS CONCEDIDOS | C40: =IFERROR(B40/$B$3,"") | E40: =IFERROR(D40/$D$3,"") | F40: =IFERROR((D40-B40)/B40,"") | H40: =IFERROR(G40/$G$3,"") | I40: =IFERROR((G40-D40)/D40,"") | K40: =IFERROR(J40/$J$3,"") | L40: =IFERROR((J40-G40)/G40,"") | N40: =IFERROR(M40/$M$3,"") | O40: =IFERROR((M40-J40)/J40,"") | Q40: =IFERROR(P40/$P$3,"") | R40: =IFERROR((P40-M40)/M40,"") | T40: =IFERROR(S40/$S$3,"") | U40: =IFERROR((S40-P40)/P40,"") | W40: =IFERROR(V40/$V$3,"") | X40: =IFERROR((V40-S40)/S40,"") | Z40: =IFERROR(Y40/$Y$3,"") | AA40: =IFERROR((Y40-V40)/V40,"") | AC40: =IFERROR(AB40/$AB$3,"") | AD40: =IFERROR((AB40-Y40)/Y40,"") | AF40: =IFERROR(AE40/$AE$3,"") | AG40: =IFERROR((AE40-AB40)/AB40,"") | AI40: =IFERROR(AH40/$AH$3,"") | AJ40: =IFERROR((AH40-AE40)/AE40,"") | AK40: =SUM(Tabela373[[#This Row],[JANEIRO]]+Tabela373[[#This Row],[FEVEREIRO]]+Tabela373[[#This Row],[MARÇO]]+Tabela373[[#This Row],[ABRIL]]+Tabela373[[#This Row],[MAIO]]+Tabela373[[#This Row],[JUNHO]]+Tabela373[[#This Row],[JULHO]]+Tabela373[[#This Row],[AGOSTO]]+Tabela373[[#This Row],[SETEMBRO]]+Tabela373[[#This Row],[NOVEMBRO]]+Tabela373[[#This Row],[DEZEMBRO]]) -> 0 | AL40: =IFERROR(AK40/$AK$3,"") | AM40: =AVERAGE(Tabela373[[#This Row],[JANEIRO]],Tabela373[[#This Row],[FEVEREIRO]],Tabela373[[#This Row],[MARÇO]],Tabela373[[#This Row],[ABRIL]],Tabela373[[#This Row],[MAIO]],Tabela373[[#This Row],[JUNHO]],Tabela373[[#This Row],[JULHO]],Tabela373[[#This Row],[AGOSTO]],Tabela373[[#This Row],[SETEMBRO]],Tabela373[[#This Row],[OUTUBRO]],Tabela373[[#This Row],[NOVEMBRO]],Tabela373[[#This Row],[DEZEMBRO]]) -> #DIV/0!
A41: DEVOLUÇÕES DE CLIENTES | C41: =IFERROR(B41/$B$3,"") | E41: =IFERROR(D41/$D$3,"") | F41: =IFERROR((D41-B41)/B41,"") | H41: =IFERROR(G41/$G$3,"") | I41: =IFERROR((G41-D41)/D41,"") | K41: =IFERROR(J41/$J$3,"") | L41: =IFERROR((J41-G41)/G41,"") | N41: =IFERROR(M41/$M$3,"") | O41: =IFERROR((M41-J41)/J41,"") | Q41: =IFERROR(P41/$P$3,"") | R41: =IFERROR((P41-M41)/M41,"") | T41: =IFERROR(S41/$S$3,"") | U41: =IFERROR((S41-P41)/P41,"") | W41: =IFERROR(V41/$V$3,"") | X41: =IFERROR((V41-S41)/S41,"") | Z41: =IFERROR(Y41/$Y$3,"") | AA41: =IFERROR((Y41-V41)/V41,"") | AC41: =IFERROR(AB41/$AB$3,"") | AD41: =IFERROR((AB41-Y41)/Y41,"") | AF41: =IFERROR(AE41/$AE$3,"") | AG41: =IFERROR((AE41-AB41)/AB41,"") | AI41: =IFERROR(AH41/$AH$3,"") | AJ41: =IFERROR((AH41-AE41)/AE41,"") | AK41: =SUM(Tabela373[[#This Row],[JANEIRO]]+Tabela373[[#This Row],[FEVEREIRO]]+Tabela373[[#This Row],[MARÇO]]+Tabela373[[#This Row],[ABRIL]]+Tabela373[[#This Row],[MAIO]]+Tabela373[[#This Row],[JUNHO]]+Tabela373[[#This Row],[JULHO]]+Tabela373[[#This Row],[AGOSTO]]+Tabela373[[#This Row],[SETEMBRO]]+Tabela373[[#This Row],[NOVEMBRO]]+Tabela373[[#This Row],[DEZEMBRO]]) -> 0 | AL41: =IFERROR(AK41/$AK$3,"") | AM41: =AVERAGE(Tabela373[[#This Row],[JANEIRO]],Tabela373[[#This Row],[FEVEREIRO]],Tabela373[[#This Row],[MARÇO]],Tabela373[[#This Row],[ABRIL]],Tabela373[[#This Row],[MAIO]],Tabela373[[#This Row],[JUNHO]],Tabela373[[#This Row],[JULHO]],Tabela373[[#This Row],[AGOSTO]],Tabela373[[#This Row],[SETEMBRO]],Tabela373[[#This Row],[OUTUBRO]],Tabela373[[#This Row],[NOVEMBRO]],Tabela373[[#This Row],[DEZEMBRO]]) -> #DIV/0!
C42: =IFERROR(B42/$B$3,"") | E42: =IFERROR(D42/$D$3,"") | F42: =IFERROR((D42-B42)/B42,"") | H42: =IFERROR(G42/$G$3,"") | I42: =IFERROR((G42-D42)/D42,"") | K42: =IFERROR(J42/$J$3,"") | L42: =IFERROR((J42-G42)/G42,"") | N42: =IFERROR(M42/$M$3,"") | O42: =IFERROR((M42-J42)/J42,"") | Q42: =IFERROR(P42/$P$3,"") | R42: =IFERROR((P42-M42)/M42,"") | T42: =IFERROR(S42/$S$3,"") | U42: =IFERROR((S42-P42)/P42,"") | W42: =IFERROR(V42/$V$3,"") | X42: =IFERROR((V42-S42)/S42,"") | Z42: =IFERROR(Y42/$Y$3,"") | AA42: =IFERROR((Y42-V42)/V42,"") | AC42: =IFERROR(AB42/$AB$3,"") | AD42: =IFERROR((AB42-Y42)/Y42,"") | AF42: =IFERROR(AE42/$AE$3,"") | AG42: =IFERROR((AE42-AB42)/AB42,"") | AI42: =IFERROR(AH42/$AH$3,"") | AJ42: =IFERROR((AH42-AE42)/AE42,"") | AK42: =SUM(Tabela373[[#This Row],[JANEIRO]]+Tabela373[[#This Row],[FEVEREIRO]]+Tabela373[[#This Row],[MARÇO]]+Tabela373[[#This Row],[ABRIL]]+Tabela373[[#This Row],[MAIO]]+Tabela373[[#This Row],[JUNHO]]+Tabela373[[#This Row],[JULHO]]+Tabela373[[#This Row],[AGOSTO]]+Tabela373[[#This Row],[SETEMBRO]]+Tabela373[[#This Row],[NOVEMBRO]]+Tabela373[[#This Row],[DEZEMBRO]]) -> 0 | AL42: =IFERROR(AK42/$AK$3,"") | AM42: =AVERAGE(Tabela373[[#This Row],[JANEIRO]],Tabela373[[#This Row],[FEVEREIRO]],Tabela373[[#This Row],[MARÇO]],Tabela373[[#This Row],[ABRIL]],Tabela373[[#This Row],[MAIO]],Tabela373[[#This Row],[JUNHO]],Tabela373[[#This Row],[JULHO]],Tabela373[[#This Row],[AGOSTO]],Tabela373[[#This Row],[SETEMBRO]],Tabela373[[#This Row],[OUTUBRO]],Tabela373[[#This Row],[NOVEMBRO]],Tabela373[[#This Row],[DEZEMBRO]]) -> #DIV/0!
A43: (=) RECEITA LIQUIDA | B43: =B3-B31 -> 0 | C43: =IFERROR(B43/$B$3,"") | D43: =D3-D31 -> 0 | E43: =IFERROR(D43/$D$3,"") | F43: =IFERROR((D43-B43)/B43,"") | G43: =G3-G31 -> 0 | H43: =IFERROR(G43/$G$3,"") | I43: =IFERROR((G43-D43)/D43,"") | J43: =J3-J31 -> 0 | K43: =IFERROR(J43/$J$3,"") | L43: =IFERROR((J43-G43)/G43,"") | M43: =M3-M31 -> 0 | N43: =IFERROR(M43/$M$3,"") | O43: =IFERROR((M43-J43)/J43,"") | P43: =P3-P31 -> 0 | Q43: =IFERROR(P43/$P$3,"") | R43: =IFERROR((P43-M43)/M43,"") | S43: =S3-S31 -> 0 | T43: =IFERROR(S43/$S$3,"") | U43: =IFERROR((S43-P43)/P43,"") | V43: =V3-V31 -> 0 | W43: =IFERROR(V43/$V$3,"") | X43: =IFERROR((V43-S43)/S43,"") | Y43: =Y3-Y31 -> 0 | Z43: =IFERROR(Y43/$Y$3,"") | AA43: =IFERROR((Y43-V43)/V43,"") | AB43: =AB3-AB31 -> 0 | AC43: =IFERROR(AB43/$AB$3,"") | AD43: =IFERROR((AB43-Y43)/Y43,"") | AE43: =AE3-AE31 -> 0 | AF43: =IFERROR(AE43/$AE$3,"") | AG43: =IFERROR((AE43-AB43)/AB43,"") | AH43: =AH3-AH31 -> 0 | AI43: =IFERROR(AH43/$AH$3,"") | AJ43: =IFERROR((AH43-AE43)/AE43,"") | AK43: =SUM(Tabela373[[#This Row],[JANEIRO]]+Tabela373[[#This Row],[FEVEREIRO]]+Tabela373[[#This Row],[MARÇO]]+Tabela373[[#This Row],[ABRIL]]+Tabela373[[#This Row],[MAIO]]+Tabela373[[#This Row],[JUNHO]]+Tabela373[[#This Row],[JULHO]]+Tabela373[[#This Row],[AGOSTO]]+Tabela373[[#This Row],[SETEMBRO]]+Tabela373[[#This Row],[NOVEMBRO]]+Tabela373[[#This Row],[DEZEMBRO]]) -> 0 | AL43: =IFERROR(AK43/$AK$3,"") | AM43: =AVERAGE(Tabela373[[#This Row],[JANEIRO]],Tabela373[[#This Row],[FEVEREIRO]],Tabela373[[#This Row],[MARÇO]],Tabela373[[#This Row],[ABRIL]],Tabela373[[#This Row],[MAIO]],Tabela373[[#This Row],[JUNHO]],Tabela373[[#This Row],[JULHO]],Tabela373[[#This Row],[AGOSTO]],Tabela373[[#This Row],[SETEMBRO]],Tabela373[[#This Row],[OUTUBRO]],Tabela373[[#This Row],[NOVEMBRO]],Tabela373[[#This Row],[DEZEMBRO]]) -> 0
A44: (-) CUSTOS DIRETOS | B44: =B45+B50+B54+B60 -> 0 | C44: =IFERROR(B44/$B$3,"") | D44: =D45+D50+D54+D60 -> 0 | E44: =IFERROR(D44/$D$3,"") | F44: =IFERROR((D44-B44)/B44,"") | G44: =G45+G50+G54+G60 -> 0 | H44: =IFERROR(G44/$G$3,"") | I44: =IFERROR((G44-D44)/D44,"") | J44: =J45+J50+J54+J60 -> 0 | K44: =IFERROR(J44/$J$3,"") | L44: =IFERROR((J44-G44)/G44,"") | M44: =M45+M50+M54+M60 -> 0 | N44: =IFERROR(M44/$M$3,"") | O44: =IFERROR((M44-J44)/J44,"") | P44: =P45+P50+P54+P60 -> 0 | Q44: =IFERROR(P44/$P$3,"") | R44: =IFERROR((P44-M44)/M44,"") | S44: =S45+S50+S54+S60 -> 0 | T44: =IFERROR(S44/$S$3,"") | U44: =IFERROR((S44-P44)/P44,"") | V44: =V45+V50+V54+V60 -> 0 | W44: =IFERROR(V44/$V$3,"") | X44: =IFERROR((V44-S44)/S44,"") | Y44: =Y45+Y50+Y54+Y60 -> 0 | Z44: =IFERROR(Y44/$Y$3,"") | AA44: =IFERROR((Y44-V44)/V44,"") | AB44: =AB45+AB50+AB54+AB60 -> 0 | AC44: =IFERROR(AB44/$AB$3,"") | AD44: =IFERROR((AB44-Y44)/Y44,"") | AE44: =AE45+AE50+AE54+AE60 -> 0 | AF44: =IFERROR(AE44/$AE$3,"") | AG44: =IFERROR((AE44-AB44)/AB44,"") | AH44: =AH45+AH50+AH54+AH60 -> 0 | AI44: =IFERROR(AH44/$AH$3,"") | AJ44: =IFERROR((AH44-AE44)/AE44,"") | AK44: =SUM(Tabela373[[#This Row],[JANEIRO]]+Tabela373[[#This Row],[FEVEREIRO]]+Tabela373[[#This Row],[MARÇO]]+Tabela373[[#This Row],[ABRIL]]+Tabela373[[#This Row],[MAIO]]+Tabela373[[#This Row],[JUNHO]]+Tabela373[[#This Row],[JULHO]]+Tabela373[[#This Row],[AGOSTO]]+Tabela373[[#This Row],[SETEMBRO]]+Tabela373[[#This Row],[NOVEMBRO]]+Tabela373[[#This Row],[DEZEMBRO]]) -> 0 | AL44: =IFERROR(AK44/$AK$3,"") | AM44: =AVERAGE(Tabela373[[#This Row],[JANEIRO]],Tabela373[[#This Row],[FEVEREIRO]],Tabela373[[#This Row],[MARÇO]],Tabela373[[#This Row],[ABRIL]],Tabela373[[#This Row],[MAIO]],Tabela373[[#This Row],[JUNHO]],Tabela373[[#This Row],[JULHO]],Tabela373[[#This Row],[AGOSTO]],Tabela373[[#This Row],[SETEMBRO]],Tabela373[[#This Row],[OUTUBRO]],Tabela373[[#This Row],[NOVEMBRO]],Tabela373[[#This Row],[DEZEMBRO]]) -> 0
A45: CUSTOS DE PRODUÇÃO | B45: =SUM(B46:B49) -> 0 | C45: =IFERROR(B45/$B$3,"") | D45: =SUM(D46:D49) -> 0 | E45: =IFERROR(D45/$D$3,"") | F45: =IFERROR((D45-B45)/B45,"") | G45: =SUM(G46:G49) -> 0 | H45: =IFERROR(G45/$G$3,"") | I45: =IFERROR((G45-D45)/D45,"") | J45: =SUM(J46:J49) -> 0 | K45: =IFERROR(J45/$J$3,"") | L45: =IFERROR((J45-G45)/G45,"") | M45: =SUM(M46:M49) -> 0 | N45: =IFERROR(M45/$M$3,"") | O45: =IFERROR((M45-J45)/J45,"") | P45: =SUM(P46:P49) -> 0 | Q45: =IFERROR(P45/$P$3,"") | R45: =IFERROR((P45-M45)/M45,"") | S45: =SUM(S46:S49) -> 0 | T45: =IFERROR(S45/$S$3,"") | U45: =IFERROR((S45-P45)/P45,"") | V45: =SUM(V46:V49) -> 0 | W45: =IFERROR(V45/$V$3,"") | X45: =IFERROR((V45-S45)/S45,"") | Y45: =SUM(Y46:Y49) -> 0 | Z45: =IFERROR(Y45/$Y$3,"") | AA45: =IFERROR((Y45-V45)/V45,"") | AB45: =SUM(AB46:AB49) -> 0 | AC45: =IFERROR(AB45/$AB$3,"") | AD45: =IFERROR((AB45-Y45)/Y45,"") | AE45: =SUM(AE46:AE49) -> 0 | AF45: =IFERROR(AE45/$AE$3,"") | AG45: =IFERROR((AE45-AB45)/AB45,"") | AH45: =SUM(AH46:AH49) -> 0 | AI45: =IFERROR(AH45/$AH$3,"") | AJ45: =IFERROR((AH45-AE45)/AE45,"") | AK45: =SUM(Tabela373[[#This Row],[JANEIRO]]+Tabela373[[#This Row],[FEVEREIRO]]+Tabela373[[#This Row],[MARÇO]]+Tabela373[[#This Row],[ABRIL]]+Tabela373[[#This Row],[MAIO]]+Tabela373[[#This Row],[JUNHO]]+Tabela373[[#This Row],[JULHO]]+Tabela373[[#This Row],[AGOSTO]]+Tabela373[[#This Row],[SETEMBRO]]+Tabela373[[#This Row],[NOVEMBRO]]+Tabela373[[#This Row],[DEZEMBRO]]) -> 0 | AL45: =IFERROR(AK45/$AK$3,"") | AM45: =AVERAGE(Tabela373[[#This Row],[JANEIRO]],Tabela373[[#This Row],[FEVEREIRO]],Tabela373[[#This Row],[MARÇO]],Tabela373[[#This Row],[ABRIL]],Tabela373[[#This Row],[MAIO]],Tabela373[[#This Row],[JUNHO]],Tabela373[[#This Row],[JULHO]],Tabela373[[#This Row],[AGOSTO]],Tabela373[[#This Row],[SETEMBRO]],Tabela373[[#This Row],[OUTUBRO]],Tabela373[[#This Row],[NOVEMBRO]],Tabela373[[#This Row],[DEZEMBRO]]) -> 0
A46: EMBALAGENS PRODUÇÃO | C46: =IFERROR(B46/$B$3,"") | E46: =IFERROR(D46/$D$3,"") | F46: =IFERROR((D46-B46)/B46,"") | H46: =IFERROR(G46/$G$3,"") | I46: =IFERROR((G46-D46)/D46,"") | K46: =IFERROR(J46/$J$3,"") | L46: =IFERROR((J46-G46)/G46,"") | N46: =IFERROR(M46/$M$3,"") | O46: =IFERROR((M46-J46)/J46,"") | Q46: =IFERROR(P46/$P$3,"") | R46: =IFERROR((P46-M46)/M46,"") | T46: =IFERROR(S46/$S$3,"") | U46: =IFERROR((S46-P46)/P46,"") | W46: =IFERROR(V46/$V$3,"") | X46: =IFERROR((V46-S46)/S46,"") | Z46: =IFERROR(Y46/$Y$3,"") | AA46: =IFERROR((Y46-V46)/V46,"") | AC46: =IFERROR(AB46/$AB$3,"") | AD46: =IFERROR((AB46-Y46)/Y46,"") | AF46: =IFERROR(AE46/$AE$3,"") | AG46: =IFERROR((AE46-AB46)/AB46,"") | AI46: =IFERROR(AH46/$AH$3,"") | AJ46: =IFERROR((AH46-AE46)/AE46,"") | AK46: =SUM(Tabela373[[#This Row],[JANEIRO]]+Tabela373[[#This Row],[FEVEREIRO]]+Tabela373[[#This Row],[MARÇO]]+Tabela373[[#This Row],[ABRIL]]+Tabela373[[#This Row],[MAIO]]+Tabela373[[#This Row],[JUNHO]]+Tabela373[[#This Row],[JULHO]]+Tabela373[[#This Row],[AGOSTO]]+Tabela373[[#This Row],[SETEMBRO]]+Tabela373[[#This Row],[NOVEMBRO]]+Tabela373[[#This Row],[DEZEMBRO]]) -> 0 | AL46: =IFERROR(AK46/$AK$3,"") | AM46: =AVERAGE(Tabela373[[#This Row],[JANEIRO]],Tabela373[[#This Row],[FEVEREIRO]],Tabela373[[#This Row],[MARÇO]],Tabela373[[#This Row],[ABRIL]],Tabela373[[#This Row],[MAIO]],Tabela373[[#This Row],[JUNHO]],Tabela373[[#This Row],[JULHO]],Tabela373[[#This Row],[AGOSTO]],Tabela373[[#This Row],[SETEMBRO]],Tabela373[[#This Row],[OUTUBRO]],Tabela373[[#This Row],[NOVEMBRO]],Tabela373[[#This Row],[DEZEMBRO]]) -> #DIV/0!
A47: INSUMOS DIRETOS | C47: =IFERROR(B47/$B$3,"") | E47: =IFERROR(D47/$D$3,"") | F47: =IFERROR((D47-B47)/B47,"") | H47: =IFERROR(G47/$G$3,"") | I47: =IFERROR((G47-D47)/D47,"") | K47: =IFERROR(J47/$J$3,"") | L47: =IFERROR((J47-G47)/G47,"") | N47: =IFERROR(M47/$M$3,"") | O47: =IFERROR((M47-J47)/J47,"") | Q47: =IFERROR(P47/$P$3,"") | R47: =IFERROR((P47-M47)/M47,"") | T47: =IFERROR(S47/$S$3,"") | U47: =IFERROR((S47-P47)/P47,"") | W47: =IFERROR(V47/$V$3,"") | X47: =IFERROR((V47-S47)/S47,"") | Z47: =IFERROR(Y47/$Y$3,"") | AA47: =IFERROR((Y47-V47)/V47,"") | AC47: =IFERROR(AB47/$AB$3,"") | AD47: =IFERROR((AB47-Y47)/Y47,"") | AF47: =IFERROR(AE47/$AE$3,"") | AG47: =IFERROR((AE47-AB47)/AB47,"") | AI47: =IFERROR(AH47/$AH$3,"") | AJ47: =IFERROR((AH47-AE47)/AE47,"") | AK47: =SUM(Tabela373[[#This Row],[JANEIRO]]+Tabela373[[#This Row],[FEVEREIRO]]+Tabela373[[#This Row],[MARÇO]]+Tabela373[[#This Row],[ABRIL]]+Tabela373[[#This Row],[MAIO]]+Tabela373[[#This Row],[JUNHO]]+Tabela373[[#This Row],[JULHO]]+Tabela373[[#This Row],[AGOSTO]]+Tabela373[[#This Row],[SETEMBRO]]+Tabela373[[#This Row],[NOVEMBRO]]+Tabela373[[#This Row],[DEZEMBRO]]) -> 0 | AL47: =IFERROR(AK47/$AK$3,"") | AM47: =AVERAGE(Tabela373[[#This Row],[JANEIRO]],Tabela373[[#This Row],[FEVEREIRO]],Tabela373[[#This Row],[MARÇO]],Tabela373[[#This Row],[ABRIL]],Tabela373[[#This Row],[MAIO]],Tabela373[[#This Row],[JUNHO]],Tabela373[[#This Row],[JULHO]],Tabela373[[#This Row],[AGOSTO]],Tabela373[[#This Row],[SETEMBRO]],Tabela373[[#This Row],[OUTUBRO]],Tabela373[[#This Row],[NOVEMBRO]],Tabela373[[#This Row],[DEZEMBRO]]) -> #DIV/0!
A48: MATÉRIA PRIMA | C48: =IFERROR(B48/$B$3,"") | E48: =IFERROR(D48/$D$3,"") | F48: =IFERROR((D48-B48)/B48,"") | H48: =IFERROR(G48/$G$3,"") | I48: =IFERROR((G48-D48)/D48,"") | K48: =IFERROR(J48/$J$3,"") | L48: =IFERROR((J48-G48)/G48,"") | N48: =IFERROR(M48/$M$3,"") | O48: =IFERROR((M48-J48)/J48,"") | Q48: =IFERROR(P48/$P$3,"") | R48: =IFERROR((P48-M48)/M48,"") | T48: =IFERROR(S48/$S$3,"") | U48: =IFERROR((S48-P48)/P48,"") | W48: =IFERROR(V48/$V$3,"") | X48: =IFERROR((V48-S48)/S48,"") | Z48: =IFERROR(Y48/$Y$3,"") | AA48: =IFERROR((Y48-V48)/V48,"") | AC48: =IFERROR(AB48/$AB$3,"") | AD48: =IFERROR((AB48-Y48)/Y48,"") | AF48: =IFERROR(AE48/$AE$3,"") | AG48: =IFERROR((AE48-AB48)/AB48,"") | AI48: =IFERROR(AH48/$AH$3,"") | AJ48: =IFERROR((AH48-AE48)/AE48,"") | AK48: =SUM(Tabela373[[#This Row],[JANEIRO]]+Tabela373[[#This Row],[FEVEREIRO]]+Tabela373[[#This Row],[MARÇO]]+Tabela373[[#This Row],[ABRIL]]+Tabela373[[#This Row],[MAIO]]+Tabela373[[#This Row],[JUNHO]]+Tabela373[[#This Row],[JULHO]]+Tabela373[[#This Row],[AGOSTO]]+Tabela373[[#This Row],[SETEMBRO]]+Tabela373[[#This Row],[NOVEMBRO]]+Tabela373[[#This Row],[DEZEMBRO]]) -> 0 | AL48: =IFERROR(AK48/$AK$3,"") | AM48: =AVERAGE(Tabela373[[#This Row],[JANEIRO]],Tabela373[[#This Row],[FEVEREIRO]],Tabela373[[#This Row],[MARÇO]],Tabela373[[#This Row],[ABRIL]],Tabela373[[#This Row],[MAIO]],Tabela373[[#This Row],[JUNHO]],Tabela373[[#This Row],[JULHO]],Tabela373[[#This Row],[AGOSTO]],Tabela373[[#This Row],[SETEMBRO]],Tabela373[[#This Row],[OUTUBRO]],Tabela373[[#This Row],[NOVEMBRO]],Tabela373[[#This Row],[DEZEMBRO]]) -> #DIV/0!
C49: =IFERROR(B49/$B$3,"") | E49: =IFERROR(D49/$D$3,"") | F49: =IFERROR((D49-B49)/B49,"") | H49: =IFERROR(G49/$G$3,"") | I49: =IFERROR((G49-D49)/D49,"") | K49: =IFERROR(J49/$J$3,"") | L49: =IFERROR((J49-G49)/G49,"") | N49: =IFERROR(M49/$M$3,"") | O49: =IFERROR((M49-J49)/J49,"") | Q49: =IFERROR(P49/$P$3,"") | R49: =IFERROR((P49-M49)/M49,"") | T49: =IFERROR(S49/$S$3,"") | U49: =IFERROR((S49-P49)/P49,"") | W49: =IFERROR(V49/$V$3,"") | X49: =IFERROR((V49-S49)/S49,"") | Z49: =IFERROR(Y49/$Y$3,"") | AA49: =IFERROR((Y49-V49)/V49,"") | AC49: =IFERROR(AB49/$AB$3,"") | AD49: =IFERROR((AB49-Y49)/Y49,"") | AF49: =IFERROR(AE49/$AE$3,"") | AG49: =IFERROR((AE49-AB49)/AB49,"") | AI49: =IFERROR(AH49/$AH$3,"") | AJ49: =IFERROR((AH49-AE49)/AE49,"") | AK49: =SUM(Tabela373[[#This Row],[JANEIRO]]+Tabela373[[#This Row],[FEVEREIRO]]+Tabela373[[#This Row],[MARÇO]]+Tabela373[[#This Row],[ABRIL]]+Tabela373[[#This Row],[MAIO]]+Tabela373[[#This Row],[JUNHO]]+Tabela373[[#This Row],[JULHO]]+Tabela373[[#This Row],[AGOSTO]]+Tabela373[[#This Row],[SETEMBRO]]+Tabela373[[#This Row],[NOVEMBRO]]+Tabela373[[#This Row],[DEZEMBRO]]) -> 0 | AL49: =IFERROR(AK49/$AK$3,"") | AM49: =AVERAGE(Tabela373[[#This Row],[JANEIRO]],Tabela373[[#This Row],[FEVEREIRO]],Tabela373[[#This Row],[MARÇO]],Tabela373[[#This Row],[ABRIL]],Tabela373[[#This Row],[MAIO]],Tabela373[[#This Row],[JUNHO]],Tabela373[[#This Row],[JULHO]],Tabela373[[#This Row],[AGOSTO]],Tabela373[[#This Row],[SETEMBRO]],Tabela373[[#This Row],[OUTUBRO]],Tabela373[[#This Row],[NOVEMBRO]],Tabela373[[#This Row],[DEZEMBRO]]) -> #DIV/0!
A50: CUSTOS DE MERCADORIAS PARA REVENDA | B50: =SUM(B51:B53) -> 0 | C50: =IFERROR(B50/$B$3,"") | D50: =SUM(D51:D53) -> 0 | E50: =IFERROR(D50/$D$3,"") | F50: =IFERROR((D50-B50)/B50,"") | G50: =SUM(G51:G53) -> 0 | H50: =IFERROR(G50/$G$3,"") | I50: =IFERROR((G50-D50)/D50,"") | J50: =SUM(J51:J53) -> 0 | K50: =IFERROR(J50/$J$3,"") | L50: =IFERROR((J50-G50)/G50,"") | M50: =SUM(M51:M53) -> 0 | N50: =IFERROR(M50/$M$3,"") | O50: =IFERROR((M50-J50)/J50,"") | P50: =SUM(P51:P53) -> 0 | Q50: =IFERROR(P50/$P$3,"") | R50: =IFERROR((P50-M50)/M50,"") | S50: =SUM(S51:S53) -> 0 | T50: =IFERROR(S50/$S$3,"") | U50: =IFERROR((S50-P50)/P50,"") | V50: =SUM(V51:V53) -> 0 | W50: =IFERROR(V50/$V$3,"") | X50: =IFERROR((V50-S50)/S50,"") | Y50: =SUM(Y51:Y53) -> 0 | Z50: =IFERROR(Y50/$Y$3,"") | AA50: =IFERROR((Y50-V50)/V50,"") | AB50: =SUM(AB51:AB53) -> 0 | AC50: =IFERROR(AB50/$AB$3,"") | AD50: =IFERROR((AB50-Y50)/Y50,"") | AE50: =SUM(AE51:AE53) -> 0 | AF50: =IFERROR(AE50/$AE$3,"") | AG50: =IFERROR((AE50-AB50)/AB50,"") | AH50: =SUM(AH51:AH53) -> 0 | AI50: =IFERROR(AH50/$AH$3,"") | AJ50: =IFERROR((AH50-AE50)/AE50,"") | AK50: =SUM(Tabela373[[#This Row],[JANEIRO]]+Tabela373[[#This Row],[FEVEREIRO]]+Tabela373[[#This Row],[MARÇO]]+Tabela373[[#This Row],[ABRIL]]+Tabela373[[#This Row],[MAIO]]+Tabela373[[#This Row],[JUNHO]]+Tabela373[[#This Row],[JULHO]]+Tabela373[[#This Row],[AGOSTO]]+Tabela373[[#This Row],[SETEMBRO]]+Tabela373[[#This Row],[NOVEMBRO]]+Tabela373[[#This Row],[DEZEMBRO]]) -> 0 | AL50: =IFERROR(AK50/$AK$3,"") | AM50: =AVERAGE(Tabela373[[#This Row],[JANEIRO]],Tabela373[[#This Row],[FEVEREIRO]],Tabela373[[#This Row],[MARÇO]],Tabela373[[#This Row],[ABRIL]],Tabela373[[#This Row],[MAIO]],Tabela373[[#This Row],[JUNHO]],Tabela373[[#This Row],[JULHO]],Tabela373[[#This Row],[AGOSTO]],Tabela373[[#This Row],[SETEMBRO]],Tabela373[[#This Row],[OUTUBRO]],Tabela373[[#This Row],[NOVEMBRO]],Tabela373[[#This Row],[DEZEMBRO]]) -> 0
A51: COMPRA DE MERCADORIAS PARA REVENDA | C51: =IFERROR(B51/$B$3,"") | E51: =IFERROR(D51/$D$3,"") | F51: =IFERROR((D51-B51)/B51,"") | H51: =IFERROR(G51/$G$3,"") | I51: =IFERROR((G51-D51)/D51,"") | K51: =IFERROR(J51/$J$3,"") | L51: =IFERROR((J51-G51)/G51,"") | N51: =IFERROR(M51/$M$3,"") | O51: =IFERROR((M51-J51)/J51,"") | Q51: =IFERROR(P51/$P$3,"") | R51: =IFERROR((P51-M51)/M51,"") | T51: =IFERROR(S51/$S$3,"") | U51: =IFERROR((S51-P51)/P51,"") | W51: =IFERROR(V51/$V$3,"") | X51: =IFERROR((V51-S51)/S51,"") | Z51: =IFERROR(Y51/$Y$3,"") | AA51: =IFERROR((Y51-V51)/V51,"") | AC51: =IFERROR(AB51/$AB$3,"") | AD51: =IFERROR((AB51-Y51)/Y51,"") | AF51: =IFERROR(AE51/$AE$3,"") | AG51: =IFERROR((AE51-AB51)/AB51,"") | AI51: =IFERROR(AH51/$AH$3,"") | AJ51: =IFERROR((AH51-AE51)/AE51,"") | AK51: =SUM(Tabela373[[#This Row],[JANEIRO]]+Tabela373[[#This Row],[FEVEREIRO]]+Tabela373[[#This Row],[MARÇO]]+Tabela373[[#This Row],[ABRIL]]+Tabela373[[#This Row],[MAIO]]+Tabela373[[#This Row],[JUNHO]]+Tabela373[[#This Row],[JULHO]]+Tabela373[[#This Row],[AGOSTO]]+Tabela373[[#This Row],[SETEMBRO]]+Tabela373[[#This Row],[NOVEMBRO]]+Tabela373[[#This Row],[DEZEMBRO]]) -> 0 | AL51: =IFERROR(AK51/$AK$3,"") | AM51: =AVERAGE(Tabela373[[#This Row],[JANEIRO]],Tabela373[[#This Row],[FEVEREIRO]],Tabela373[[#This Row],[MARÇO]],Tabela373[[#This Row],[ABRIL]],Tabela373[[#This Row],[MAIO]],Tabela373[[#This Row],[JUNHO]],Tabela373[[#This Row],[JULHO]],Tabela373[[#This Row],[AGOSTO]],Tabela373[[#This Row],[SETEMBRO]],Tabela373[[#This Row],[OUTUBRO]],Tabela373[[#This Row],[NOVEMBRO]],Tabela373[[#This Row],[DEZEMBRO]]) -> #DIV/0!
A52: EMBALAGENS MERCADORIA PARA REVENDA | C52: =IFERROR(B52/$B$3,"") | E52: =IFERROR(D52/$D$3,"") | F52: =IFERROR((D52-B52)/B52,"") | H52: =IFERROR(G52/$G$3,"") | I52: =IFERROR((G52-D52)/D52,"") | K52: =IFERROR(J52/$J$3,"") | L52: =IFERROR((J52-G52)/G52,"") | N52: =IFERROR(M52/$M$3,"") | O52: =IFERROR((M52-J52)/J52,"") | Q52: =IFERROR(P52/$P$3,"") | R52: =IFERROR((P52-M52)/M52,"") | T52: =IFERROR(S52/$S$3,"") | U52: =IFERROR((S52-P52)/P52,"") | W52: =IFERROR(V52/$V$3,"") | X52: =IFERROR((V52-S52)/S52,"") | Z52: =IFERROR(Y52/$Y$3,"") | AA52: =IFERROR((Y52-V52)/V52,"") | AC52: =IFERROR(AB52/$AB$3,"") | AD52: =IFERROR((AB52-Y52)/Y52,"") | AF52: =IFERROR(AE52/$AE$3,"") | AG52: =IFERROR((AE52-AB52)/AB52,"") | AI52: =IFERROR(AH52/$AH$3,"") | AJ52: =IFERROR((AH52-AE52)/AE52,"") | AK52: =SUM(Tabela373[[#This Row],[JANEIRO]]+Tabela373[[#This Row],[FEVEREIRO]]+Tabela373[[#This Row],[MARÇO]]+Tabela373[[#This Row],[ABRIL]]+Tabela373[[#This Row],[MAIO]]+Tabela373[[#This Row],[JUNHO]]+Tabela373[[#This Row],[JULHO]]+Tabela373[[#This Row],[AGOSTO]]+Tabela373[[#This Row],[SETEMBRO]]+Tabela373[[#This Row],[NOVEMBRO]]+Tabela373[[#This Row],[DEZEMBRO]]) -> 0 | AL52: =IFERROR(AK52/$AK$3,"") | AM52: =AVERAGE(Tabela373[[#This Row],[JANEIRO]],Tabela373[[#This Row],[FEVEREIRO]],Tabela373[[#This Row],[MARÇO]],Tabela373[[#This Row],[ABRIL]],Tabela373[[#This Row],[MAIO]],Tabela373[[#This Row],[JUNHO]],Tabela373[[#This Row],[JULHO]],Tabela373[[#This Row],[AGOSTO]],Tabela373[[#This Row],[SETEMBRO]],Tabela373[[#This Row],[OUTUBRO]],Tabela373[[#This Row],[NOVEMBRO]],Tabela373[[#This Row],[DEZEMBRO]]) -> #DIV/0!
C53: =IFERROR(B53/$B$3,"") | E53: =IFERROR(D53/$D$3,"") | F53: =IFERROR((D53-B53)/B53,"") | H53: =IFERROR(G53/$G$3,"") | I53: =IFERROR((G53-D53)/D53,"") | K53: =IFERROR(J53/$J$3,"") | L53: =IFERROR((J53-G53)/G53,"") | N53: =IFERROR(M53/$M$3,"") | O53: =IFERROR((M53-J53)/J53,"") | Q53: =IFERROR(P53/$P$3,"") | R53: =IFERROR((P53-M53)/M53,"") | T53: =IFERROR(S53/$S$3,"") | U53: =IFERROR((S53-P53)/P53,"") | W53: =IFERROR(V53/$V$3,"") | X53: =IFERROR((V53-S53)/S53,"") | Z53: =IFERROR(Y53/$Y$3,"") | AA53: =IFERROR((Y53-V53)/V53,"") | AC53: =IFERROR(AB53/$AB$3,"") | AD53: =IFERROR((AB53-Y53)/Y53,"") | AF53: =IFERROR(AE53/$AE$3,"") | AG53: =IFERROR((AE53-AB53)/AB53,"") | AI53: =IFERROR(AH53/$AH$3,"") | AJ53: =IFERROR((AH53-AE53)/AE53,"") | AK53: =SUM(Tabela373[[#This Row],[JANEIRO]]+Tabela373[[#This Row],[FEVEREIRO]]+Tabela373[[#This Row],[MARÇO]]+Tabela373[[#This Row],[ABRIL]]+Tabela373[[#This Row],[MAIO]]+Tabela373[[#This Row],[JUNHO]]+Tabela373[[#This Row],[JULHO]]+Tabela373[[#This Row],[AGOSTO]]+Tabela373[[#This Row],[SETEMBRO]]+Tabela373[[#This Row],[NOVEMBRO]]+Tabela373[[#This Row],[DEZEMBRO]]) -> 0 | AL53: =IFERROR(AK53/$AK$3,"") | AM53: =AVERAGE(Tabela373[[#This Row],[JANEIRO]],Tabela373[[#This Row],[FEVEREIRO]],Tabela373[[#This Row],[MARÇO]],Tabela373[[#This Row],[ABRIL]],Tabela373[[#This Row],[MAIO]],Tabela373[[#This Row],[JUNHO]],Tabela373[[#This Row],[JULHO]],Tabela373[[#This Row],[AGOSTO]],Tabela373[[#This Row],[SETEMBRO]],Tabela373[[#This Row],[OUTUBRO]],Tabela373[[#This Row],[NOVEMBRO]],Tabela373[[#This Row],[DEZEMBRO]]) -> #DIV/0!
A54: CUSTOS COM SERVIÇOS | B54: =SUM(B55:B63) -> 0 | C54: =IFERROR(B54/$B$3,"") | D54: =SUM(D55:D63) -> 0 | E54: =IFERROR(D54/$D$3,"") | F54: =IFERROR((D54-B54)/B54,"") | G54: =SUM(G55:G63) -> 0 | H54: =IFERROR(G54/$G$3,"") | I54: =IFERROR((G54-D54)/D54,"") | J54: =SUM(J55:J63) -> 0 | K54: =IFERROR(J54/$J$3,"") | L54: =IFERROR((J54-G54)/G54,"") | M54: =SUM(M55:M63) -> 0 | N54: =IFERROR(M54/$M$3,"") | O54: =IFERROR((M54-J54)/J54,"") | P54: =SUM(P55:P63) -> 0 | Q54: =IFERROR(P54/$P$3,"") | R54: =IFERROR((P54-M54)/M54,"") | S54: =SUM(S55:S63) -> 0 | T54: =IFERROR(S54/$S$3,"") | U54: =IFERROR((S54-P54)/P54,"") | V54: =SUM(V55:V63) -> 0 | W54: =IFERROR(V54/$V$3,"") | X54: =IFERROR((V54-S54)/S54,"") | Y54: =SUM(Y55:Y63) -> 0 | Z54: =IFERROR(Y54/$Y$3,"") | AA54: =IFERROR((Y54-V54)/V54,"") | AB54: =SUM(AB55:AB63) -> 0 | AC54: =IFERROR(AB54/$AB$3,"") | AD54: =IFERROR((AB54-Y54)/Y54,"") | AE54: =SUM(AE55:AE63) -> 0 | AF54: =IFERROR(AE54/$AE$3,"") | AG54: =IFERROR((AE54-AB54)/AB54,"") | AH54: =SUM(AH55:AH63) -> 0 | AI54: =IFERROR(AH54/$AH$3,"") | AJ54: =IFERROR((AH54-AE54)/AE54,"") | AK54: =SUM(Tabela373[[#This Row],[JANEIRO]]+Tabela373[[#This Row],[FEVEREIRO]]+Tabela373[[#This Row],[MARÇO]]+Tabela373[[#This Row],[ABRIL]]+Tabela373[[#This Row],[MAIO]]+Tabela373[[#This Row],[JUNHO]]+Tabela373[[#This Row],[JULHO]]+Tabela373[[#This Row],[AGOSTO]]+Tabela373[[#This Row],[SETEMBRO]]+Tabela373[[#This Row],[NOVEMBRO]]+Tabela373[[#This Row],[DEZEMBRO]]) -> 0 | AL54: =IFERROR(AK54/$AK$3,"") | AM54: =AVERAGE(Tabela373[[#This Row],[JANEIRO]],Tabela373[[#This Row],[FEVEREIRO]],Tabela373[[#This Row],[MARÇO]],Tabela373[[#This Row],[ABRIL]],Tabela373[[#This Row],[MAIO]],Tabela373[[#This Row],[JUNHO]],Tabela373[[#This Row],[JULHO]],Tabela373[[#This Row],[AGOSTO]],Tabela373[[#This Row],[SETEMBRO]],Tabela373[[#This Row],[OUTUBRO]],Tabela373[[#This Row],[NOVEMBRO]],Tabela373[[#This Row],[DEZEMBRO]]) -> 0
A55: MÃO DE OBRA AVULSA | C55: =IFERROR(B55/$B$3,"") | E55: =IFERROR(D55/$D$3,"") | F55: =IFERROR((D55-B55)/B55,"") | H55: =IFERROR(G55/$G$3,"") | I55: =IFERROR((G55-D55)/D55,"") | K55: =IFERROR(J55/$J$3,"") | L55: =IFERROR((J55-G55)/G55,"") | N55: =IFERROR(M55/$M$3,"") | O55: =IFERROR((M55-J55)/J55,"") | Q55: =IFERROR(P55/$P$3,"") | R55: =IFERROR((P55-M55)/M55,"") | T55: =IFERROR(S55/$S$3,"") | U55: =IFERROR((S55-P55)/P55,"") | W55: =IFERROR(V55/$V$3,"") | X55: =IFERROR((V55-S55)/S55,"") | Z55: =IFERROR(Y55/$Y$3,"") | AA55: =IFERROR((Y55-V55)/V55,"") | AC55: =IFERROR(AB55/$AB$3,"") | AD55: =IFERROR((AB55-Y55)/Y55,"") | AF55: =IFERROR(AE55/$AE$3,"") | AG55: =IFERROR((AE55-AB55)/AB55,"") | AI55: =IFERROR(AH55/$AH$3,"") | AJ55: =IFERROR((AH55-AE55)/AE55,"") | AK55: =SUM(Tabela373[[#This Row],[JANEIRO]]+Tabela373[[#This Row],[FEVEREIRO]]+Tabela373[[#This Row],[MARÇO]]+Tabela373[[#This Row],[ABRIL]]+Tabela373[[#This Row],[MAIO]]+Tabela373[[#This Row],[JUNHO]]+Tabela373[[#This Row],[JULHO]]+Tabela373[[#This Row],[AGOSTO]]+Tabela373[[#This Row],[SETEMBRO]]+Tabela373[[#This Row],[NOVEMBRO]]+Tabela373[[#This Row],[DEZEMBRO]]) -> 0 | AL55: =IFERROR(AK55/$AK$3,"") | AM55: =AVERAGE(Tabela373[[#This Row],[JANEIRO]],Tabela373[[#This Row],[FEVEREIRO]],Tabela373[[#This Row],[MARÇO]],Tabela373[[#This Row],[ABRIL]],Tabela373[[#This Row],[MAIO]],Tabela373[[#This Row],[JUNHO]],Tabela373[[#This Row],[JULHO]],Tabela373[[#This Row],[AGOSTO]],Tabela373[[#This Row],[SETEMBRO]],Tabela373[[#This Row],[OUTUBRO]],Tabela373[[#This Row],[NOVEMBRO]],Tabela373[[#This Row],[DEZEMBRO]]) -> #DIV/0!
A56: MÃO DE OBRA VARIÁVEL | C56: =IFERROR(B56/$B$3,"") | E56: =IFERROR(D56/$D$3,"") | F56: =IFERROR((D56-B56)/B56,"") | H56: =IFERROR(G56/$G$3,"") | I56: =IFERROR((G56-D56)/D56,"") | K56: =IFERROR(J56/$J$3,"") | L56: =IFERROR((J56-G56)/G56,"") | N56: =IFERROR(M56/$M$3,"") | O56: =IFERROR((M56-J56)/J56,"") | Q56: =IFERROR(P56/$P$3,"") | R56: =IFERROR((P56-M56)/M56,"") | T56: =IFERROR(S56/$S$3,"") | U56: =IFERROR((S56-P56)/P56,"") | W56: =IFERROR(V56/$V$3,"") | X56: =IFERROR((V56-S56)/S56,"") | Z56: =IFERROR(Y56/$Y$3,"") | AA56: =IFERROR((Y56-V56)/V56,"") | AC56: =IFERROR(AB56/$AB$3,"") | AD56: =IFERROR((AB56-Y56)/Y56,"") | AF56: =IFERROR(AE56/$AE$3,"") | AG56: =IFERROR((AE56-AB56)/AB56,"") | AI56: =IFERROR(AH56/$AH$3,"") | AJ56: =IFERROR((AH56-AE56)/AE56,"") | AK56: =SUM(Tabela373[[#This Row],[JANEIRO]]+Tabela373[[#This Row],[FEVEREIRO]]+Tabela373[[#This Row],[MARÇO]]+Tabela373[[#This Row],[ABRIL]]+Tabela373[[#This Row],[MAIO]]+Tabela373[[#This Row],[JUNHO]]+Tabela373[[#This Row],[JULHO]]+Tabela373[[#This Row],[AGOSTO]]+Tabela373[[#This Row],[SETEMBRO]]+Tabela373[[#This Row],[NOVEMBRO]]+Tabela373[[#This Row],[DEZEMBRO]]) -> 0 | AL56: =IFERROR(AK56/$AK$3,"") | AM56: =AVERAGE(Tabela373[[#This Row],[JANEIRO]],Tabela373[[#This Row],[FEVEREIRO]],Tabela373[[#This Row],[MARÇO]],Tabela373[[#This Row],[ABRIL]],Tabela373[[#This Row],[MAIO]],Tabela373[[#This Row],[JUNHO]],Tabela373[[#This Row],[JULHO]],Tabela373[[#This Row],[AGOSTO]],Tabela373[[#This Row],[SETEMBRO]],Tabela373[[#This Row],[OUTUBRO]],Tabela373[[#This Row],[NOVEMBRO]],Tabela373[[#This Row],[DEZEMBRO]]) -> #DIV/0!
A57: FRETE DE COMPRA | C57: =IFERROR(B57/$B$3,"") | E57: =IFERROR(D57/$D$3,"") | F57: =IFERROR((D57-B57)/B57,"") | H57: =IFERROR(G57/$G$3,"") | I57: =IFERROR((G57-D57)/D57,"") | K57: =IFERROR(J57/$J$3,"") | L57: =IFERROR((J57-G57)/G57,"") | N57: =IFERROR(M57/$M$3,"") | O57: =IFERROR((M57-J57)/J57,"") | Q57: =IFERROR(P57/$P$3,"") | R57: =IFERROR((P57-M57)/M57,"") | T57: =IFERROR(S57/$S$3,"") | U57: =IFERROR((S57-P57)/P57,"") | W57: =IFERROR(V57/$V$3,"") | X57: =IFERROR((V57-S57)/S57,"") | Z57: =IFERROR(Y57/$Y$3,"") | AA57: =IFERROR((Y57-V57)/V57,"") | AC57: =IFERROR(AB57/$AB$3,"") | AD57: =IFERROR((AB57-Y57)/Y57,"") | AF57: =IFERROR(AE57/$AE$3,"") | AG57: =IFERROR((AE57-AB57)/AB57,"") | AI57: =IFERROR(AH57/$AH$3,"") | AJ57: =IFERROR((AH57-AE57)/AE57,"") | AK57: =SUM(Tabela373[[#This Row],[JANEIRO]]+Tabela373[[#This Row],[FEVEREIRO]]+Tabela373[[#This Row],[MARÇO]]+Tabela373[[#This Row],[ABRIL]]+Tabela373[[#This Row],[MAIO]]+Tabela373[[#This Row],[JUNHO]]+Tabela373[[#This Row],[JULHO]]+Tabela373[[#This Row],[AGOSTO]]+Tabela373[[#This Row],[SETEMBRO]]+Tabela373[[#This Row],[NOVEMBRO]]+Tabela373[[#This Row],[DEZEMBRO]]) -> 0 | AL57: =IFERROR(AK57/$AK$3,"") | AM57: =AVERAGE(Tabela373[[#This Row],[JANEIRO]],Tabela373[[#This Row],[FEVEREIRO]],Tabela373[[#This Row],[MARÇO]],Tabela373[[#This Row],[ABRIL]],Tabela373[[#This Row],[MAIO]],Tabela373[[#This Row],[JUNHO]],Tabela373[[#This Row],[JULHO]],Tabela373[[#This Row],[AGOSTO]],Tabela373[[#This Row],[SETEMBRO]],Tabela373[[#This Row],[OUTUBRO]],Tabela373[[#This Row],[NOVEMBRO]],Tabela373[[#This Row],[DEZEMBRO]]) -> #DIV/0!
A58: SERVIÇOS TERCEIRIZADOS | C58: =IFERROR(B58/$B$3,"") | E58: =IFERROR(D58/$D$3,"") | F58: =IFERROR((D58-B58)/B58,"") | H58: =IFERROR(G58/$G$3,"") | I58: =IFERROR((G58-D58)/D58,"") | K58: =IFERROR(J58/$J$3,"") | L58: =IFERROR((J58-G58)/G58,"") | N58: =IFERROR(M58/$M$3,"") | O58: =IFERROR((M58-J58)/J58,"") | Q58: =IFERROR(P58/$P$3,"") | R58: =IFERROR((P58-M58)/M58,"") | T58: =IFERROR(S58/$S$3,"") | U58: =IFERROR((S58-P58)/P58,"") | W58: =IFERROR(V58/$V$3,"") | X58: =IFERROR((V58-S58)/S58,"") | Z58: =IFERROR(Y58/$Y$3,"") | AA58: =IFERROR((Y58-V58)/V58,"") | AC58: =IFERROR(AB58/$AB$3,"") | AD58: =IFERROR((AB58-Y58)/Y58,"") | AF58: =IFERROR(AE58/$AE$3,"") | AG58: =IFERROR((AE58-AB58)/AB58,"") | AI58: =IFERROR(AH58/$AH$3,"") | AJ58: =IFERROR((AH58-AE58)/AE58,"") | AK58: =SUM(Tabela373[[#This Row],[JANEIRO]]+Tabela373[[#This Row],[FEVEREIRO]]+Tabela373[[#This Row],[MARÇO]]+Tabela373[[#This Row],[ABRIL]]+Tabela373[[#This Row],[MAIO]]+Tabela373[[#This Row],[JUNHO]]+Tabela373[[#This Row],[JULHO]]+Tabela373[[#This Row],[AGOSTO]]+Tabela373[[#This Row],[SETEMBRO]]+Tabela373[[#This Row],[NOVEMBRO]]+Tabela373[[#This Row],[DEZEMBRO]]) -> 0 | AL58: =IFERROR(AK58/$AK$3,"") | AM58: =AVERAGE(Tabela373[[#This Row],[JANEIRO]],Tabela373[[#This Row],[FEVEREIRO]],Tabela373[[#This Row],[MARÇO]],Tabela373[[#This Row],[ABRIL]],Tabela373[[#This Row],[MAIO]],Tabela373[[#This Row],[JUNHO]],Tabela373[[#This Row],[JULHO]],Tabela373[[#This Row],[AGOSTO]],Tabela373[[#This Row],[SETEMBRO]],Tabela373[[#This Row],[OUTUBRO]],Tabela373[[#This Row],[NOVEMBRO]],Tabela373[[#This Row],[DEZEMBRO]]) -> #DIV/0!
C59: =IFERROR(B59/$B$3,"") | E59: =IFERROR(D59/$D$3,"") | F59: =IFERROR((D59-B59)/B59,"") | H59: =IFERROR(G59/$G$3,"") | I59: =IFERROR((G59-D59)/D59,"") | K59: =IFERROR(J59/$J$3,"") | L59: =IFERROR((J59-G59)/G59,"") | N59: =IFERROR(M59/$M$3,"") | O59: =IFERROR((M59-J59)/J59,"") | Q59: =IFERROR(P59/$P$3,"") | R59: =IFERROR((P59-M59)/M59,"") | T59: =IFERROR(S59/$S$3,"") | U59: =IFERROR((S59-P59)/P59,"") | W59: =IFERROR(V59/$V$3,"") | X59: =IFERROR((V59-S59)/S59,"") | Z59: =IFERROR(Y59/$Y$3,"") | AA59: =IFERROR((Y59-V59)/V59,"") | AC59: =IFERROR(AB59/$AB$3,"") | AD59: =IFERROR((AB59-Y59)/Y59,"") | AF59: =IFERROR(AE59/$AE$3,"") | AG59: =IFERROR((AE59-AB59)/AB59,"") | AI59: =IFERROR(AH59/$AH$3,"") | AJ59: =IFERROR((AH59-AE59)/AE59,"") | AK59: =SUM(Tabela373[[#This Row],[JANEIRO]]+Tabela373[[#This Row],[FEVEREIRO]]+Tabela373[[#This Row],[MARÇO]]+Tabela373[[#This Row],[ABRIL]]+Tabela373[[#This Row],[MAIO]]+Tabela373[[#This Row],[JUNHO]]+Tabela373[[#This Row],[JULHO]]+Tabela373[[#This Row],[AGOSTO]]+Tabela373[[#This Row],[SETEMBRO]]+Tabela373[[#This Row],[NOVEMBRO]]+Tabela373[[#This Row],[DEZEMBRO]]) -> 0 | AL59: =IFERROR(AK59/$AK$3,"") | AM59: =AVERAGE(Tabela373[[#This Row],[JANEIRO]],Tabela373[[#This Row],[FEVEREIRO]],Tabela373[[#This Row],[MARÇO]],Tabela373[[#This Row],[ABRIL]],Tabela373[[#This Row],[MAIO]],Tabela373[[#This Row],[JUNHO]],Tabela373[[#This Row],[JULHO]],Tabela373[[#This Row],[AGOSTO]],Tabela373[[#This Row],[SETEMBRO]],Tabela373[[#This Row],[OUTUBRO]],Tabela373[[#This Row],[NOVEMBRO]],Tabela373[[#This Row],[DEZEMBRO]]) -> #DIV/0!
A60: CUSTOS COM FROTA | B60: =SUM(B61:B69) -> 0 | C60: =IFERROR(B60/$B$3,"") | D60: =SUM(D61:D69) -> 0 | E60: =IFERROR(D60/$D$3,"") | F60: =IFERROR((D60-B60)/B60,"") | G60: =SUM(G61:G69) -> 0 | H60: =IFERROR(G60/$G$3,"") | I60: =IFERROR((G60-D60)/D60,"") | J60: =SUM(J61:J69) -> 0 | K60: =IFERROR(J60/$J$3,"") | L60: =IFERROR((J60-G60)/G60,"") | M60: =SUM(M61:M69) -> 0 | N60: =IFERROR(M60/$M$3,"") | O60: =IFERROR((M60-J60)/J60,"") | P60: =SUM(P61:P69) -> 0 | Q60: =IFERROR(P60/$P$3,"") | R60: =IFERROR((P60-M60)/M60,"") | S60: =SUM(S61:S69) -> 0 | T60: =IFERROR(S60/$S$3,"") | U60: =IFERROR((S60-P60)/P60,"") | V60: =SUM(V61:V69) -> 0 | W60: =IFERROR(V60/$V$3,"") | X60: =IFERROR((V60-S60)/S60,"") | Y60: =SUM(Y61:Y69) -> 0 | Z60: =IFERROR(Y60/$Y$3,"") | AA60: =IFERROR((Y60-V60)/V60,"") | AB60: =SUM(AB61:AB69) -> 0 | AC60: =IFERROR(AB60/$AB$3,"") | AD60: =IFERROR((AB60-Y60)/Y60,"") | AE60: =SUM(AE61:AE69) -> 0 | AF60: =IFERROR(AE60/$AE$3,"") | AG60: =IFERROR((AE60-AB60)/AB60,"") | AH60: =SUM(AH61:AH69) -> 0 | AI60: =IFERROR(AH60/$AH$3,"") | AJ60: =IFERROR((AH60-AE60)/AE60,"") | AK60: =SUM(Tabela373[[#This Row],[JANEIRO]]+Tabela373[[#This Row],[FEVEREIRO]]+Tabela373[[#This Row],[MARÇO]]+Tabela373[[#This Row],[ABRIL]]+Tabela373[[#This Row],[MAIO]]+Tabela373[[#This Row],[JUNHO]]+Tabela373[[#This Row],[JULHO]]+Tabela373[[#This Row],[AGOSTO]]+Tabela373[[#This Row],[SETEMBRO]]+Tabela373[[#This Row],[NOVEMBRO]]+Tabela373[[#This Row],[DEZEMBRO]]) -> 0 | AL60: =IFERROR(AK60/$AK$3,"") | AM60: =AVERAGE(Tabela373[[#This Row],[JANEIRO]],Tabela373[[#This Row],[FEVEREIRO]],Tabela373[[#This Row],[MARÇO]],Tabela373[[#This Row],[ABRIL]],Tabela373[[#This Row],[MAIO]],Tabela373[[#This Row],[JUNHO]],Tabela373[[#This Row],[JULHO]],Tabela373[[#This Row],[AGOSTO]],Tabela373[[#This Row],[SETEMBRO]],Tabela373[[#This Row],[OUTUBRO]],Tabela373[[#This Row],[NOVEMBRO]],Tabela373[[#This Row],[DEZEMBRO]]) -> 0
A61: MANUTENÇÃO DA FROTA | C61: =IFERROR(B61/$B$3,"") | E61: =IFERROR(D61/$D$3,"") | F61: =IFERROR((D61-B61)/B61,"") | H61: =IFERROR(G61/$G$3,"") | I61: =IFERROR((G61-D61)/D61,"") | K61: =IFERROR(J61/$J$3,"") | L61: =IFERROR((J61-G61)/G61,"") | N61: =IFERROR(M61/$M$3,"") | O61: =IFERROR((M61-J61)/J61,"") | Q61: =IFERROR(P61/$P$3,"") | R61: =IFERROR((P61-M61)/M61,"") | T61: =IFERROR(S61/$S$3,"") | U61: =IFERROR((S61-P61)/P61,"") | W61: =IFERROR(V61/$V$3,"") | X61: =IFERROR((V61-S61)/S61,"") | Z61: =IFERROR(Y61/$Y$3,"") | AA61: =IFERROR((Y61-V61)/V61,"") | AC61: =IFERROR(AB61/$AB$3,"") | AD61: =IFERROR((AB61-Y61)/Y61,"") | AF61: =IFERROR(AE61/$AE$3,"") | AG61: =IFERROR((AE61-AB61)/AB61,"") | AI61: =IFERROR(AH61/$AH$3,"") | AJ61: =IFERROR((AH61-AE61)/AE61,"") | AK61: =SUM(Tabela373[[#This Row],[JANEIRO]]+Tabela373[[#This Row],[FEVEREIRO]]+Tabela373[[#This Row],[MARÇO]]+Tabela373[[#This Row],[ABRIL]]+Tabela373[[#This Row],[MAIO]]+Tabela373[[#This Row],[JUNHO]]+Tabela373[[#This Row],[JULHO]]+Tabela373[[#This Row],[AGOSTO]]+Tabela373[[#This Row],[SETEMBRO]]+Tabela373[[#This Row],[NOVEMBRO]]+Tabela373[[#This Row],[DEZEMBRO]]) -> 0 | AL61: =IFERROR(AK61/$AK$3,"") | AM61: =AVERAGE(Tabela373[[#This Row],[JANEIRO]],Tabela373[[#This Row],[FEVEREIRO]],Tabela373[[#This Row],[MARÇO]],Tabela373[[#This Row],[ABRIL]],Tabela373[[#This Row],[MAIO]],Tabela373[[#This Row],[JUNHO]],Tabela373[[#This Row],[JULHO]],Tabela373[[#This Row],[AGOSTO]],Tabela373[[#This Row],[SETEMBRO]],Tabela373[[#This Row],[OUTUBRO]],Tabela373[[#This Row],[NOVEMBRO]],Tabela373[[#This Row],[DEZEMBRO]]) -> #DIV/0!
A62: COMBUSTÍVEL | C62: =IFERROR(B62/$B$3,"") | E62: =IFERROR(D62/$D$3,"") | F62: =IFERROR((D62-B62)/B62,"") | H62: =IFERROR(G62/$G$3,"") | I62: =IFERROR((G62-D62)/D62,"") | K62: =IFERROR(J62/$J$3,"") | L62: =IFERROR((J62-G62)/G62,"") | N62: =IFERROR(M62/$M$3,"") | O62: =IFERROR((M62-J62)/J62,"") | Q62: =IFERROR(P62/$P$3,"") | R62: =IFERROR((P62-M62)/M62,"") | T62: =IFERROR(S62/$S$3,"") | U62: =IFERROR((S62-P62)/P62,"") | W62: =IFERROR(V62/$V$3,"") | X62: =IFERROR((V62-S62)/S62,"") | Z62: =IFERROR(Y62/$Y$3,"") | AA62: =IFERROR((Y62-V62)/V62,"") | AC62: =IFERROR(AB62/$AB$3,"") | AD62: =IFERROR((AB62-Y62)/Y62,"") | AF62: =IFERROR(AE62/$AE$3,"") | AG62: =IFERROR((AE62-AB62)/AB62,"") | AI62: =IFERROR(AH62/$AH$3,"") | AJ62: =IFERROR((AH62-AE62)/AE62,"") | AK62: =SUM(Tabela373[[#This Row],[JANEIRO]]+Tabela373[[#This Row],[FEVEREIRO]]+Tabela373[[#This Row],[MARÇO]]+Tabela373[[#This Row],[ABRIL]]+Tabela373[[#This Row],[MAIO]]+Tabela373[[#This Row],[JUNHO]]+Tabela373[[#This Row],[JULHO]]+Tabela373[[#This Row],[AGOSTO]]+Tabela373[[#This Row],[SETEMBRO]]+Tabela373[[#This Row],[NOVEMBRO]]+Tabela373[[#This Row],[DEZEMBRO]]) -> 0 | AL62: =IFERROR(AK62/$AK$3,"") | AM62: =AVERAGE(Tabela373[[#This Row],[JANEIRO]],Tabela373[[#This Row],[FEVEREIRO]],Tabela373[[#This Row],[MARÇO]],Tabela373[[#This Row],[ABRIL]],Tabela373[[#This Row],[MAIO]],Tabela373[[#This Row],[JUNHO]],Tabela373[[#This Row],[JULHO]],Tabela373[[#This Row],[AGOSTO]],Tabela373[[#This Row],[SETEMBRO]],Tabela373[[#This Row],[OUTUBRO]],Tabela373[[#This Row],[NOVEMBRO]],Tabela373[[#This Row],[DEZEMBRO]]) -> #DIV/0!
C63: =IFERROR(B63/$B$3,"") | E63: =IFERROR(D63/$D$3,"") | F63: =IFERROR((D63-B63)/B63,"") | H63: =IFERROR(G63/$G$3,"") | I63: =IFERROR((G63-D63)/D63,"") | K63: =IFERROR(J63/$J$3,"") | L63: =IFERROR((J63-G63)/G63,"") | N63: =IFERROR(M63/$M$3,"") | O63: =IFERROR((M63-J63)/J63,"") | Q63: =IFERROR(P63/$P$3,"") | R63: =IFERROR((P63-M63)/M63,"") | T63: =IFERROR(S63/$S$3,"") | U63: =IFERROR((S63-P63)/P63,"") | W63: =IFERROR(V63/$V$3,"") | X63: =IFERROR((V63-S63)/S63,"") | Z63: =IFERROR(Y63/$Y$3,"") | AA63: =IFERROR((Y63-V63)/V63,"") | AC63: =IFERROR(AB63/$AB$3,"") | AD63: =IFERROR((AB63-Y63)/Y63,"") | AF63: =IFERROR(AE63/$AE$3,"") | AG63: =IFERROR((AE63-AB63)/AB63,"") | AI63: =IFERROR(AH63/$AH$3,"") | AJ63: =IFERROR((AH63-AE63)/AE63,"") | AK63: =SUM(Tabela373[[#This Row],[JANEIRO]]+Tabela373[[#This Row],[FEVEREIRO]]+Tabela373[[#This Row],[MARÇO]]+Tabela373[[#This Row],[ABRIL]]+Tabela373[[#This Row],[MAIO]]+Tabela373[[#This Row],[JUNHO]]+Tabela373[[#This Row],[JULHO]]+Tabela373[[#This Row],[AGOSTO]]+Tabela373[[#This Row],[SETEMBRO]]+Tabela373[[#This Row],[NOVEMBRO]]+Tabela373[[#This Row],[DEZEMBRO]]) -> 0 | AL63: =IFERROR(AK63/$AK$3,"") | AM63: =AVERAGE(Tabela373[[#This Row],[JANEIRO]],Tabela373[[#This Row],[FEVEREIRO]],Tabela373[[#This Row],[MARÇO]],Tabela373[[#This Row],[ABRIL]],Tabela373[[#This Row],[MAIO]],Tabela373[[#This Row],[JUNHO]],Tabela373[[#This Row],[JULHO]],Tabela373[[#This Row],[AGOSTO]],Tabela373[[#This Row],[SETEMBRO]],Tabela373[[#This Row],[OUTUBRO]],Tabela373[[#This Row],[NOVEMBRO]],Tabela373[[#This Row],[DEZEMBRO]]) -> #DIV/0!
A64: (-) DESPESAS COM VENDA | B64: =B65+B70+B75+B80 -> 0 | C64: =IFERROR(B64/$B$3,"") | D64: =D65+D70+D75+D80 -> 0 | E64: =IFERROR(D64/$D$3,"") | F64: =IFERROR((D64-B64)/B64,"") | G64: =G65+G70+G75+G80 -> 0 | H64: =IFERROR(G64/$G$3,"") | I64: =IFERROR((G64-D64)/D64,"") | J64: =J65+J70+J75+J80 -> 0 | K64: =IFERROR(J64/$J$3,"") | L64: =IFERROR((J64-G64)/G64,"") | M64: =M65+M70+M75+M80 -> 0 | N64: =IFERROR(M64/$M$3,"") | O64: =IFERROR((M64-J64)/J64,"") | P64: =P65+P70+P75+P80 -> 0 | Q64: =IFERROR(P64/$P$3,"") | R64: =IFERROR((P64-M64)/M64,"") | S64: =S65+S70+S75+S80 -> 0 | T64: =IFERROR(S64/$S$3,"") | U64: =IFERROR((S64-P64)/P64,"") | V64: =V65+V70+V75+V80 -> 0 | W64: =IFERROR(V64/$V$3,"") | X64: =IFERROR((V64-S64)/S64,"") | Y64: =Y65+Y70+Y75+Y80 -> 0 | Z64: =IFERROR(Y64/$Y$3,"") | AA64: =IFERROR((Y64-V64)/V64,"") | AB64: =AB65+AB70+AB75+AB80 -> 0 | AC64: =IFERROR(AB64/$AB$3,"") | AD64: =IFERROR((AB64-Y64)/Y64,"") | AE64: =AE65+AE70+AE75+AE80 -> 0 | AF64: =IFERROR(AE64/$AE$3,"") | AG64: =IFERROR((AE64-AB64)/AB64,"") | AH64: =AH65+AH70+AH75+AH80 -> 0 | AI64: =IFERROR(AH64/$AH$3,"") | AJ64: =IFERROR((AH64-AE64)/AE64,"") | AK64: =SUM(Tabela373[[#This Row],[JANEIRO]]+Tabela373[[#This Row],[FEVEREIRO]]+Tabela373[[#This Row],[MARÇO]]+Tabela373[[#This Row],[ABRIL]]+Tabela373[[#This Row],[MAIO]]+Tabela373[[#This Row],[JUNHO]]+Tabela373[[#This Row],[JULHO]]+Tabela373[[#This Row],[AGOSTO]]+Tabela373[[#This Row],[SETEMBRO]]+Tabela373[[#This Row],[NOVEMBRO]]+Tabela373[[#This Row],[DEZEMBRO]]) -> 0 | AL64: =IFERROR(AK64/$AK$3,"") | AM64: =AVERAGE(Tabela373[[#This Row],[JANEIRO]],Tabela373[[#This Row],[FEVEREIRO]],Tabela373[[#This Row],[MARÇO]],Tabela373[[#This Row],[ABRIL]],Tabela373[[#This Row],[MAIO]],Tabela373[[#This Row],[JUNHO]],Tabela373[[#This Row],[JULHO]],Tabela373[[#This Row],[AGOSTO]],Tabela373[[#This Row],[SETEMBRO]],Tabela373[[#This Row],[OUTUBRO]],Tabela373[[#This Row],[NOVEMBRO]],Tabela373[[#This Row],[DEZEMBRO]]) -> 0
A65: COMISSÕES | B65: =SUM(B66:B69) -> 0 | C65: =IFERROR(B65/$B$3,"") | D65: =SUM(D66:D69) -> 0 | E65: =IFERROR(D65/$D$3,"") | F65: =IFERROR((D65-B65)/B65,"") | G65: =SUM(G66:G69) -> 0 | H65: =IFERROR(G65/$G$3,"") | I65: =IFERROR((G65-D65)/D65,"") | J65: =SUM(J66:J69) -> 0 | K65: =IFERROR(J65/$J$3,"") | L65: =IFERROR((J65-G65)/G65,"") | M65: =SUM(M66:M69) -> 0 | N65: =IFERROR(M65/$M$3,"") | O65: =IFERROR((M65-J65)/J65,"") | P65: =SUM(P66:P69) -> 0 | Q65: =IFERROR(P65/$P$3,"") | R65: =IFERROR((P65-M65)/M65,"") | S65: =SUM(S66:S69) -> 0 | T65: =IFERROR(S65/$S$3,"") | U65: =IFERROR((S65-P65)/P65,"") | V65: =SUM(V66:V69) -> 0 | W65: =IFERROR(V65/$V$3,"") | X65: =IFERROR((V65-S65)/S65,"") | Y65: =SUM(Y66:Y69) -> 0 | Z65: =IFERROR(Y65/$Y$3,"") | AA65: =IFERROR((Y65-V65)/V65,"") | AB65: =SUM(AB66:AB69) -> 0 | AC65: =IFERROR(AB65/$AB$3,"") | AD65: =IFERROR((AB65-Y65)/Y65,"") | AE65: =SUM(AE66:AE69) -> 0 | AF65: =IFERROR(AE65/$AE$3,"") | AG65: =IFERROR((AE65-AB65)/AB65,"") | AH65: =SUM(AH66:AH69) -> 0 | AI65: =IFERROR(AH65/$AH$3,"") | AJ65: =IFERROR((AH65-AE65)/AE65,"") | AK65: =SUM(Tabela373[[#This Row],[JANEIRO]]+Tabela373[[#This Row],[FEVEREIRO]]+Tabela373[[#This Row],[MARÇO]]+Tabela373[[#This Row],[ABRIL]]+Tabela373[[#This Row],[MAIO]]+Tabela373[[#This Row],[JUNHO]]+Tabela373[[#This Row],[JULHO]]+Tabela373[[#This Row],[AGOSTO]]+Tabela373[[#This Row],[SETEMBRO]]+Tabela373[[#This Row],[NOVEMBRO]]+Tabela373[[#This Row],[DEZEMBRO]]) -> 0 | AL65: =IFERROR(AK65/$AK$3,"") | AM65: =AVERAGE(Tabela373[[#This Row],[JANEIRO]],Tabela373[[#This Row],[FEVEREIRO]],Tabela373[[#This Row],[MARÇO]],Tabela373[[#This Row],[ABRIL]],Tabela373[[#This Row],[MAIO]],Tabela373[[#This Row],[JUNHO]],Tabela373[[#This Row],[JULHO]],Tabela373[[#This Row],[AGOSTO]],Tabela373[[#This Row],[SETEMBRO]],Tabela373[[#This Row],[OUTUBRO]],Tabela373[[#This Row],[NOVEMBRO]],Tabela373[[#This Row],[DEZEMBRO]]) -> 0
A66: BONIFICAÇÃO POR META | C66: =IFERROR(B66/$B$3,"") | E66: =IFERROR(D66/$D$3,"") | F66: =IFERROR((D66-B66)/B66,"") | H66: =IFERROR(G66/$G$3,"") | I66: =IFERROR((G66-D66)/D66,"") | K66: =IFERROR(J66/$J$3,"") | L66: =IFERROR((J66-G66)/G66,"") | N66: =IFERROR(M66/$M$3,"") | O66: =IFERROR((M66-J66)/J66,"") | Q66: =IFERROR(P66/$P$3,"") | R66: =IFERROR((P66-M66)/M66,"") | T66: =IFERROR(S66/$S$3,"") | U66: =IFERROR((S66-P66)/P66,"") | W66: =IFERROR(V66/$V$3,"") | X66: =IFERROR((V66-S66)/S66,"") | Z66: =IFERROR(Y66/$Y$3,"") | AA66: =IFERROR((Y66-V66)/V66,"") | AC66: =IFERROR(AB66/$AB$3,"") | AD66: =IFERROR((AB66-Y66)/Y66,"") | AF66: =IFERROR(AE66/$AE$3,"") | AG66: =IFERROR((AE66-AB66)/AB66,"") | AI66: =IFERROR(AH66/$AH$3,"") | AJ66: =IFERROR((AH66-AE66)/AE66,"") | AK66: =SUM(Tabela373[[#This Row],[JANEIRO]]+Tabela373[[#This Row],[FEVEREIRO]]+Tabela373[[#This Row],[MARÇO]]+Tabela373[[#This Row],[ABRIL]]+Tabela373[[#This Row],[MAIO]]+Tabela373[[#This Row],[JUNHO]]+Tabela373[[#This Row],[JULHO]]+Tabela373[[#This Row],[AGOSTO]]+Tabela373[[#This Row],[SETEMBRO]]+Tabela373[[#This Row],[NOVEMBRO]]+Tabela373[[#This Row],[DEZEMBRO]]) -> 0 | AL66: =IFERROR(AK66/$AK$3,"") | AM66: =AVERAGE(Tabela373[[#This Row],[JANEIRO]],Tabela373[[#This Row],[FEVEREIRO]],Tabela373[[#This Row],[MARÇO]],Tabela373[[#This Row],[ABRIL]],Tabela373[[#This Row],[MAIO]],Tabela373[[#This Row],[JUNHO]],Tabela373[[#This Row],[JULHO]],Tabela373[[#This Row],[AGOSTO]],Tabela373[[#This Row],[SETEMBRO]],Tabela373[[#This Row],[OUTUBRO]],Tabela373[[#This Row],[NOVEMBRO]],Tabela373[[#This Row],[DEZEMBRO]]) -> #DIV/0!
A67: COMISSÃO VENDEDORES | C67: =IFERROR(B67/$B$3,"") | E67: =IFERROR(D67/$D$3,"") | F67: =IFERROR((D67-B67)/B67,"") | H67: =IFERROR(G67/$G$3,"") | I67: =IFERROR((G67-D67)/D67,"") | K67: =IFERROR(J67/$J$3,"") | L67: =IFERROR((J67-G67)/G67,"") | N67: =IFERROR(M67/$M$3,"") | O67: =IFERROR((M67-J67)/J67,"") | Q67: =IFERROR(P67/$P$3,"") | R67: =IFERROR((P67-M67)/M67,"") | T67: =IFERROR(S67/$S$3,"") | U67: =IFERROR((S67-P67)/P67,"") | W67: =IFERROR(V67/$V$3,"") | X67: =IFERROR((V67-S67)/S67,"") | Z67: =IFERROR(Y67/$Y$3,"") | AA67: =IFERROR((Y67-V67)/V67,"") | AC67: =IFERROR(AB67/$AB$3,"") | AD67: =IFERROR((AB67-Y67)/Y67,"") | AF67: =IFERROR(AE67/$AE$3,"") | AG67: =IFERROR((AE67-AB67)/AB67,"") | AI67: =IFERROR(AH67/$AH$3,"") | AJ67: =IFERROR((AH67-AE67)/AE67,"") | AK67: =SUM(Tabela373[[#This Row],[JANEIRO]]+Tabela373[[#This Row],[FEVEREIRO]]+Tabela373[[#This Row],[MARÇO]]+Tabela373[[#This Row],[ABRIL]]+Tabela373[[#This Row],[MAIO]]+Tabela373[[#This Row],[JUNHO]]+Tabela373[[#This Row],[JULHO]]+Tabela373[[#This Row],[AGOSTO]]+Tabela373[[#This Row],[SETEMBRO]]+Tabela373[[#This Row],[NOVEMBRO]]+Tabela373[[#This Row],[DEZEMBRO]]) -> 0 | AL67: =IFERROR(AK67/$AK$3,"") | AM67: =AVERAGE(Tabela373[[#This Row],[JANEIRO]],Tabela373[[#This Row],[FEVEREIRO]],Tabela373[[#This Row],[MARÇO]],Tabela373[[#This Row],[ABRIL]],Tabela373[[#This Row],[MAIO]],Tabela373[[#This Row],[JUNHO]],Tabela373[[#This Row],[JULHO]],Tabela373[[#This Row],[AGOSTO]],Tabela373[[#This Row],[SETEMBRO]],Tabela373[[#This Row],[OUTUBRO]],Tabela373[[#This Row],[NOVEMBRO]],Tabela373[[#This Row],[DEZEMBRO]]) -> #DIV/0!
A68: COMISSÃO REPRESENTANTES | C68: =IFERROR(B68/$B$3,"") | E68: =IFERROR(D68/$D$3,"") | F68: =IFERROR((D68-B68)/B68,"") | H68: =IFERROR(G68/$G$3,"") | I68: =IFERROR((G68-D68)/D68,"") | K68: =IFERROR(J68/$J$3,"") | L68: =IFERROR((J68-G68)/G68,"") | N68: =IFERROR(M68/$M$3,"") | O68: =IFERROR((M68-J68)/J68,"") | Q68: =IFERROR(P68/$P$3,"") | R68: =IFERROR((P68-M68)/M68,"") | T68: =IFERROR(S68/$S$3,"") | U68: =IFERROR((S68-P68)/P68,"") | W68: =IFERROR(V68/$V$3,"") | X68: =IFERROR((V68-S68)/S68,"") | Z68: =IFERROR(Y68/$Y$3,"") | AA68: =IFERROR((Y68-V68)/V68,"") | AC68: =IFERROR(AB68/$AB$3,"") | AD68: =IFERROR((AB68-Y68)/Y68,"") | AF68: =IFERROR(AE68/$AE$3,"") | AG68: =IFERROR((AE68-AB68)/AB68,"") | AI68: =IFERROR(AH68/$AH$3,"") | AJ68: =IFERROR((AH68-AE68)/AE68,"") | AK68: =SUM(Tabela373[[#This Row],[JANEIRO]]+Tabela373[[#This Row],[FEVEREIRO]]+Tabela373[[#This Row],[MARÇO]]+Tabela373[[#This Row],[ABRIL]]+Tabela373[[#This Row],[MAIO]]+Tabela373[[#This Row],[JUNHO]]+Tabela373[[#This Row],[JULHO]]+Tabela373[[#This Row],[AGOSTO]]+Tabela373[[#This Row],[SETEMBRO]]+Tabela373[[#This Row],[NOVEMBRO]]+Tabela373[[#This Row],[DEZEMBRO]]) -> 0 | AL68: =IFERROR(AK68/$AK$3,"") | AM68: =AVERAGE(Tabela373[[#This Row],[JANEIRO]],Tabela373[[#This Row],[FEVEREIRO]],Tabela373[[#This Row],[MARÇO]],Tabela373[[#This Row],[ABRIL]],Tabela373[[#This Row],[MAIO]],Tabela373[[#This Row],[JUNHO]],Tabela373[[#This Row],[JULHO]],Tabela373[[#This Row],[AGOSTO]],Tabela373[[#This Row],[SETEMBRO]],Tabela373[[#This Row],[OUTUBRO]],Tabela373[[#This Row],[NOVEMBRO]],Tabela373[[#This Row],[DEZEMBRO]]) -> #DIV/0!
C69: =IFERROR(B69/$B$3,"") | E69: =IFERROR(D69/$D$3,"") | F69: =IFERROR((D69-B69)/B69,"") | H69: =IFERROR(G69/$G$3,"") | I69: =IFERROR((G69-D69)/D69,"") | K69: =IFERROR(J69/$J$3,"") | L69: =IFERROR((J69-G69)/G69,"") | N69: =IFERROR(M69/$M$3,"") | O69: =IFERROR((M69-J69)/J69,"") | Q69: =IFERROR(P69/$P$3,"") | R69: =IFERROR((P69-M69)/M69,"") | T69: =IFERROR(S69/$S$3,"") | U69: =IFERROR((S69-P69)/P69,"") | W69: =IFERROR(V69/$V$3,"") | X69: =IFERROR((V69-S69)/S69,"") | Z69: =IFERROR(Y69/$Y$3,"") | AA69: =IFERROR((Y69-V69)/V69,"") | AC69: =IFERROR(AB69/$AB$3,"") | AD69: =IFERROR((AB69-Y69)/Y69,"") | AF69: =IFERROR(AE69/$AE$3,"") | AG69: =IFERROR((AE69-AB69)/AB69,"") | AI69: =IFERROR(AH69/$AH$3,"") | AJ69: =IFERROR((AH69-AE69)/AE69,"") | AK69: =SUM(Tabela373[[#This Row],[JANEIRO]]+Tabela373[[#This Row],[FEVEREIRO]]+Tabela373[[#This Row],[MARÇO]]+Tabela373[[#This Row],[ABRIL]]+Tabela373[[#This Row],[MAIO]]+Tabela373[[#This Row],[JUNHO]]+Tabela373[[#This Row],[JULHO]]+Tabela373[[#This Row],[AGOSTO]]+Tabela373[[#This Row],[SETEMBRO]]+Tabela373[[#This Row],[NOVEMBRO]]+Tabela373[[#This Row],[DEZEMBRO]]) -> 0 | AL69: =IFERROR(AK69/$AK$3,"") | AM69: =AVERAGE(Tabela373[[#This Row],[JANEIRO]],Tabela373[[#This Row],[FEVEREIRO]],Tabela373[[#This Row],[MARÇO]],Tabela373[[#This Row],[ABRIL]],Tabela373[[#This Row],[MAIO]],Tabela373[[#This Row],[JUNHO]],Tabela373[[#This Row],[JULHO]],Tabela373[[#This Row],[AGOSTO]],Tabela373[[#This Row],[SETEMBRO]],Tabela373[[#This Row],[OUTUBRO]],Tabela373[[#This Row],[NOVEMBRO]],Tabela373[[#This Row],[DEZEMBRO]]) -> #DIV/0!
A70: LOGÍSTICA DE VENDA | B70: =SUM(B71:B74) -> 0 | C70: =IFERROR(B70/$B$3,"") | D70: =SUM(D71:D74) -> 0 | E70: =IFERROR(D70/$D$3,"") | F70: =IFERROR((D70-B70)/B70,"") | G70: =SUM(G71:G74) -> 0 | H70: =IFERROR(G70/$G$3,"") | I70: =IFERROR((G70-D70)/D70,"") | J70: =SUM(J71:J74) -> 0 | K70: =IFERROR(J70/$J$3,"") | L70: =IFERROR((J70-G70)/G70,"") | M70: =SUM(M71:M74) -> 0 | N70: =IFERROR(M70/$M$3,"") | O70: =IFERROR((M70-J70)/J70,"") | P70: =SUM(P71:P74) -> 0 | Q70: =IFERROR(P70/$P$3,"") | R70: =IFERROR((P70-M70)/M70,"") | S70: =SUM(S71:S74) -> 0 | T70: =IFERROR(S70/$S$3,"") | U70: =IFERROR((S70-P70)/P70,"") | V70: =SUM(V71:V74) -> 0 | W70: =IFERROR(V70/$V$3,"") | X70: =IFERROR((V70-S70)/S70,"") | Y70: =SUM(Y71:Y74) -> 0 | Z70: =IFERROR(Y70/$Y$3,"") | AA70: =IFERROR((Y70-V70)/V70,"") | AB70: =SUM(AB71:AB74) -> 0 | AC70: =IFERROR(AB70/$AB$3,"") | AD70: =IFERROR((AB70-Y70)/Y70,"") | AE70: =SUM(AE71:AE74) -> 0 | AF70: =IFERROR(AE70/$AE$3,"") | AG70: =IFERROR((AE70-AB70)/AB70,"") | AH70: =SUM(AH71:AH74) -> 0 | AI70: =IFERROR(AH70/$AH$3,"") | AJ70: =IFERROR((AH70-AE70)/AE70,"") | AK70: =SUM(Tabela373[[#This Row],[JANEIRO]]+Tabela373[[#This Row],[FEVEREIRO]]+Tabela373[[#This Row],[MARÇO]]+Tabela373[[#This Row],[ABRIL]]+Tabela373[[#This Row],[MAIO]]+Tabela373[[#This Row],[JUNHO]]+Tabela373[[#This Row],[JULHO]]+Tabela373[[#This Row],[AGOSTO]]+Tabela373[[#This Row],[SETEMBRO]]+Tabela373[[#This Row],[NOVEMBRO]]+Tabela373[[#This Row],[DEZEMBRO]]) -> 0 | AL70: =IFERROR(AK70/$AK$3,"") | AM70: =AVERAGE(Tabela373[[#This Row],[JANEIRO]],Tabela373[[#This Row],[FEVEREIRO]],Tabela373[[#This Row],[MARÇO]],Tabela373[[#This Row],[ABRIL]],Tabela373[[#This Row],[MAIO]],Tabela373[[#This Row],[JUNHO]],Tabela373[[#This Row],[JULHO]],Tabela373[[#This Row],[AGOSTO]],Tabela373[[#This Row],[SETEMBRO]],Tabela373[[#This Row],[OUTUBRO]],Tabela373[[#This Row],[NOVEMBRO]],Tabela373[[#This Row],[DEZEMBRO]]) -> 0
A71: EMBALAGENS DE VENDA | C71: =IFERROR(B71/$B$3,"") | E71: =IFERROR(D71/$D$3,"") | F71: =IFERROR((D71-B71)/B71,"") | H71: =IFERROR(G71/$G$3,"") | I71: =IFERROR((G71-D71)/D71,"") | K71: =IFERROR(J71/$J$3,"") | L71: =IFERROR((J71-G71)/G71,"") | N71: =IFERROR(M71/$M$3,"") | O71: =IFERROR((M71-J71)/J71,"") | Q71: =IFERROR(P71/$P$3,"") | R71: =IFERROR((P71-M71)/M71,"") | T71: =IFERROR(S71/$S$3,"") | U71: =IFERROR((S71-P71)/P71,"") | W71: =IFERROR(V71/$V$3,"") | X71: =IFERROR((V71-S71)/S71,"") | Z71: =IFERROR(Y71/$Y$3,"") | AA71: =IFERROR((Y71-V71)/V71,"") | AC71: =IFERROR(AB71/$AB$3,"") | AD71: =IFERROR((AB71-Y71)/Y71,"") | AF71: =IFERROR(AE71/$AE$3,"") | AG71: =IFERROR((AE71-AB71)/AB71,"") | AI71: =IFERROR(AH71/$AH$3,"") | AJ71: =IFERROR((AH71-AE71)/AE71,"") | AK71: =SUM(Tabela373[[#This Row],[JANEIRO]]+Tabela373[[#This Row],[FEVEREIRO]]+Tabela373[[#This Row],[MARÇO]]+Tabela373[[#This Row],[ABRIL]]+Tabela373[[#This Row],[MAIO]]+Tabela373[[#This Row],[JUNHO]]+Tabela373[[#This Row],[JULHO]]+Tabela373[[#This Row],[AGOSTO]]+Tabela373[[#This Row],[SETEMBRO]]+Tabela373[[#This Row],[NOVEMBRO]]+Tabela373[[#This Row],[DEZEMBRO]]) -> 0 | AL71: =IFERROR(AK71/$AK$3,"") | AM71: =AVERAGE(Tabela373[[#This Row],[JANEIRO]],Tabela373[[#This Row],[FEVEREIRO]],Tabela373[[#This Row],[MARÇO]],Tabela373[[#This Row],[ABRIL]],Tabela373[[#This Row],[MAIO]],Tabela373[[#This Row],[JUNHO]],Tabela373[[#This Row],[JULHO]],Tabela373[[#This Row],[AGOSTO]],Tabela373[[#This Row],[SETEMBRO]],Tabela373[[#This Row],[OUTUBRO]],Tabela373[[#This Row],[NOVEMBRO]],Tabela373[[#This Row],[DEZEMBRO]]) -> #DIV/0!
A72: FRETE DE ENTREGA | C72: =IFERROR(B72/$B$3,"") | E72: =IFERROR(D72/$D$3,"") | F72: =IFERROR((D72-B72)/B72,"") | H72: =IFERROR(G72/$G$3,"") | I72: =IFERROR((G72-D72)/D72,"") | K72: =IFERROR(J72/$J$3,"") | L72: =IFERROR((J72-G72)/G72,"") | N72: =IFERROR(M72/$M$3,"") | O72: =IFERROR((M72-J72)/J72,"") | Q72: =IFERROR(P72/$P$3,"") | R72: =IFERROR((P72-M72)/M72,"") | T72: =IFERROR(S72/$S$3,"") | U72: =IFERROR((S72-P72)/P72,"") | W72: =IFERROR(V72/$V$3,"") | X72: =IFERROR((V72-S72)/S72,"") | Z72: =IFERROR(Y72/$Y$3,"") | AA72: =IFERROR((Y72-V72)/V72,"") | AC72: =IFERROR(AB72/$AB$3,"") | AD72: =IFERROR((AB72-Y72)/Y72,"") | AF72: =IFERROR(AE72/$AE$3,"") | AG72: =IFERROR((AE72-AB72)/AB72,"") | AI72: =IFERROR(AH72/$AH$3,"") | AJ72: =IFERROR((AH72-AE72)/AE72,"") | AK72: =SUM(Tabela373[[#This Row],[JANEIRO]]+Tabela373[[#This Row],[FEVEREIRO]]+Tabela373[[#This Row],[MARÇO]]+Tabela373[[#This Row],[ABRIL]]+Tabela373[[#This Row],[MAIO]]+Tabela373[[#This Row],[JUNHO]]+Tabela373[[#This Row],[JULHO]]+Tabela373[[#This Row],[AGOSTO]]+Tabela373[[#This Row],[SETEMBRO]]+Tabela373[[#This Row],[NOVEMBRO]]+Tabela373[[#This Row],[DEZEMBRO]]) -> 0 | AL72: =IFERROR(AK72/$AK$3,"") | AM72: =AVERAGE(Tabela373[[#This Row],[JANEIRO]],Tabela373[[#This Row],[FEVEREIRO]],Tabela373[[#This Row],[MARÇO]],Tabela373[[#This Row],[ABRIL]],Tabela373[[#This Row],[MAIO]],Tabela373[[#This Row],[JUNHO]],Tabela373[[#This Row],[JULHO]],Tabela373[[#This Row],[AGOSTO]],Tabela373[[#This Row],[SETEMBRO]],Tabela373[[#This Row],[OUTUBRO]],Tabela373[[#This Row],[NOVEMBRO]],Tabela373[[#This Row],[DEZEMBRO]]) -> #DIV/0!
A73: LOGÍSTICA REVERSA (DEVOLUÇÕES) | C73: =IFERROR(B73/$B$3,"") | E73: =IFERROR(D73/$D$3,"") | F73: =IFERROR((D73-B73)/B73,"") | H73: =IFERROR(G73/$G$3,"") | I73: =IFERROR((G73-D73)/D73,"") | K73: =IFERROR(J73/$J$3,"") | L73: =IFERROR((J73-G73)/G73,"") | N73: =IFERROR(M73/$M$3,"") | O73: =IFERROR((M73-J73)/J73,"") | Q73: =IFERROR(P73/$P$3,"") | R73: =IFERROR((P73-M73)/M73,"") | T73: =IFERROR(S73/$S$3,"") | U73: =IFERROR((S73-P73)/P73,"") | W73: =IFERROR(V73/$V$3,"") | X73: =IFERROR((V73-S73)/S73,"") | Z73: =IFERROR(Y73/$Y$3,"") | AA73: =IFERROR((Y73-V73)/V73,"") | AC73: =IFERROR(AB73/$AB$3,"") | AD73: =IFERROR((AB73-Y73)/Y73,"") | AF73: =IFERROR(AE73/$AE$3,"") | AG73: =IFERROR((AE73-AB73)/AB73,"") | AI73: =IFERROR(AH73/$AH$3,"") | AJ73: =IFERROR((AH73-AE73)/AE73,"") | AK73: =SUM(Tabela373[[#This Row],[JANEIRO]]+Tabela373[[#This Row],[FEVEREIRO]]+Tabela373[[#This Row],[MARÇO]]+Tabela373[[#This Row],[ABRIL]]+Tabela373[[#This Row],[MAIO]]+Tabela373[[#This Row],[JUNHO]]+Tabela373[[#This Row],[JULHO]]+Tabela373[[#This Row],[AGOSTO]]+Tabela373[[#This Row],[SETEMBRO]]+Tabela373[[#This Row],[NOVEMBRO]]+Tabela373[[#This Row],[DEZEMBRO]]) -> 0 | AL73: =IFERROR(AK73/$AK$3,"") | AM73: =AVERAGE(Tabela373[[#This Row],[JANEIRO]],Tabela373[[#This Row],[FEVEREIRO]],Tabela373[[#This Row],[MARÇO]],Tabela373[[#This Row],[ABRIL]],Tabela373[[#This Row],[MAIO]],Tabela373[[#This Row],[JUNHO]],Tabela373[[#This Row],[JULHO]],Tabela373[[#This Row],[AGOSTO]],Tabela373[[#This Row],[SETEMBRO]],Tabela373[[#This Row],[OUTUBRO]],Tabela373[[#This Row],[NOVEMBRO]],Tabela373[[#This Row],[DEZEMBRO]]) -> #DIV/0!
C74: =IFERROR(B74/$B$3,"") | E74: =IFERROR(D74/$D$3,"") | F74: =IFERROR((D74-B74)/B74,"") | H74: =IFERROR(G74/$G$3,"") | I74: =IFERROR((G74-D74)/D74,"") | K74: =IFERROR(J74/$J$3,"") | L74: =IFERROR((J74-G74)/G74,"") | N74: =IFERROR(M74/$M$3,"") | O74: =IFERROR((M74-J74)/J74,"") | Q74: =IFERROR(P74/$P$3,"") | R74: =IFERROR((P74-M74)/M74,"") | T74: =IFERROR(S74/$S$3,"") | U74: =IFERROR((S74-P74)/P74,"") | W74: =IFERROR(V74/$V$3,"") | X74: =IFERROR((V74-S74)/S74,"") | Z74: =IFERROR(Y74/$Y$3,"") | AA74: =IFERROR((Y74-V74)/V74,"") | AC74: =IFERROR(AB74/$AB$3,"") | AD74: =IFERROR((AB74-Y74)/Y74,"") | AF74: =IFERROR(AE74/$AE$3,"") | AG74: =IFERROR((AE74-AB74)/AB74,"") | AI74: =IFERROR(AH74/$AH$3,"") | AJ74: =IFERROR((AH74-AE74)/AE74,"") | AK74: =SUM(Tabela373[[#This Row],[JANEIRO]]+Tabela373[[#This Row],[FEVEREIRO]]+Tabela373[[#This Row],[MARÇO]]+Tabela373[[#This Row],[ABRIL]]+Tabela373[[#This Row],[MAIO]]+Tabela373[[#This Row],[JUNHO]]+Tabela373[[#This Row],[JULHO]]+Tabela373[[#This Row],[AGOSTO]]+Tabela373[[#This Row],[SETEMBRO]]+Tabela373[[#This Row],[NOVEMBRO]]+Tabela373[[#This Row],[DEZEMBRO]]) -> 0 | AL74: =IFERROR(AK74/$AK$3,"") | AM74: =AVERAGE(Tabela373[[#This Row],[JANEIRO]],Tabela373[[#This Row],[FEVEREIRO]],Tabela373[[#This Row],[MARÇO]],Tabela373[[#This Row],[ABRIL]],Tabela373[[#This Row],[MAIO]],Tabela373[[#This Row],[JUNHO]],Tabela373[[#This Row],[JULHO]],Tabela373[[#This Row],[AGOSTO]],Tabela373[[#This Row],[SETEMBRO]],Tabela373[[#This Row],[OUTUBRO]],Tabela373[[#This Row],[NOVEMBRO]],Tabela373[[#This Row],[DEZEMBRO]]) -> #DIV/0!
A75: TAXAS MEIO DE PAGAMENTO | B75: =SUM(B76:B79) -> 0 | C75: =IFERROR(B75/$B$3,"") | D75: =SUM(D76:D79) -> 0 | E75: =IFERROR(D75/$D$3,"") | F75: =IFERROR((D75-B75)/B75,"") | G75: =SUM(G76:G79) -> 0 | H75: =IFERROR(G75/$G$3,"") | I75: =IFERROR((G75-D75)/D75,"") | J75: =SUM(J76:J79) -> 0 | K75: =IFERROR(J75/$J$3,"") | L75: =IFERROR((J75-G75)/G75,"") | M75: =SUM(M76:M79) -> 0 | N75: =IFERROR(M75/$M$3,"") | O75: =IFERROR((M75-J75)/J75,"") | P75: =SUM(P76:P79) -> 0 | Q75: =IFERROR(P75/$P$3,"") | R75: =IFERROR((P75-M75)/M75,"") | S75: =SUM(S76:S79) -> 0 | T75: =IFERROR(S75/$S$3,"") | U75: =IFERROR((S75-P75)/P75,"") | V75: =SUM(V76:V79) -> 0 | W75: =IFERROR(V75/$V$3,"") | X75: =IFERROR((V75-S75)/S75,"") | Y75: =SUM(Y76:Y79) -> 0 | Z75: =IFERROR(Y75/$Y$3,"") | AA75: =IFERROR((Y75-V75)/V75,"") | AB75: =SUM(AB76:AB79) -> 0 | AC75: =IFERROR(AB75/$AB$3,"") | AD75: =IFERROR((AB75-Y75)/Y75,"") | AE75: =SUM(AE76:AE79) -> 0 | AF75: =IFERROR(AE75/$AE$3,"") | AG75: =IFERROR((AE75-AB75)/AB75,"") | AH75: =SUM(AH76:AH79) -> 0 | AI75: =IFERROR(AH75/$AH$3,"") | AJ75: =IFERROR((AH75-AE75)/AE75,"") | AK75: =SUM(Tabela373[[#This Row],[JANEIRO]]+Tabela373[[#This Row],[FEVEREIRO]]+Tabela373[[#This Row],[MARÇO]]+Tabela373[[#This Row],[ABRIL]]+Tabela373[[#This Row],[MAIO]]+Tabela373[[#This Row],[JUNHO]]+Tabela373[[#This Row],[JULHO]]+Tabela373[[#This Row],[AGOSTO]]+Tabela373[[#This Row],[SETEMBRO]]+Tabela373[[#This Row],[NOVEMBRO]]+Tabela373[[#This Row],[DEZEMBRO]]) -> 0 | AL75: =IFERROR(AK75/$AK$3,"") | AM75: =AVERAGE(Tabela373[[#This Row],[JANEIRO]],Tabela373[[#This Row],[FEVEREIRO]],Tabela373[[#This Row],[MARÇO]],Tabela373[[#This Row],[ABRIL]],Tabela373[[#This Row],[MAIO]],Tabela373[[#This Row],[JUNHO]],Tabela373[[#This Row],[JULHO]],Tabela373[[#This Row],[AGOSTO]],Tabela373[[#This Row],[SETEMBRO]],Tabela373[[#This Row],[OUTUBRO]],Tabela373[[#This Row],[NOVEMBRO]],Tabela373[[#This Row],[DEZEMBRO]]) -> 0
A76: TAXAS ANTECIPAÇÃO DE RECEBÍVEIS | C76: =IFERROR(B76/$B$3,"") | E76: =IFERROR(D76/$D$3,"") | F76: =IFERROR((D76-B76)/B76,"") | H76: =IFERROR(G76/$G$3,"") | I76: =IFERROR((G76-D76)/D76,"") | K76: =IFERROR(J76/$J$3,"") | L76: =IFERROR((J76-G76)/G76,"") | N76: =IFERROR(M76/$M$3,"") | O76: =IFERROR((M76-J76)/J76,"") | Q76: =IFERROR(P76/$P$3,"") | R76: =IFERROR((P76-M76)/M76,"") | T76: =IFERROR(S76/$S$3,"") | U76: =IFERROR((S76-P76)/P76,"") | W76: =IFERROR(V76/$V$3,"") | X76: =IFERROR((V76-S76)/S76,"") | Z76: =IFERROR(Y76/$Y$3,"") | AA76: =IFERROR((Y76-V76)/V76,"") | AC76: =IFERROR(AB76/$AB$3,"") | AD76: =IFERROR((AB76-Y76)/Y76,"") | AF76: =IFERROR(AE76/$AE$3,"") | AG76: =IFERROR((AE76-AB76)/AB76,"") | AI76: =IFERROR(AH76/$AH$3,"") | AJ76: =IFERROR((AH76-AE76)/AE76,"") | AK76: =SUM(Tabela373[[#This Row],[JANEIRO]]+Tabela373[[#This Row],[FEVEREIRO]]+Tabela373[[#This Row],[MARÇO]]+Tabela373[[#This Row],[ABRIL]]+Tabela373[[#This Row],[MAIO]]+Tabela373[[#This Row],[JUNHO]]+Tabela373[[#This Row],[JULHO]]+Tabela373[[#This Row],[AGOSTO]]+Tabela373[[#This Row],[SETEMBRO]]+Tabela373[[#This Row],[NOVEMBRO]]+Tabela373[[#This Row],[DEZEMBRO]]) -> 0 | AL76: =IFERROR(AK76/$AK$3,"") | AM76: =AVERAGE(Tabela373[[#This Row],[JANEIRO]],Tabela373[[#This Row],[FEVEREIRO]],Tabela373[[#This Row],[MARÇO]],Tabela373[[#This Row],[ABRIL]],Tabela373[[#This Row],[MAIO]],Tabela373[[#This Row],[JUNHO]],Tabela373[[#This Row],[JULHO]],Tabela373[[#This Row],[AGOSTO]],Tabela373[[#This Row],[SETEMBRO]],Tabela373[[#This Row],[OUTUBRO]],Tabela373[[#This Row],[NOVEMBRO]],Tabela373[[#This Row],[DEZEMBRO]]) -> #DIV/0!
A77: TAXAS GATEWAY/PLATAFORMAS | C77: =IFERROR(B77/$B$3,"") | E77: =IFERROR(D77/$D$3,"") | F77: =IFERROR((D77-B77)/B77,"") | H77: =IFERROR(G77/$G$3,"") | I77: =IFERROR((G77-D77)/D77,"") | K77: =IFERROR(J77/$J$3,"") | L77: =IFERROR((J77-G77)/G77,"") | N77: =IFERROR(M77/$M$3,"") | O77: =IFERROR((M77-J77)/J77,"") | Q77: =IFERROR(P77/$P$3,"") | R77: =IFERROR((P77-M77)/M77,"") | T77: =IFERROR(S77/$S$3,"") | U77: =IFERROR((S77-P77)/P77,"") | W77: =IFERROR(V77/$V$3,"") | X77: =IFERROR((V77-S77)/S77,"") | Z77: =IFERROR(Y77/$Y$3,"") | AA77: =IFERROR((Y77-V77)/V77,"") | AC77: =IFERROR(AB77/$AB$3,"") | AD77: =IFERROR((AB77-Y77)/Y77,"") | AF77: =IFERROR(AE77/$AE$3,"") | AG77: =IFERROR((AE77-AB77)/AB77,"") | AI77: =IFERROR(AH77/$AH$3,"") | AJ77: =IFERROR((AH77-AE77)/AE77,"") | AK77: =SUM(Tabela373[[#This Row],[JANEIRO]]+Tabela373[[#This Row],[FEVEREIRO]]+Tabela373[[#This Row],[MARÇO]]+Tabela373[[#This Row],[ABRIL]]+Tabela373[[#This Row],[MAIO]]+Tabela373[[#This Row],[JUNHO]]+Tabela373[[#This Row],[JULHO]]+Tabela373[[#This Row],[AGOSTO]]+Tabela373[[#This Row],[SETEMBRO]]+Tabela373[[#This Row],[NOVEMBRO]]+Tabela373[[#This Row],[DEZEMBRO]]) -> 0 | AL77: =IFERROR(AK77/$AK$3,"") | AM77: =AVERAGE(Tabela373[[#This Row],[JANEIRO]],Tabela373[[#This Row],[FEVEREIRO]],Tabela373[[#This Row],[MARÇO]],Tabela373[[#This Row],[ABRIL]],Tabela373[[#This Row],[MAIO]],Tabela373[[#This Row],[JUNHO]],Tabela373[[#This Row],[JULHO]],Tabela373[[#This Row],[AGOSTO]],Tabela373[[#This Row],[SETEMBRO]],Tabela373[[#This Row],[OUTUBRO]],Tabela373[[#This Row],[NOVEMBRO]],Tabela373[[#This Row],[DEZEMBRO]]) -> #DIV/0!
A78: TAXAS MAQUININHA DE CARTÃO | C78: =IFERROR(B78/$B$3,"") | E78: =IFERROR(D78/$D$3,"") | F78: =IFERROR((D78-B78)/B78,"") | H78: =IFERROR(G78/$G$3,"") | I78: =IFERROR((G78-D78)/D78,"") | K78: =IFERROR(J78/$J$3,"") | L78: =IFERROR((J78-G78)/G78,"") | N78: =IFERROR(M78/$M$3,"") | O78: =IFERROR((M78-J78)/J78,"") | Q78: =IFERROR(P78/$P$3,"") | R78: =IFERROR((P78-M78)/M78,"") | T78: =IFERROR(S78/$S$3,"") | U78: =IFERROR((S78-P78)/P78,"") | W78: =IFERROR(V78/$V$3,"") | X78: =IFERROR((V78-S78)/S78,"") | Z78: =IFERROR(Y78/$Y$3,"") | AA78: =IFERROR((Y78-V78)/V78,"") | AC78: =IFERROR(AB78/$AB$3,"") | AD78: =IFERROR((AB78-Y78)/Y78,"") | AF78: =IFERROR(AE78/$AE$3,"") | AG78: =IFERROR((AE78-AB78)/AB78,"") | AI78: =IFERROR(AH78/$AH$3,"") | AJ78: =IFERROR((AH78-AE78)/AE78,"") | AK78: =SUM(Tabela373[[#This Row],[JANEIRO]]+Tabela373[[#This Row],[FEVEREIRO]]+Tabela373[[#This Row],[MARÇO]]+Tabela373[[#This Row],[ABRIL]]+Tabela373[[#This Row],[MAIO]]+Tabela373[[#This Row],[JUNHO]]+Tabela373[[#This Row],[JULHO]]+Tabela373[[#This Row],[AGOSTO]]+Tabela373[[#This Row],[SETEMBRO]]+Tabela373[[#This Row],[NOVEMBRO]]+Tabela373[[#This Row],[DEZEMBRO]]) -> 0 | AL78: =IFERROR(AK78/$AK$3,"") | AM78: =AVERAGE(Tabela373[[#This Row],[JANEIRO]],Tabela373[[#This Row],[FEVEREIRO]],Tabela373[[#This Row],[MARÇO]],Tabela373[[#This Row],[ABRIL]],Tabela373[[#This Row],[MAIO]],Tabela373[[#This Row],[JUNHO]],Tabela373[[#This Row],[JULHO]],Tabela373[[#This Row],[AGOSTO]],Tabela373[[#This Row],[SETEMBRO]],Tabela373[[#This Row],[OUTUBRO]],Tabela373[[#This Row],[NOVEMBRO]],Tabela373[[#This Row],[DEZEMBRO]]) -> #DIV/0!
C79: =IFERROR(B79/$B$3,"") | E79: =IFERROR(D79/$D$3,"") | F79: =IFERROR((D79-B79)/B79,"") | H79: =IFERROR(G79/$G$3,"") | I79: =IFERROR((G79-D79)/D79,"") | K79: =IFERROR(J79/$J$3,"") | L79: =IFERROR((J79-G79)/G79,"") | N79: =IFERROR(M79/$M$3,"") | O79: =IFERROR((M79-J79)/J79,"") | Q79: =IFERROR(P79/$P$3,"") | R79: =IFERROR((P79-M79)/M79,"") | T79: =IFERROR(S79/$S$3,"") | U79: =IFERROR((S79-P79)/P79,"") | W79: =IFERROR(V79/$V$3,"") | X79: =IFERROR((V79-S79)/S79,"") | Z79: =IFERROR(Y79/$Y$3,"") | AA79: =IFERROR((Y79-V79)/V79,"") | AC79: =IFERROR(AB79/$AB$3,"") | AD79: =IFERROR((AB79-Y79)/Y79,"") | AF79: =IFERROR(AE79/$AE$3,"") | AG79: =IFERROR((AE79-AB79)/AB79,"") | AI79: =IFERROR(AH79/$AH$3,"") | AJ79: =IFERROR((AH79-AE79)/AE79,"") | AK79: =SUM(Tabela373[[#This Row],[JANEIRO]]+Tabela373[[#This Row],[FEVEREIRO]]+Tabela373[[#This Row],[MARÇO]]+Tabela373[[#This Row],[ABRIL]]+Tabela373[[#This Row],[MAIO]]+Tabela373[[#This Row],[JUNHO]]+Tabela373[[#This Row],[JULHO]]+Tabela373[[#This Row],[AGOSTO]]+Tabela373[[#This Row],[SETEMBRO]]+Tabela373[[#This Row],[NOVEMBRO]]+Tabela373[[#This Row],[DEZEMBRO]]) -> 0 | AL79: =IFERROR(AK79/$AK$3,"") | AM79: =AVERAGE(Tabela373[[#This Row],[JANEIRO]],Tabela373[[#This Row],[FEVEREIRO]],Tabela373[[#This Row],[MARÇO]],Tabela373[[#This Row],[ABRIL]],Tabela373[[#This Row],[MAIO]],Tabela373[[#This Row],[JUNHO]],Tabela373[[#This Row],[JULHO]],Tabela373[[#This Row],[AGOSTO]],Tabela373[[#This Row],[SETEMBRO]],Tabela373[[#This Row],[OUTUBRO]],Tabela373[[#This Row],[NOVEMBRO]],Tabela373[[#This Row],[DEZEMBRO]]) -> #DIV/0!
A80: TAXAS MARKETPLACE | B80: =SUM(B81:B84) -> 0 | C80: =IFERROR(B80/$B$3,"") | D80: =SUM(D81:D84) -> 0 | E80: =IFERROR(D80/$D$3,"") | F80: =IFERROR((D80-B80)/B80,"") | G80: =SUM(G81:G84) -> 0 | H80: =IFERROR(G80/$G$3,"") | I80: =IFERROR((G80-D80)/D80,"") | J80: =SUM(J81:J84) -> 0 | K80: =IFERROR(J80/$J$3,"") | L80: =IFERROR((J80-G80)/G80,"") | M80: =SUM(M81:M84) -> 0 | N80: =IFERROR(M80/$M$3,"") | O80: =IFERROR((M80-J80)/J80,"") | P80: =SUM(P81:P84) -> 0 | Q80: =IFERROR(P80/$P$3,"") | R80: =IFERROR((P80-M80)/M80,"") | S80: =SUM(S81:S84) -> 0 | T80: =IFERROR(S80/$S$3,"") | U80: =IFERROR((S80-P80)/P80,"") | V80: =SUM(V81:V84) -> 0 | W80: =IFERROR(V80/$V$3,"") | X80: =IFERROR((V80-S80)/S80,"") | Y80: =SUM(Y81:Y84) -> 0 | Z80: =IFERROR(Y80/$Y$3,"") | AA80: =IFERROR((Y80-V80)/V80,"") | AB80: =SUM(AB81:AB84) -> 0 | AC80: =IFERROR(AB80/$AB$3,"") | AD80: =IFERROR((AB80-Y80)/Y80,"") | AE80: =SUM(AE81:AE84) -> 0 | AF80: =IFERROR(AE80/$AE$3,"") | AG80: =IFERROR((AE80-AB80)/AB80,"") | AH80: =SUM(AH81:AH84) -> 0 | AI80: =IFERROR(AH80/$AH$3,"") | AJ80: =IFERROR((AH80-AE80)/AE80,"") | AK80: =SUM(Tabela373[[#This Row],[JANEIRO]]+Tabela373[[#This Row],[FEVEREIRO]]+Tabela373[[#This Row],[MARÇO]]+Tabela373[[#This Row],[ABRIL]]+Tabela373[[#This Row],[MAIO]]+Tabela373[[#This Row],[JUNHO]]+Tabela373[[#This Row],[JULHO]]+Tabela373[[#This Row],[AGOSTO]]+Tabela373[[#This Row],[SETEMBRO]]+Tabela373[[#This Row],[NOVEMBRO]]+Tabela373[[#This Row],[DEZEMBRO]]) -> 0 | AL80: =IFERROR(AK80/$AK$3,"") | AM80: =AVERAGE(Tabela373[[#This Row],[JANEIRO]],Tabela373[[#This Row],[FEVEREIRO]],Tabela373[[#This Row],[MARÇO]],Tabela373[[#This Row],[ABRIL]],Tabela373[[#This Row],[MAIO]],Tabela373[[#This Row],[JUNHO]],Tabela373[[#This Row],[JULHO]],Tabela373[[#This Row],[AGOSTO]],Tabela373[[#This Row],[SETEMBRO]],Tabela373[[#This Row],[OUTUBRO]],Tabela373[[#This Row],[NOVEMBRO]],Tabela373[[#This Row],[DEZEMBRO]]) -> 0
A81: TAXAS ADS INTERNOS MARKETPLACE | C81: =IFERROR(B81/$B$3,"") | E81: =IFERROR(D81/$D$3,"") | F81: =IFERROR((D81-B81)/B81,"") | H81: =IFERROR(G81/$G$3,"") | I81: =IFERROR((G81-D81)/D81,"") | K81: =IFERROR(J81/$J$3,"") | L81: =IFERROR((J81-G81)/G81,"") | N81: =IFERROR(M81/$M$3,"") | O81: =IFERROR((M81-J81)/J81,"") | Q81: =IFERROR(P81/$P$3,"") | R81: =IFERROR((P81-M81)/M81,"") | T81: =IFERROR(S81/$S$3,"") | U81: =IFERROR((S81-P81)/P81,"") | W81: =IFERROR(V81/$V$3,"") | X81: =IFERROR((V81-S81)/S81,"") | Z81: =IFERROR(Y81/$Y$3,"") | AA81: =IFERROR((Y81-V81)/V81,"") | AC81: =IFERROR(AB81/$AB$3,"") | AD81: =IFERROR((AB81-Y81)/Y81,"") | AF81: =IFERROR(AE81/$AE$3,"") | AG81: =IFERROR((AE81-AB81)/AB81,"") | AI81: =IFERROR(AH81/$AH$3,"") | AJ81: =IFERROR((AH81-AE81)/AE81,"") | AK81: =SUM(Tabela373[[#This Row],[JANEIRO]]+Tabela373[[#This Row],[FEVEREIRO]]+Tabela373[[#This Row],[MARÇO]]+Tabela373[[#This Row],[ABRIL]]+Tabela373[[#This Row],[MAIO]]+Tabela373[[#This Row],[JUNHO]]+Tabela373[[#This Row],[JULHO]]+Tabela373[[#This Row],[AGOSTO]]+Tabela373[[#This Row],[SETEMBRO]]+Tabela373[[#This Row],[NOVEMBRO]]+Tabela373[[#This Row],[DEZEMBRO]]) -> 0 | AL81: =IFERROR(AK81/$AK$3,"") | AM81: =AVERAGE(Tabela373[[#This Row],[JANEIRO]],Tabela373[[#This Row],[FEVEREIRO]],Tabela373[[#This Row],[MARÇO]],Tabela373[[#This Row],[ABRIL]],Tabela373[[#This Row],[MAIO]],Tabela373[[#This Row],[JUNHO]],Tabela373[[#This Row],[JULHO]],Tabela373[[#This Row],[AGOSTO]],Tabela373[[#This Row],[SETEMBRO]],Tabela373[[#This Row],[OUTUBRO]],Tabela373[[#This Row],[NOVEMBRO]],Tabela373[[#This Row],[DEZEMBRO]]) -> #DIV/0!
A82: TAXAS ENVIO MARKETPLACE | C82: =IFERROR(B82/$B$3,"") | E82: =IFERROR(D82/$D$3,"") | F82: =IFERROR((D82-B82)/B82,"") | H82: =IFERROR(G82/$G$3,"") | I82: =IFERROR((G82-D82)/D82,"") | K82: =IFERROR(J82/$J$3,"") | L82: =IFERROR((J82-G82)/G82,"") | N82: =IFERROR(M82/$M$3,"") | O82: =IFERROR((M82-J82)/J82,"") | Q82: =IFERROR(P82/$P$3,"") | R82: =IFERROR((P82-M82)/M82,"") | T82: =IFERROR(S82/$S$3,"") | U82: =IFERROR((S82-P82)/P82,"") | W82: =IFERROR(V82/$V$3,"") | X82: =IFERROR((V82-S82)/S82,"") | Z82: =IFERROR(Y82/$Y$3,"") | AA82: =IFERROR((Y82-V82)/V82,"") | AC82: =IFERROR(AB82/$AB$3,"") | AD82: =IFERROR((AB82-Y82)/Y82,"") | AF82: =IFERROR(AE82/$AE$3,"") | AG82: =IFERROR((AE82-AB82)/AB82,"") | AI82: =IFERROR(AH82/$AH$3,"") | AJ82: =IFERROR((AH82-AE82)/AE82,"") | AK82: =SUM(Tabela373[[#This Row],[JANEIRO]]+Tabela373[[#This Row],[FEVEREIRO]]+Tabela373[[#This Row],[MARÇO]]+Tabela373[[#This Row],[ABRIL]]+Tabela373[[#This Row],[MAIO]]+Tabela373[[#This Row],[JUNHO]]+Tabela373[[#This Row],[JULHO]]+Tabela373[[#This Row],[AGOSTO]]+Tabela373[[#This Row],[SETEMBRO]]+Tabela373[[#This Row],[NOVEMBRO]]+Tabela373[[#This Row],[DEZEMBRO]]) -> 0 | AL82: =IFERROR(AK82/$AK$3,"") | AM82: =AVERAGE(Tabela373[[#This Row],[JANEIRO]],Tabela373[[#This Row],[FEVEREIRO]],Tabela373[[#This Row],[MARÇO]],Tabela373[[#This Row],[ABRIL]],Tabela373[[#This Row],[MAIO]],Tabela373[[#This Row],[JUNHO]],Tabela373[[#This Row],[JULHO]],Tabela373[[#This Row],[AGOSTO]],Tabela373[[#This Row],[SETEMBRO]],Tabela373[[#This Row],[OUTUBRO]],Tabela373[[#This Row],[NOVEMBRO]],Tabela373[[#This Row],[DEZEMBRO]]) -> #DIV/0!
A83: TAXAS MARKETPLACE | C83: =IFERROR(B83/$B$3,"") | E83: =IFERROR(D83/$D$3,"") | F83: =IFERROR((D83-B83)/B83,"") | H83: =IFERROR(G83/$G$3,"") | I83: =IFERROR((G83-D83)/D83,"") | K83: =IFERROR(J83/$J$3,"") | L83: =IFERROR((J83-G83)/G83,"") | N83: =IFERROR(M83/$M$3,"") | O83: =IFERROR((M83-J83)/J83,"") | Q83: =IFERROR(P83/$P$3,"") | R83: =IFERROR((P83-M83)/M83,"") | T83: =IFERROR(S83/$S$3,"") | U83: =IFERROR((S83-P83)/P83,"") | W83: =IFERROR(V83/$V$3,"") | X83: =IFERROR((V83-S83)/S83,"") | Z83: =IFERROR(Y83/$Y$3,"") | AA83: =IFERROR((Y83-V83)/V83,"") | AC83: =IFERROR(AB83/$AB$3,"") | AD83: =IFERROR((AB83-Y83)/Y83,"") | AF83: =IFERROR(AE83/$AE$3,"") | AG83: =IFERROR((AE83-AB83)/AB83,"") | AI83: =IFERROR(AH83/$AH$3,"") | AJ83: =IFERROR((AH83-AE83)/AE83,"") | AK83: =SUM(Tabela373[[#This Row],[JANEIRO]]+Tabela373[[#This Row],[FEVEREIRO]]+Tabela373[[#This Row],[MARÇO]]+Tabela373[[#This Row],[ABRIL]]+Tabela373[[#This Row],[MAIO]]+Tabela373[[#This Row],[JUNHO]]+Tabela373[[#This Row],[JULHO]]+Tabela373[[#This Row],[AGOSTO]]+Tabela373[[#This Row],[SETEMBRO]]+Tabela373[[#This Row],[NOVEMBRO]]+Tabela373[[#This Row],[DEZEMBRO]]) -> 0 | AL83: =IFERROR(AK83/$AK$3,"") | AM83: =AVERAGE(Tabela373[[#This Row],[JANEIRO]],Tabela373[[#This Row],[FEVEREIRO]],Tabela373[[#This Row],[MARÇO]],Tabela373[[#This Row],[ABRIL]],Tabela373[[#This Row],[MAIO]],Tabela373[[#This Row],[JUNHO]],Tabela373[[#This Row],[JULHO]],Tabela373[[#This Row],[AGOSTO]],Tabela373[[#This Row],[SETEMBRO]],Tabela373[[#This Row],[OUTUBRO]],Tabela373[[#This Row],[NOVEMBRO]],Tabela373[[#This Row],[DEZEMBRO]]) -> #DIV/0!
C84: =IFERROR(B84/$B$3,"") | E84: =IFERROR(D84/$D$3,"") | F84: =IFERROR((D84-B84)/B84,"") | H84: =IFERROR(G84/$G$3,"") | I84: =IFERROR((G84-D84)/D84,"") | K84: =IFERROR(J84/$J$3,"") | L84: =IFERROR((J84-G84)/G84,"") | N84: =IFERROR(M84/$M$3,"") | O84: =IFERROR((M84-J84)/J84,"") | Q84: =IFERROR(P84/$P$3,"") | R84: =IFERROR((P84-M84)/M84,"") | T84: =IFERROR(S84/$S$3,"") | U84: =IFERROR((S84-P84)/P84,"") | W84: =IFERROR(V84/$V$3,"") | X84: =IFERROR((V84-S84)/S84,"") | Z84: =IFERROR(Y84/$Y$3,"") | AA84: =IFERROR((Y84-V84)/V84,"") | AC84: =IFERROR(AB84/$AB$3,"") | AD84: =IFERROR((AB84-Y84)/Y84,"") | AF84: =IFERROR(AE84/$AE$3,"") | AG84: =IFERROR((AE84-AB84)/AB84,"") | AI84: =IFERROR(AH84/$AH$3,"") | AJ84: =IFERROR((AH84-AE84)/AE84,"") | AK84: =SUM(Tabela373[[#This Row],[JANEIRO]]+Tabela373[[#This Row],[FEVEREIRO]]+Tabela373[[#This Row],[MARÇO]]+Tabela373[[#This Row],[ABRIL]]+Tabela373[[#This Row],[MAIO]]+Tabela373[[#This Row],[JUNHO]]+Tabela373[[#This Row],[JULHO]]+Tabela373[[#This Row],[AGOSTO]]+Tabela373[[#This Row],[SETEMBRO]]+Tabela373[[#This Row],[NOVEMBRO]]+Tabela373[[#This Row],[DEZEMBRO]]) -> 0 | AL84: =IFERROR(AK84/$AK$3,"") | AM84: =AVERAGE(Tabela373[[#This Row],[JANEIRO]],Tabela373[[#This Row],[FEVEREIRO]],Tabela373[[#This Row],[MARÇO]],Tabela373[[#This Row],[ABRIL]],Tabela373[[#This Row],[MAIO]],Tabela373[[#This Row],[JUNHO]],Tabela373[[#This Row],[JULHO]],Tabela373[[#This Row],[AGOSTO]],Tabela373[[#This Row],[SETEMBRO]],Tabela373[[#This Row],[OUTUBRO]],Tabela373[[#This Row],[NOVEMBRO]],Tabela373[[#This Row],[DEZEMBRO]]) -> #DIV/0!
A85: (=) MARGEM DE CONTRIBUIÇÃO | B85: =B43-B44-B64 -> 0 | C85: =IFERROR(B85/$B$3,"") | D85: =D43-D44-D64 -> 0 | E85: =IFERROR(D85/$D$3,"") | F85: =IFERROR((D85-B85)/B85,"") | G85: =G43-G44-G64 -> 0 | H85: =IFERROR(G85/$G$3,"") | I85: =IFERROR((G85-D85)/D85,"") | J85: =J43-J44-J64 -> 0 | K85: =IFERROR(J85/$J$3,"") | L85: =IFERROR((J85-G85)/G85,"") | M85: =M43-M44-M64 -> 0 | N85: =IFERROR(M85/$M$3,"") | O85: =IFERROR((M85-J85)/J85,"") | P85: =P43-P44-P64 -> 0 | Q85: =IFERROR(P85/$P$3,"") | R85: =IFERROR((P85-M85)/M85,"") | S85: =S43-S44-S64 -> 0 | T85: =IFERROR(S85/$S$3,"") | U85: =IFERROR((S85-P85)/P85,"") | V85: =V43-V44-V64 -> 0 | W85: =IFERROR(V85/$V$3,"") | X85: =IFERROR((V85-S85)/S85,"") | Y85: =Y43-Y44-Y64 -> 0 | Z85: =IFERROR(Y85/$Y$3,"") | AA85: =IFERROR((Y85-V85)/V85,"") | AB85: =AB43-AB44-AB64 -> 0 | AC85: =IFERROR(AB85/$AB$3,"") | AD85: =IFERROR((AB85-Y85)/Y85,"") | AE85: =AE43-AE44-AE64 -> 0 | AF85: =IFERROR(AE85/$AE$3,"") | AG85: =IFERROR((AE85-AB85)/AB85,"") | AH85: =AH43-AH44-AH64 -> 0 | AI85: =IFERROR(AH85/$AH$3,"") | AJ85: =IFERROR((AH85-AE85)/AE85,"") | AK85: =SUM(Tabela373[[#This Row],[JANEIRO]]+Tabela373[[#This Row],[FEVEREIRO]]+Tabela373[[#This Row],[MARÇO]]+Tabela373[[#This Row],[ABRIL]]+Tabela373[[#This Row],[MAIO]]+Tabela373[[#This Row],[JUNHO]]+Tabela373[[#This Row],[JULHO]]+Tabela373[[#This Row],[AGOSTO]]+Tabela373[[#This Row],[SETEMBRO]]+Tabela373[[#This Row],[NOVEMBRO]]+Tabela373[[#This Row],[DEZEMBRO]]) -> 0 | AL85: =IFERROR(AK85/$AK$3,"") | AM85: =AVERAGE(Tabela373[[#This Row],[JANEIRO]],Tabela373[[#This Row],[FEVEREIRO]],Tabela373[[#This Row],[MARÇO]],Tabela373[[#This Row],[ABRIL]],Tabela373[[#This Row],[MAIO]],Tabela373[[#This Row],[JUNHO]],Tabela373[[#This Row],[JULHO]],Tabela373[[#This Row],[AGOSTO]],Tabela373[[#This Row],[SETEMBRO]],Tabela373[[#This Row],[OUTUBRO]],Tabela373[[#This Row],[NOVEMBRO]],Tabela373[[#This Row],[DEZEMBRO]]) -> 0
A86: (-) CUSTOS FIXOS | B86: =B87+B100 -> 0 | C86: =IFERROR(B86/$B$3,"") | D86: =D87+D100 -> 0 | E86: =IFERROR(D86/$D$3,"") | F86: =IFERROR((D86-B86)/B86,"") | G86: =G87+G100 -> 0 | H86: =IFERROR(G86/$G$3,"") | I86: =IFERROR((G86-D86)/D86,"") | J86: =J87+J100 -> 0 | K86: =IFERROR(J86/$J$3,"") | L86: =IFERROR((J86-G86)/G86,"") | M86: =M87+M100 -> 0 | N86: =IFERROR(M86/$M$3,"") | O86: =IFERROR((M86-J86)/J86,"") | P86: =P87+P100 -> 0 | Q86: =IFERROR(P86/$P$3,"") | R86: =IFERROR((P86-M86)/M86,"") | S86: =S87+S100 -> 0 | T86: =IFERROR(S86/$S$3,"") | U86: =IFERROR((S86-P86)/P86,"") | V86: =V87+V100 -> 0 | W86: =IFERROR(V86/$V$3,"") | X86: =IFERROR((V86-S86)/S86,"") | Y86: =Y87+Y100 -> 0 | Z86: =IFERROR(Y86/$Y$3,"") | AA86: =IFERROR((Y86-V86)/V86,"") | AB86: =AB87+AB100 -> 0 | AC86: =IFERROR(AB86/$AB$3,"") | AD86: =IFERROR((AB86-Y86)/Y86,"") | AE86: =AE87+AE100 -> 0 | AF86: =IFERROR(AE86/$AE$3,"") | AG86: =IFERROR((AE86-AB86)/AB86,"") | AH86: =AH87+AH100 -> 0 | AI86: =IFERROR(AH86/$AH$3,"") | AJ86: =IFERROR((AH86-AE86)/AE86,"") | AK86: =SUM(Tabela373[[#This Row],[JANEIRO]]+Tabela373[[#This Row],[FEVEREIRO]]+Tabela373[[#This Row],[MARÇO]]+Tabela373[[#This Row],[ABRIL]]+Tabela373[[#This Row],[MAIO]]+Tabela373[[#This Row],[JUNHO]]+Tabela373[[#This Row],[JULHO]]+Tabela373[[#This Row],[AGOSTO]]+Tabela373[[#This Row],[SETEMBRO]]+Tabela373[[#This Row],[NOVEMBRO]]+Tabela373[[#This Row],[DEZEMBRO]]) -> 0 | AL86: =IFERROR(AK86/$AK$3,"") | AM86: =AVERAGE(Tabela373[[#This Row],[JANEIRO]],Tabela373[[#This Row],[FEVEREIRO]],Tabela373[[#This Row],[MARÇO]],Tabela373[[#This Row],[ABRIL]],Tabela373[[#This Row],[MAIO]],Tabela373[[#This Row],[JUNHO]],Tabela373[[#This Row],[JULHO]],Tabela373[[#This Row],[AGOSTO]],Tabela373[[#This Row],[SETEMBRO]],Tabela373[[#This Row],[OUTUBRO]],Tabela373[[#This Row],[NOVEMBRO]],Tabela373[[#This Row],[DEZEMBRO]]) -> 0
A87: CUSTOS COM PESSOAL OPERACIONAL | B87: =SUM(B88:B99) -> 0 | C87: =IFERROR(B87/$B$3,"") | D87: =SUM(D88:D99) -> 0 | E87: =IFERROR(D87/$D$3,"") | F87: =IFERROR((D87-B87)/B87,"") | G87: =SUM(G88:G99) -> 0 | H87: =IFERROR(G87/$G$3,"") | I87: =IFERROR((G87-D87)/D87,"") | J87: =SUM(J88:J99) -> 0 | K87: =IFERROR(J87/$J$3,"") | L87: =IFERROR((J87-G87)/G87,"") | M87: =SUM(M88:M99) -> 0 | N87: =IFERROR(M87/$M$3,"") | O87: =IFERROR((M87-J87)/J87,"") | P87: =SUM(P88:P99) -> 0 | Q87: =IFERROR(P87/$P$3,"") | R87: =IFERROR((P87-M87)/M87,"") | S87: =SUM(S88:S99) -> 0 | T87: =IFERROR(S87/$S$3,"") | U87: =IFERROR((S87-P87)/P87,"") | V87: =SUM(V88:V99) -> 0 | W87: =IFERROR(V87/$V$3,"") | X87: =IFERROR((V87-S87)/S87,"") | Y87: =SUM(Y88:Y99) -> 0 | Z87: =IFERROR(Y87/$Y$3,"") | AA87: =IFERROR((Y87-V87)/V87,"") | AB87: =SUM(AB88:AB99) -> 0 | AC87: =IFERROR(AB87/$AB$3,"") | AD87: =IFERROR((AB87-Y87)/Y87,"") | AE87: =SUM(AE88:AE99) -> 0 | AF87: =IFERROR(AE87/$AE$3,"") | AG87: =IFERROR((AE87-AB87)/AB87,"") | AH87: =SUM(AH88:AH99) -> 0 | AI87: =IFERROR(AH87/$AH$3,"") | AJ87: =IFERROR((AH87-AE87)/AE87,"") | AK87: =SUM(Tabela373[[#This Row],[JANEIRO]]+Tabela373[[#This Row],[FEVEREIRO]]+Tabela373[[#This Row],[MARÇO]]+Tabela373[[#This Row],[ABRIL]]+Tabela373[[#This Row],[MAIO]]+Tabela373[[#This Row],[JUNHO]]+Tabela373[[#This Row],[JULHO]]+Tabela373[[#This Row],[AGOSTO]]+Tabela373[[#This Row],[SETEMBRO]]+Tabela373[[#This Row],[NOVEMBRO]]+Tabela373[[#This Row],[DEZEMBRO]]) -> 0 | AL87: =IFERROR(AK87/$AK$3,"") | AM87: =AVERAGE(Tabela373[[#This Row],[JANEIRO]],Tabela373[[#This Row],[FEVEREIRO]],Tabela373[[#This Row],[MARÇO]],Tabela373[[#This Row],[ABRIL]],Tabela373[[#This Row],[MAIO]],Tabela373[[#This Row],[JUNHO]],Tabela373[[#This Row],[JULHO]],Tabela373[[#This Row],[AGOSTO]],Tabela373[[#This Row],[SETEMBRO]],Tabela373[[#This Row],[OUTUBRO]],Tabela373[[#This Row],[NOVEMBRO]],Tabela373[[#This Row],[DEZEMBRO]]) -> 0
A88: 13º SALARIO PRODUÇÃO | C88: =IFERROR(B88/$B$3,"") | E88: =IFERROR(D88/$D$3,"") | F88: =IFERROR((D88-B88)/B88,"") | H88: =IFERROR(G88/$G$3,"") | I88: =IFERROR((G88-D88)/D88,"") | K88: =IFERROR(J88/$J$3,"") | L88: =IFERROR((J88-G88)/G88,"") | N88: =IFERROR(M88/$M$3,"") | O88: =IFERROR((M88-J88)/J88,"") | Q88: =IFERROR(P88/$P$3,"") | R88: =IFERROR((P88-M88)/M88,"") | T88: =IFERROR(S88/$S$3,"") | U88: =IFERROR((S88-P88)/P88,"") | W88: =IFERROR(V88/$V$3,"") | X88: =IFERROR((V88-S88)/S88,"") | Z88: =IFERROR(Y88/$Y$3,"") | AA88: =IFERROR((Y88-V88)/V88,"") | AC88: =IFERROR(AB88/$AB$3,"") | AD88: =IFERROR((AB88-Y88)/Y88,"") | AF88: =IFERROR(AE88/$AE$3,"") | AG88: =IFERROR((AE88-AB88)/AB88,"") | AI88: =IFERROR(AH88/$AH$3,"") | AJ88: =IFERROR((AH88-AE88)/AE88,"") | AK88: =SUM(Tabela373[[#This Row],[JANEIRO]]+Tabela373[[#This Row],[FEVEREIRO]]+Tabela373[[#This Row],[MARÇO]]+Tabela373[[#This Row],[ABRIL]]+Tabela373[[#This Row],[MAIO]]+Tabela373[[#This Row],[JUNHO]]+Tabela373[[#This Row],[JULHO]]+Tabela373[[#This Row],[AGOSTO]]+Tabela373[[#This Row],[SETEMBRO]]+Tabela373[[#This Row],[NOVEMBRO]]+Tabela373[[#This Row],[DEZEMBRO]]) -> 0 | AL88: =IFERROR(AK88/$AK$3,"") | AM88: =AVERAGE(Tabela373[[#This Row],[JANEIRO]],Tabela373[[#This Row],[FEVEREIRO]],Tabela373[[#This Row],[MARÇO]],Tabela373[[#This Row],[ABRIL]],Tabela373[[#This Row],[MAIO]],Tabela373[[#This Row],[JUNHO]],Tabela373[[#This Row],[JULHO]],Tabela373[[#This Row],[AGOSTO]],Tabela373[[#This Row],[SETEMBRO]],Tabela373[[#This Row],[OUTUBRO]],Tabela373[[#This Row],[NOVEMBRO]],Tabela373[[#This Row],[DEZEMBRO]]) -> #DIV/0!
A89: ALIMENTAÇÃO PRODUÇÃO | C89: =IFERROR(B89/$B$3,"") | E89: =IFERROR(D89/$D$3,"") | F89: =IFERROR((D89-B89)/B89,"") | H89: =IFERROR(G89/$G$3,"") | I89: =IFERROR((G89-D89)/D89,"") | K89: =IFERROR(J89/$J$3,"") | L89: =IFERROR((J89-G89)/G89,"") | N89: =IFERROR(M89/$M$3,"") | O89: =IFERROR((M89-J89)/J89,"") | Q89: =IFERROR(P89/$P$3,"") | R89: =IFERROR((P89-M89)/M89,"") | T89: =IFERROR(S89/$S$3,"") | U89: =IFERROR((S89-P89)/P89,"") | W89: =IFERROR(V89/$V$3,"") | X89: =IFERROR((V89-S89)/S89,"") | Z89: =IFERROR(Y89/$Y$3,"") | AA89: =IFERROR((Y89-V89)/V89,"") | AC89: =IFERROR(AB89/$AB$3,"") | AD89: =IFERROR((AB89-Y89)/Y89,"") | AF89: =IFERROR(AE89/$AE$3,"") | AG89: =IFERROR((AE89-AB89)/AB89,"") | AI89: =IFERROR(AH89/$AH$3,"") | AJ89: =IFERROR((AH89-AE89)/AE89,"") | AK89: =SUM(Tabela373[[#This Row],[JANEIRO]]+Tabela373[[#This Row],[FEVEREIRO]]+Tabela373[[#This Row],[MARÇO]]+Tabela373[[#This Row],[ABRIL]]+Tabela373[[#This Row],[MAIO]]+Tabela373[[#This Row],[JUNHO]]+Tabela373[[#This Row],[JULHO]]+Tabela373[[#This Row],[AGOSTO]]+Tabela373[[#This Row],[SETEMBRO]]+Tabela373[[#This Row],[NOVEMBRO]]+Tabela373[[#This Row],[DEZEMBRO]]) -> 0 | AL89: =IFERROR(AK89/$AK$3,"") | AM89: =AVERAGE(Tabela373[[#This Row],[JANEIRO]],Tabela373[[#This Row],[FEVEREIRO]],Tabela373[[#This Row],[MARÇO]],Tabela373[[#This Row],[ABRIL]],Tabela373[[#This Row],[MAIO]],Tabela373[[#This Row],[JUNHO]],Tabela373[[#This Row],[JULHO]],Tabela373[[#This Row],[AGOSTO]],Tabela373[[#This Row],[SETEMBRO]],Tabela373[[#This Row],[OUTUBRO]],Tabela373[[#This Row],[NOVEMBRO]],Tabela373[[#This Row],[DEZEMBRO]]) -> #DIV/0!
A90: CONTRIBUIÇÃO SINDICAL PRODUÇÃO | C90: =IFERROR(B90/$B$3,"") | E90: =IFERROR(D90/$D$3,"") | F90: =IFERROR((D90-B90)/B90,"") | H90: =IFERROR(G90/$G$3,"") | I90: =IFERROR((G90-D90)/D90,"") | K90: =IFERROR(J90/$J$3,"") | L90: =IFERROR((J90-G90)/G90,"") | N90: =IFERROR(M90/$M$3,"") | O90: =IFERROR((M90-J90)/J90,"") | Q90: =IFERROR(P90/$P$3,"") | R90: =IFERROR((P90-M90)/M90,"") | T90: =IFERROR(S90/$S$3,"") | U90: =IFERROR((S90-P90)/P90,"") | W90: =IFERROR(V90/$V$3,"") | X90: =IFERROR((V90-S90)/S90,"") | Z90: =IFERROR(Y90/$Y$3,"") | AA90: =IFERROR((Y90-V90)/V90,"") | AC90: =IFERROR(AB90/$AB$3,"") | AD90: =IFERROR((AB90-Y90)/Y90,"") | AF90: =IFERROR(AE90/$AE$3,"") | AG90: =IFERROR((AE90-AB90)/AB90,"") | AI90: =IFERROR(AH90/$AH$3,"") | AJ90: =IFERROR((AH90-AE90)/AE90,"") | AK90: =SUM(Tabela373[[#This Row],[JANEIRO]]+Tabela373[[#This Row],[FEVEREIRO]]+Tabela373[[#This Row],[MARÇO]]+Tabela373[[#This Row],[ABRIL]]+Tabela373[[#This Row],[MAIO]]+Tabela373[[#This Row],[JUNHO]]+Tabela373[[#This Row],[JULHO]]+Tabela373[[#This Row],[AGOSTO]]+Tabela373[[#This Row],[SETEMBRO]]+Tabela373[[#This Row],[NOVEMBRO]]+Tabela373[[#This Row],[DEZEMBRO]]) -> 0 | AL90: =IFERROR(AK90/$AK$3,"") | AM90: =AVERAGE(Tabela373[[#This Row],[JANEIRO]],Tabela373[[#This Row],[FEVEREIRO]],Tabela373[[#This Row],[MARÇO]],Tabela373[[#This Row],[ABRIL]],Tabela373[[#This Row],[MAIO]],Tabela373[[#This Row],[JUNHO]],Tabela373[[#This Row],[JULHO]],Tabela373[[#This Row],[AGOSTO]],Tabela373[[#This Row],[SETEMBRO]],Tabela373[[#This Row],[OUTUBRO]],Tabela373[[#This Row],[NOVEMBRO]],Tabela373[[#This Row],[DEZEMBRO]]) -> #DIV/0!
A91: EPI | C91: =IFERROR(B91/$B$3,"") | E91: =IFERROR(D91/$D$3,"") | F91: =IFERROR((D91-B91)/B91,"") | H91: =IFERROR(G91/$G$3,"") | I91: =IFERROR((G91-D91)/D91,"") | K91: =IFERROR(J91/$J$3,"") | L91: =IFERROR((J91-G91)/G91,"") | N91: =IFERROR(M91/$M$3,"") | O91: =IFERROR((M91-J91)/J91,"") | Q91: =IFERROR(P91/$P$3,"") | R91: =IFERROR((P91-M91)/M91,"") | T91: =IFERROR(S91/$S$3,"") | U91: =IFERROR((S91-P91)/P91,"") | W91: =IFERROR(V91/$V$3,"") | X91: =IFERROR((V91-S91)/S91,"") | Z91: =IFERROR(Y91/$Y$3,"") | AA91: =IFERROR((Y91-V91)/V91,"") | AC91: =IFERROR(AB91/$AB$3,"") | AD91: =IFERROR((AB91-Y91)/Y91,"") | AF91: =IFERROR(AE91/$AE$3,"") | AG91: =IFERROR((AE91-AB91)/AB91,"") | AI91: =IFERROR(AH91/$AH$3,"") | AJ91: =IFERROR((AH91-AE91)/AE91,"") | AK91: =SUM(Tabela373[[#This Row],[JANEIRO]]+Tabela373[[#This Row],[FEVEREIRO]]+Tabela373[[#This Row],[MARÇO]]+Tabela373[[#This Row],[ABRIL]]+Tabela373[[#This Row],[MAIO]]+Tabela373[[#This Row],[JUNHO]]+Tabela373[[#This Row],[JULHO]]+Tabela373[[#This Row],[AGOSTO]]+Tabela373[[#This Row],[SETEMBRO]]+Tabela373[[#This Row],[NOVEMBRO]]+Tabela373[[#This Row],[DEZEMBRO]]) -> 0 | AL91: =IFERROR(AK91/$AK$3,"") | AM91: =AVERAGE(Tabela373[[#This Row],[JANEIRO]],Tabela373[[#This Row],[FEVEREIRO]],Tabela373[[#This Row],[MARÇO]],Tabela373[[#This Row],[ABRIL]],Tabela373[[#This Row],[MAIO]],Tabela373[[#This Row],[JUNHO]],Tabela373[[#This Row],[JULHO]],Tabela373[[#This Row],[AGOSTO]],Tabela373[[#This Row],[SETEMBRO]],Tabela373[[#This Row],[OUTUBRO]],Tabela373[[#This Row],[NOVEMBRO]],Tabela373[[#This Row],[DEZEMBRO]]) -> #DIV/0!
A92: FÉRIAS PRODUÇÃO | C92: =IFERROR(B92/$B$3,"") | E92: =IFERROR(D92/$D$3,"") | F92: =IFERROR((D92-B92)/B92,"") | H92: =IFERROR(G92/$G$3,"") | I92: =IFERROR((G92-D92)/D92,"") | K92: =IFERROR(J92/$J$3,"") | L92: =IFERROR((J92-G92)/G92,"") | N92: =IFERROR(M92/$M$3,"") | O92: =IFERROR((M92-J92)/J92,"") | Q92: =IFERROR(P92/$P$3,"") | R92: =IFERROR((P92-M92)/M92,"") | T92: =IFERROR(S92/$S$3,"") | U92: =IFERROR((S92-P92)/P92,"") | W92: =IFERROR(V92/$V$3,"") | X92: =IFERROR((V92-S92)/S92,"") | Z92: =IFERROR(Y92/$Y$3,"") | AA92: =IFERROR((Y92-V92)/V92,"") | AC92: =IFERROR(AB92/$AB$3,"") | AD92: =IFERROR((AB92-Y92)/Y92,"") | AF92: =IFERROR(AE92/$AE$3,"") | AG92: =IFERROR((AE92-AB92)/AB92,"") | AI92: =IFERROR(AH92/$AH$3,"") | AJ92: =IFERROR((AH92-AE92)/AE92,"") | AK92: =SUM(Tabela373[[#This Row],[JANEIRO]]+Tabela373[[#This Row],[FEVEREIRO]]+Tabela373[[#This Row],[MARÇO]]+Tabela373[[#This Row],[ABRIL]]+Tabela373[[#This Row],[MAIO]]+Tabela373[[#This Row],[JUNHO]]+Tabela373[[#This Row],[JULHO]]+Tabela373[[#This Row],[AGOSTO]]+Tabela373[[#This Row],[SETEMBRO]]+Tabela373[[#This Row],[NOVEMBRO]]+Tabela373[[#This Row],[DEZEMBRO]]) -> 0 | AL92: =IFERROR(AK92/$AK$3,"") | AM92: =AVERAGE(Tabela373[[#This Row],[JANEIRO]],Tabela373[[#This Row],[FEVEREIRO]],Tabela373[[#This Row],[MARÇO]],Tabela373[[#This Row],[ABRIL]],Tabela373[[#This Row],[MAIO]],Tabela373[[#This Row],[JUNHO]],Tabela373[[#This Row],[JULHO]],Tabela373[[#This Row],[AGOSTO]],Tabela373[[#This Row],[SETEMBRO]],Tabela373[[#This Row],[OUTUBRO]],Tabela373[[#This Row],[NOVEMBRO]],Tabela373[[#This Row],[DEZEMBRO]]) -> #DIV/0!
A93: FGTS PRODUÇÃO | C93: =IFERROR(B93/$B$3,"") | E93: =IFERROR(D93/$D$3,"") | F93: =IFERROR((D93-B93)/B93,"") | H93: =IFERROR(G93/$G$3,"") | I93: =IFERROR((G93-D93)/D93,"") | K93: =IFERROR(J93/$J$3,"") | L93: =IFERROR((J93-G93)/G93,"") | N93: =IFERROR(M93/$M$3,"") | O93: =IFERROR((M93-J93)/J93,"") | Q93: =IFERROR(P93/$P$3,"") | R93: =IFERROR((P93-M93)/M93,"") | T93: =IFERROR(S93/$S$3,"") | U93: =IFERROR((S93-P93)/P93,"") | W93: =IFERROR(V93/$V$3,"") | X93: =IFERROR((V93-S93)/S93,"") | Z93: =IFERROR(Y93/$Y$3,"") | AA93: =IFERROR((Y93-V93)/V93,"") | AC93: =IFERROR(AB93/$AB$3,"") | AD93: =IFERROR((AB93-Y93)/Y93,"") | AF93: =IFERROR(AE93/$AE$3,"") | AG93: =IFERROR((AE93-AB93)/AB93,"") | AI93: =IFERROR(AH93/$AH$3,"") | AJ93: =IFERROR((AH93-AE93)/AE93,"") | AK93: =SUM(Tabela373[[#This Row],[JANEIRO]]+Tabela373[[#This Row],[FEVEREIRO]]+Tabela373[[#This Row],[MARÇO]]+Tabela373[[#This Row],[ABRIL]]+Tabela373[[#This Row],[MAIO]]+Tabela373[[#This Row],[JUNHO]]+Tabela373[[#This Row],[JULHO]]+Tabela373[[#This Row],[AGOSTO]]+Tabela373[[#This Row],[SETEMBRO]]+Tabela373[[#This Row],[NOVEMBRO]]+Tabela373[[#This Row],[DEZEMBRO]]) -> 0 | AL93: =IFERROR(AK93/$AK$3,"") | AM93: =AVERAGE(Tabela373[[#This Row],[JANEIRO]],Tabela373[[#This Row],[FEVEREIRO]],Tabela373[[#This Row],[MARÇO]],Tabela373[[#This Row],[ABRIL]],Tabela373[[#This Row],[MAIO]],Tabela373[[#This Row],[JUNHO]],Tabela373[[#This Row],[JULHO]],Tabela373[[#This Row],[AGOSTO]],Tabela373[[#This Row],[SETEMBRO]],Tabela373[[#This Row],[OUTUBRO]],Tabela373[[#This Row],[NOVEMBRO]],Tabela373[[#This Row],[DEZEMBRO]]) -> #DIV/0!
A94: HORAS EXTRAS PRODUÇÃO | C94: =IFERROR(B94/$B$3,"") | E94: =IFERROR(D94/$D$3,"") | F94: =IFERROR((D94-B94)/B94,"") | H94: =IFERROR(G94/$G$3,"") | I94: =IFERROR((G94-D94)/D94,"") | K94: =IFERROR(J94/$J$3,"") | L94: =IFERROR((J94-G94)/G94,"") | N94: =IFERROR(M94/$M$3,"") | O94: =IFERROR((M94-J94)/J94,"") | Q94: =IFERROR(P94/$P$3,"") | R94: =IFERROR((P94-M94)/M94,"") | T94: =IFERROR(S94/$S$3,"") | U94: =IFERROR((S94-P94)/P94,"") | W94: =IFERROR(V94/$V$3,"") | X94: =IFERROR((V94-S94)/S94,"") | Z94: =IFERROR(Y94/$Y$3,"") | AA94: =IFERROR((Y94-V94)/V94,"") | AC94: =IFERROR(AB94/$AB$3,"") | AD94: =IFERROR((AB94-Y94)/Y94,"") | AF94: =IFERROR(AE94/$AE$3,"") | AG94: =IFERROR((AE94-AB94)/AB94,"") | AI94: =IFERROR(AH94/$AH$3,"") | AJ94: =IFERROR((AH94-AE94)/AE94,"") | AK94: =SUM(Tabela373[[#This Row],[JANEIRO]]+Tabela373[[#This Row],[FEVEREIRO]]+Tabela373[[#This Row],[MARÇO]]+Tabela373[[#This Row],[ABRIL]]+Tabela373[[#This Row],[MAIO]]+Tabela373[[#This Row],[JUNHO]]+Tabela373[[#This Row],[JULHO]]+Tabela373[[#This Row],[AGOSTO]]+Tabela373[[#This Row],[SETEMBRO]]+Tabela373[[#This Row],[NOVEMBRO]]+Tabela373[[#This Row],[DEZEMBRO]]) -> 0 | AL94: =IFERROR(AK94/$AK$3,"") | AM94: =AVERAGE(Tabela373[[#This Row],[JANEIRO]],Tabela373[[#This Row],[FEVEREIRO]],Tabela373[[#This Row],[MARÇO]],Tabela373[[#This Row],[ABRIL]],Tabela373[[#This Row],[MAIO]],Tabela373[[#This Row],[JUNHO]],Tabela373[[#This Row],[JULHO]],Tabela373[[#This Row],[AGOSTO]],Tabela373[[#This Row],[SETEMBRO]],Tabela373[[#This Row],[OUTUBRO]],Tabela373[[#This Row],[NOVEMBRO]],Tabela373[[#This Row],[DEZEMBRO]]) -> #DIV/0!
A95: INSS PRODUÇÃO | C95: =IFERROR(B95/$B$3,"") | E95: =IFERROR(D95/$D$3,"") | F95: =IFERROR((D95-B95)/B95,"") | H95: =IFERROR(G95/$G$3,"") | I95: =IFERROR((G95-D95)/D95,"") | K95: =IFERROR(J95/$J$3,"") | L95: =IFERROR((J95-G95)/G95,"") | N95: =IFERROR(M95/$M$3,"") | O95: =IFERROR((M95-J95)/J95,"") | Q95: =IFERROR(P95/$P$3,"") | R95: =IFERROR((P95-M95)/M95,"") | T95: =IFERROR(S95/$S$3,"") | U95: =IFERROR((S95-P95)/P95,"") | W95: =IFERROR(V95/$V$3,"") | X95: =IFERROR((V95-S95)/S95,"") | Z95: =IFERROR(Y95/$Y$3,"") | AA95: =IFERROR((Y95-V95)/V95,"") | AC95: =IFERROR(AB95/$AB$3,"") | AD95: =IFERROR((AB95-Y95)/Y95,"") | AF95: =IFERROR(AE95/$AE$3,"") | AG95: =IFERROR((AE95-AB95)/AB95,"") | AI95: =IFERROR(AH95/$AH$3,"") | AJ95: =IFERROR((AH95-AE95)/AE95,"") | AK95: =SUM(Tabela373[[#This Row],[JANEIRO]]+Tabela373[[#This Row],[FEVEREIRO]]+Tabela373[[#This Row],[MARÇO]]+Tabela373[[#This Row],[ABRIL]]+Tabela373[[#This Row],[MAIO]]+Tabela373[[#This Row],[JUNHO]]+Tabela373[[#This Row],[JULHO]]+Tabela373[[#This Row],[AGOSTO]]+Tabela373[[#This Row],[SETEMBRO]]+Tabela373[[#This Row],[NOVEMBRO]]+Tabela373[[#This Row],[DEZEMBRO]]) -> 0 | AL95: =IFERROR(AK95/$AK$3,"") | AM95: =AVERAGE(Tabela373[[#This Row],[JANEIRO]],Tabela373[[#This Row],[FEVEREIRO]],Tabela373[[#This Row],[MARÇO]],Tabela373[[#This Row],[ABRIL]],Tabela373[[#This Row],[MAIO]],Tabela373[[#This Row],[JUNHO]],Tabela373[[#This Row],[JULHO]],Tabela373[[#This Row],[AGOSTO]],Tabela373[[#This Row],[SETEMBRO]],Tabela373[[#This Row],[OUTUBRO]],Tabela373[[#This Row],[NOVEMBRO]],Tabela373[[#This Row],[DEZEMBRO]]) -> #DIV/0!
A96: RECISÃO PRODUÇÃO | C96: =IFERROR(B96/$B$3,"") | E96: =IFERROR(D96/$D$3,"") | F96: =IFERROR((D96-B96)/B96,"") | H96: =IFERROR(G96/$G$3,"") | I96: =IFERROR((G96-D96)/D96,"") | K96: =IFERROR(J96/$J$3,"") | L96: =IFERROR((J96-G96)/G96,"") | N96: =IFERROR(M96/$M$3,"") | O96: =IFERROR((M96-J96)/J96,"") | Q96: =IFERROR(P96/$P$3,"") | R96: =IFERROR((P96-M96)/M96,"") | T96: =IFERROR(S96/$S$3,"") | U96: =IFERROR((S96-P96)/P96,"") | W96: =IFERROR(V96/$V$3,"") | X96: =IFERROR((V96-S96)/S96,"") | Z96: =IFERROR(Y96/$Y$3,"") | AA96: =IFERROR((Y96-V96)/V96,"") | AC96: =IFERROR(AB96/$AB$3,"") | AD96: =IFERROR((AB96-Y96)/Y96,"") | AF96: =IFERROR(AE96/$AE$3,"") | AG96: =IFERROR((AE96-AB96)/AB96,"") | AI96: =IFERROR(AH96/$AH$3,"") | AJ96: =IFERROR((AH96-AE96)/AE96,"") | AK96: =SUM(Tabela373[[#This Row],[JANEIRO]]+Tabela373[[#This Row],[FEVEREIRO]]+Tabela373[[#This Row],[MARÇO]]+Tabela373[[#This Row],[ABRIL]]+Tabela373[[#This Row],[MAIO]]+Tabela373[[#This Row],[JUNHO]]+Tabela373[[#This Row],[JULHO]]+Tabela373[[#This Row],[AGOSTO]]+Tabela373[[#This Row],[SETEMBRO]]+Tabela373[[#This Row],[NOVEMBRO]]+Tabela373[[#This Row],[DEZEMBRO]]) -> 0 | AL96: =IFERROR(AK96/$AK$3,"") | AM96: =AVERAGE(Tabela373[[#This Row],[JANEIRO]],Tabela373[[#This Row],[FEVEREIRO]],Tabela373[[#This Row],[MARÇO]],Tabela373[[#This Row],[ABRIL]],Tabela373[[#This Row],[MAIO]],Tabela373[[#This Row],[JUNHO]],Tabela373[[#This Row],[JULHO]],Tabela373[[#This Row],[AGOSTO]],Tabela373[[#This Row],[SETEMBRO]],Tabela373[[#This Row],[OUTUBRO]],Tabela373[[#This Row],[NOVEMBRO]],Tabela373[[#This Row],[DEZEMBRO]]) -> #DIV/0!
A97: SALÁRIOS PRODUÇÃO | C97: =IFERROR(B97/$B$3,"") | E97: =IFERROR(D97/$D$3,"") | F97: =IFERROR((D97-B97)/B97,"") | H97: =IFERROR(G97/$G$3,"") | I97: =IFERROR((G97-D97)/D97,"") | K97: =IFERROR(J97/$J$3,"") | L97: =IFERROR((J97-G97)/G97,"") | N97: =IFERROR(M97/$M$3,"") | O97: =IFERROR((M97-J97)/J97,"") | Q97: =IFERROR(P97/$P$3,"") | R97: =IFERROR((P97-M97)/M97,"") | T97: =IFERROR(S97/$S$3,"") | U97: =IFERROR((S97-P97)/P97,"") | W97: =IFERROR(V97/$V$3,"") | X97: =IFERROR((V97-S97)/S97,"") | Z97: =IFERROR(Y97/$Y$3,"") | AA97: =IFERROR((Y97-V97)/V97,"") | AC97: =IFERROR(AB97/$AB$3,"") | AD97: =IFERROR((AB97-Y97)/Y97,"") | AF97: =IFERROR(AE97/$AE$3,"") | AG97: =IFERROR((AE97-AB97)/AB97,"") | AI97: =IFERROR(AH97/$AH$3,"") | AJ97: =IFERROR((AH97-AE97)/AE97,"") | AK97: =SUM(Tabela373[[#This Row],[JANEIRO]]+Tabela373[[#This Row],[FEVEREIRO]]+Tabela373[[#This Row],[MARÇO]]+Tabela373[[#This Row],[ABRIL]]+Tabela373[[#This Row],[MAIO]]+Tabela373[[#This Row],[JUNHO]]+Tabela373[[#This Row],[JULHO]]+Tabela373[[#This Row],[AGOSTO]]+Tabela373[[#This Row],[SETEMBRO]]+Tabela373[[#This Row],[NOVEMBRO]]+Tabela373[[#This Row],[DEZEMBRO]]) -> 0 | AL97: =IFERROR(AK97/$AK$3,"") | AM97: =AVERAGE(Tabela373[[#This Row],[JANEIRO]],Tabela373[[#This Row],[FEVEREIRO]],Tabela373[[#This Row],[MARÇO]],Tabela373[[#This Row],[ABRIL]],Tabela373[[#This Row],[MAIO]],Tabela373[[#This Row],[JUNHO]],Tabela373[[#This Row],[JULHO]],Tabela373[[#This Row],[AGOSTO]],Tabela373[[#This Row],[SETEMBRO]],Tabela373[[#This Row],[OUTUBRO]],Tabela373[[#This Row],[NOVEMBRO]],Tabela373[[#This Row],[DEZEMBRO]]) -> #DIV/0!
A98: VALE TRANSPORTE PRODUÇÃO | C98: =IFERROR(B98/$B$3,"") | E98: =IFERROR(D98/$D$3,"") | F98: =IFERROR((D98-B98)/B98,"") | H98: =IFERROR(G98/$G$3,"") | I98: =IFERROR((G98-D98)/D98,"") | K98: =IFERROR(J98/$J$3,"") | L98: =IFERROR((J98-G98)/G98,"") | N98: =IFERROR(M98/$M$3,"") | O98: =IFERROR((M98-J98)/J98,"") | Q98: =IFERROR(P98/$P$3,"") | R98: =IFERROR((P98-M98)/M98,"") | T98: =IFERROR(S98/$S$3,"") | U98: =IFERROR((S98-P98)/P98,"") | W98: =IFERROR(V98/$V$3,"") | X98: =IFERROR((V98-S98)/S98,"") | Z98: =IFERROR(Y98/$Y$3,"") | AA98: =IFERROR((Y98-V98)/V98,"") | AC98: =IFERROR(AB98/$AB$3,"") | AD98: =IFERROR((AB98-Y98)/Y98,"") | AF98: =IFERROR(AE98/$AE$3,"") | AG98: =IFERROR((AE98-AB98)/AB98,"") | AI98: =IFERROR(AH98/$AH$3,"") | AJ98: =IFERROR((AH98-AE98)/AE98,"") | AK98: =SUM(Tabela373[[#This Row],[JANEIRO]]+Tabela373[[#This Row],[FEVEREIRO]]+Tabela373[[#This Row],[MARÇO]]+Tabela373[[#This Row],[ABRIL]]+Tabela373[[#This Row],[MAIO]]+Tabela373[[#This Row],[JUNHO]]+Tabela373[[#This Row],[JULHO]]+Tabela373[[#This Row],[AGOSTO]]+Tabela373[[#This Row],[SETEMBRO]]+Tabela373[[#This Row],[NOVEMBRO]]+Tabela373[[#This Row],[DEZEMBRO]]) -> 0 | AL98: =IFERROR(AK98/$AK$3,"") | AM98: =AVERAGE(Tabela373[[#This Row],[JANEIRO]],Tabela373[[#This Row],[FEVEREIRO]],Tabela373[[#This Row],[MARÇO]],Tabela373[[#This Row],[ABRIL]],Tabela373[[#This Row],[MAIO]],Tabela373[[#This Row],[JUNHO]],Tabela373[[#This Row],[JULHO]],Tabela373[[#This Row],[AGOSTO]],Tabela373[[#This Row],[SETEMBRO]],Tabela373[[#This Row],[OUTUBRO]],Tabela373[[#This Row],[NOVEMBRO]],Tabela373[[#This Row],[DEZEMBRO]]) -> #DIV/0!
C99: =IFERROR(B99/$B$3,"") | E99: =IFERROR(D99/$D$3,"") | F99: =IFERROR((D99-B99)/B99,"") | H99: =IFERROR(G99/$G$3,"") | I99: =IFERROR((G99-D99)/D99,"") | K99: =IFERROR(J99/$J$3,"") | L99: =IFERROR((J99-G99)/G99,"") | N99: =IFERROR(M99/$M$3,"") | O99: =IFERROR((M99-J99)/J99,"") | Q99: =IFERROR(P99/$P$3,"") | R99: =IFERROR((P99-M99)/M99,"") | T99: =IFERROR(S99/$S$3,"") | U99: =IFERROR((S99-P99)/P99,"") | W99: =IFERROR(V99/$V$3,"") | X99: =IFERROR((V99-S99)/S99,"") | Z99: =IFERROR(Y99/$Y$3,"") | AA99: =IFERROR((Y99-V99)/V99,"") | AC99: =IFERROR(AB99/$AB$3,"") | AD99: =IFERROR((AB99-Y99)/Y99,"") | AF99: =IFERROR(AE99/$AE$3,"") | AG99: =IFERROR((AE99-AB99)/AB99,"") | AI99: =IFERROR(AH99/$AH$3,"") | AJ99: =IFERROR((AH99-AE99)/AE99,"") | AK99: =SUM(Tabela373[[#This Row],[JANEIRO]]+Tabela373[[#This Row],[FEVEREIRO]]+Tabela373[[#This Row],[MARÇO]]+Tabela373[[#This Row],[ABRIL]]+Tabela373[[#This Row],[MAIO]]+Tabela373[[#This Row],[JUNHO]]+Tabela373[[#This Row],[JULHO]]+Tabela373[[#This Row],[AGOSTO]]+Tabela373[[#This Row],[SETEMBRO]]+Tabela373[[#This Row],[NOVEMBRO]]+Tabela373[[#This Row],[DEZEMBRO]]) -> 0 | AL99: =IFERROR(AK99/$AK$3,"") | AM99: =AVERAGE(Tabela373[[#This Row],[JANEIRO]],Tabela373[[#This Row],[FEVEREIRO]],Tabela373[[#This Row],[MARÇO]],Tabela373[[#This Row],[ABRIL]],Tabela373[[#This Row],[MAIO]],Tabela373[[#This Row],[JUNHO]],Tabela373[[#This Row],[JULHO]],Tabela373[[#This Row],[AGOSTO]],Tabela373[[#This Row],[SETEMBRO]],Tabela373[[#This Row],[OUTUBRO]],Tabela373[[#This Row],[NOVEMBRO]],Tabela373[[#This Row],[DEZEMBRO]]) -> #DIV/0!
A100: OUTROS CUSTOS OPERACIONAIS | B100: =SUM(B101:B104) -> 0 | C100: =IFERROR(B100/$B$3,"") | D100: =SUM(D101:D104) -> 0 | E100: =IFERROR(D100/$D$3,"") | F100: =IFERROR((D100-B100)/B100,"") | G100: =SUM(G101:G104) -> 0 | H100: =IFERROR(G100/$G$3,"") | I100: =IFERROR((G100-D100)/D100,"") | J100: =SUM(J101:J104) -> 0 | K100: =IFERROR(J100/$J$3,"") | L100: =IFERROR((J100-G100)/G100,"") | M100: =SUM(M101:M104) -> 0 | N100: =IFERROR(M100/$M$3,"") | O100: =IFERROR((M100-J100)/J100,"") | P100: =SUM(P101:P104) -> 0 | Q100: =IFERROR(P100/$P$3,"") | R100: =IFERROR((P100-M100)/M100,"") | S100: =SUM(S101:S104) -> 0 | T100: =IFERROR(S100/$S$3,"") | U100: =IFERROR((S100-P100)/P100,"") | V100: =SUM(V101:V104) -> 0 | W100: =IFERROR(V100/$V$3,"") | X100: =IFERROR((V100-S100)/S100,"") | Y100: =SUM(Y101:Y104) -> 0 | Z100: =IFERROR(Y100/$Y$3,"") | AA100: =IFERROR((Y100-V100)/V100,"") | AB100: =SUM(AB101:AB104) -> 0 | AC100: =IFERROR(AB100/$AB$3,"") | AD100: =IFERROR((AB100-Y100)/Y100,"") | AE100: =SUM(AE101:AE104) -> 0 | AF100: =IFERROR(AE100/$AE$3,"") | AG100: =IFERROR((AE100-AB100)/AB100,"") | AH100: =SUM(AH101:AH104) -> 0 | AI100: =IFERROR(AH100/$AH$3,"") | AJ100: =IFERROR((AH100-AE100)/AE100,"") | AK100: =SUM(Tabela373[[#This Row],[JANEIRO]]+Tabela373[[#This Row],[FEVEREIRO]]+Tabela373[[#This Row],[MARÇO]]+Tabela373[[#This Row],[ABRIL]]+Tabela373[[#This Row],[MAIO]]+Tabela373[[#This Row],[JUNHO]]+Tabela373[[#This Row],[JULHO]]+Tabela373[[#This Row],[AGOSTO]]+Tabela373[[#This Row],[SETEMBRO]]+Tabela373[[#This Row],[NOVEMBRO]]+Tabela373[[#This Row],[DEZEMBRO]]) -> 0 | AL100: =IFERROR(AK100/$AK$3,"") | AM100: =AVERAGE(Tabela373[[#This Row],[JANEIRO]],Tabela373[[#This Row],[FEVEREIRO]],Tabela373[[#This Row],[MARÇO]],Tabela373[[#This Row],[ABRIL]],Tabela373[[#This Row],[MAIO]],Tabela373[[#This Row],[JUNHO]],Tabela373[[#This Row],[JULHO]],Tabela373[[#This Row],[AGOSTO]],Tabela373[[#This Row],[SETEMBRO]],Tabela373[[#This Row],[OUTUBRO]],Tabela373[[#This Row],[NOVEMBRO]],Tabela373[[#This Row],[DEZEMBRO]]) -> 0
...

Sheet BP
A1: BALANÇO PATRIMONIAL
B2: 2024 | C2: 2025 | D2: 2026
A3: A T I V O
A4: ATIVO CIRCULANTE | B4: =SUM(B5:B6) -> 0 | C4: =SUM(C5:C6) -> 0 | D4: =SUM(D5:D6) -> 0
A5: Banco/Caixa
A6: Contas a Receber
A8: ATIVO NÃO CIRCULANTE | B8: =SUM(B9,B12,B15,B24) -> 0 | C8: =SUM(C9,C12,C15,C24) -> 0 | D8: =SUM(D9,D12,D15,D24) -> 0
A9: Ativo Realizável a Longo Prazo | B9: =SUM(B10) -> 0 | C9: =SUM(C10) -> 0 | D9: =SUM(D10) -> 0
A10: Ativo 1
A12: Investimentos | B12: =SUM(B13) -> 0 | C12: =SUM(C13) -> 0 | D12: =SUM(D13) -> 0
A13: Investimento 1
A15: Imobilizado | B15: =SUM(B16:B22) -> 0 | C15: =SUM(C16:C22) -> 0 | D15: =SUM(D16:D22) -> 0
A16: Terrenos
A17: Edificações
A18: Veículos
A19: Móveis e Utensílios
A20: Máquinas e Equipamentos
A21: Computadores
A22: (-) Depreciação Acumulada
A24: Intangível | B24: =SUM(B25:B26) -> 0 | C24: =SUM(C25:C26) -> 0 | D24: =SUM(D25:D26) -> 0
A25: Software
A26: (-) Amortização Acumulada
A28: TOTAL DO ATIVO | B28: =B4+B8 -> 0 | C28: =C4+C8 -> 0 | D28: =D4+D8 -> 0
A30: P A S S I V O
A32: PASSIVO CIRCULANTE | B32: =SUM(B33:B37) -> 0 | C32: =SUM(C33:C37) -> 0 | D32: =SUM(D33:D37) -> 0
A33: Tributos a Recolher
A34: Provisão de Férias
A35: Salários a Pagar
A36: Contas a Pagar
A37: Outros ajustes
A39: PASSIVO NÃO CIRCULANTE | B39: =SUM(B40:B41) -> 0 | C39: =SUM(C40:C41) -> 0 | D39: =SUM(D40:D41) -> 0
A40: Contas a Pagar LP
A41: Empréstimo/Financiamento
A43: PATRIMÔNIO LÍQUIDO | B43: =SUM(B44:B45) -> 0 | C43: =SUM(C44:C45) -> 0 | D43: =SUM(D44:D45) -> 0
A44: Capital Social
A45: Lucro/Prejuízo
A47: TOTAL DO PASSIVO | B47: =B32+B39+B43 -> 0 | C47: =C32+C39+C43 -> 0 | D47: =D32+D39+D43 -> 0

Sheet Indicadores
A1: INDICADORES FINANCEIROS
A2: Aba automática conectada às abas FC, DRE e BP. Preencha os relatórios-base e os indicadores serão atualizados.
A5: Indicadores Mensais (DRE e Fluxo de Caixa)
A6: Indicador | B6: Jan | C6: Fev | D6: Mar | E6: Abr | F6: Mai | G6: Jun | H6: Jul | I6: Ago | J6: Set | K6: Out | L6: Nov | M6: Dez | N6: Total | O6: Média
A7: Receita Líquida | B7: =IFERROR(DRE!B$43,"") -> 0 | C7: =IFERROR(DRE!D$43,"") -> 0 | D7: =IFERROR(DRE!G$43,"") -> 0 | E7: =IFERROR(DRE!J$43,"") -> 0 | F7: =IFERROR(DRE!M$43,"") -> 0 | G7: =IFERROR(DRE!P$43,"") -> 0 | H7: =IFERROR(DRE!S$43,"") -> 0 | I7: =IFERROR(DRE!V$43,"") -> 0 | J7: =IFERROR(DRE!Y$43,"") -> 0 | K7: =IFERROR(DRE!AB$43,"") -> 0 | L7: =IFERROR(DRE!AE$43,"") -> 0 | M7: =IFERROR(DRE!AH$43,"") -> 0 | N7: =IFERROR(DRE!$AK$43,"") -> 0 | O7: =IFERROR(AVERAGE(B7:M7),"") -> 0
A8: Margem Bruta | B8: =IFERROR((DRE!B$43-DRE!B$44)/DRE!B$43,"") | C8: =IFERROR((DRE!D$43-DRE!D$44)/DRE!D$43,"") | D8: =IFERROR((DRE!G$43-DRE!G$44)/DRE!G$43,"") | E8: =IFERROR((DRE!J$43-DRE!J$44)/DRE!J$43,"") | F8: =IFERROR((DRE!M$43-DRE!M$44)/DRE!M$43,"") | G8: =IFERROR((DRE!P$43-DRE!P$44)/DRE!P$43,"") | H8: =IFERROR((DRE!S$43-DRE!S$44)/DRE!S$43,"") | I8: =IFERROR((DRE!V$43-DRE!V$44)/DRE!V$43,"") | J8: =IFERROR((DRE!Y$43-DRE!Y$44)/DRE!Y$43,"") | K8: =IFERROR((DRE!AB$43-DRE!AB$44)/DRE!AB$43,"") | L8: =IFERROR((DRE!AE$43-DRE!AE$44)/DRE!AE$43,"") | M8: =IFERROR((DRE!AH$43-DRE!AH$44)/DRE!AH$43,"") | N8: =IFERROR((DRE!$AK$43-DRE!$AK$44)/DRE!$AK$43,"") | O8: =IFERROR(AVERAGE(B8:M8),"")
A9: Margem de Contribuição | B9: =IFERROR(DRE!B$85/DRE!B$43,"") | C9: =IFERROR(DRE!D$85/DRE!D$43,"") | D9: =IFERROR(DRE!G$85/DRE!G$43,"") | E9: =IFERROR(DRE!J$85/DRE!J$43,"") | F9: =IFERROR(DRE!M$85/DRE!M$43,"") | G9: =IFERROR(DRE!P$85/DRE!P$43,"") | H9: =IFERROR(DRE!S$85/DRE!S$43,"") | I9: =IFERROR(DRE!V$85/DRE!V$43,"") | J9: =IFERROR(DRE!Y$85/DRE!Y$43,"") | K9: =IFERROR(DRE!AB$85/DRE!AB$43,"") | L9: =IFERROR(DRE!AE$85/DRE!AE$43,"") | M9: =IFERROR(DRE!AH$85/DRE!AH$43,"") | N9: =IFERROR(DRE!$AK$85/DRE!$AK$43,"") | O9: =IFERROR(AVERAGE(B9:M9),"")
A10: Margem Operacional | B10: =IFERROR(DRE!B$149/DRE!B$43,"") | C10: =IFERROR(DRE!D$149/DRE!D$43,"") | D10: =IFERROR(DRE!G$149/DRE!G$43,"") | E10: =IFERROR(DRE!J$149/DRE!J$43,"") | F10: =IFERROR(DRE!M$149/DRE!M$43,"") | G10: =IFERROR(DRE!P$149/DRE!P$43,"") | H10: =IFERROR(DRE!S$149/DRE!S$43,"") | I10: =IFERROR(DRE!V$149/DRE!V$43,"") | J10: =IFERROR(DRE!Y$149/DRE!Y$43,"") | K10: =IFERROR(DRE!AB$149/DRE!AB$43,"") | L10: =IFERROR(DRE!AE$149/DRE!AE$43,"") | M10: =IFERROR(DRE!AH$149/DRE!AH$43,"") | N10: =IFERROR(DRE!$AK$149/DRE!$AK$43,"") | O10: =IFERROR(AVERAGE(B10:M10),"")
A11: Margem Líquida | B11: =IFERROR((DRE!B$149+DRE!B$150-DRE!B$163+DRE!B$169)/DRE!B$43,"") | C11: =IFERROR((DRE!D$149+DRE!D$150-DRE!D$163+DRE!D$169)/DRE!D$43,"") | D11: =IFERROR((DRE!G$149+DRE!G$150-DRE!G$163+DRE!G$169)/DRE!G$43,"") | E11: =IFERROR((DRE!J$149+DRE!J$150-DRE!J$163+DRE!J$169)/DRE!J$43,"") | F11: =IFERROR((DRE!M$149+DRE!M$150-DRE!M$163+DRE!M$169)/DRE!M$43,"") | G11: =IFERROR((DRE!P$149+DRE!P$150-DRE!P$163+DRE!P$169)/DRE!P$43,"") | H11: =IFERROR((DRE!S$149+DRE!S$150-DRE!S$163+DRE!S$169)/DRE!S$43,"") | I11: =IFERROR((DRE!V$149+DRE!V$150-DRE!V$163+DRE!V$169)/DRE!V$43,"") | J11: =IFERROR((DRE!Y$149+DRE!Y$150-DRE!Y$163+DRE!Y$169)/DRE!Y$43,"") | K11: =IFERROR((DRE!AB$149+DRE!AB$150-DRE!AB$163+DRE!AB$169)/DRE!AB$43,"") | L11: =IFERROR((DRE!AE$149+DRE!AE$150-DRE!AE$163+DRE!AE$169)/DRE!AE$43,"") | M11: =IFERROR((DRE!AH$149+DRE!AH$150-DRE!AH$163+DRE!AH$169)/DRE!AH$43,"") | N11: =IFERROR((DRE!$AK$149+DRE!$AK$150-DRE!$AK$163+DRE!$AK$169)/DRE!$AK$43,"") | O11: =IFERROR(AVERAGE(B11:M11),"")
A12: Geração de Caixa | B12: =IFERROR(FC!B$133,"") -> 0 | C12: =IFERROR(FC!C$133,"") -> 0 | D12: =IFERROR(FC!D$133,"") -> 0 | E12: =IFERROR(FC!E$133,"") -> 0 | F12: =IFERROR(FC!F$133,"") -> 0 | G12: =IFERROR(FC!G$133,"") -> 0 | H12: =IFERROR(FC!H$133,"") -> 0 | I12: =IFERROR(FC!I$133,"") -> 0 | ... M12: =IFERROR(FC!M$133,"") -> 0 | N12: =IFERROR(FC!$N$133,"") -> 0 | O12: =IFERROR(AVERAGE(B12:M12),"") -> 0
A13: Conversão Lucro em Caixa | B13: =IFERROR(FC!B$133/(DRE!B$149+DRE!B$150-DRE!B$163+DRE!B$169),"") | C13: =IFERROR(FC!C$133/(DRE!D$149+DRE!D$150-DRE!D$163+DRE!D$169),"") | D13: =IFERROR(FC!D$133/(DRE!G$149+DRE!G$150-DRE!G$163+DRE!G$169),"") | E13: =IFERROR(FC!E$133/(DRE!J$149+DRE!J$150-DRE!J$163+DRE!J$169),"") | F13: =IFERROR(FC!F$133/(DRE!M$149+DRE!M$150-DRE!M$163+DRE!M$169),"") | G13: =IFERROR(FC!G$133/(DRE!P$149+DRE!P$150-DRE!P$163+DRE!P$169),"") | H13: =IFERROR(FC!H$133/(DRE!S$149+DRE!S$150-DRE!S$163+DRE!S$169),"") | I13: =IFERROR(FC!I$133/(DRE!V$149+DRE!V$150-DRE!V$163+DRE!V$169),"") | J13: =IFERROR(FC!J$133/(DRE!Y$149+DRE!Y$150-DRE!Y$163+DRE!Y$169),"") | K13: =IFERROR(FC!K$133/(DRE!AB$149+DRE!AB$150-DRE!AB$163+DRE!AB$169),"") | L13: =IFERROR(FC!L$133/(DRE!AE$149+DRE!AE$150-DRE!AE$163+DRE!AE$169),"") | M13: =IFERROR(FC!M$133/(DRE!AH$149+DRE!AH$150-DRE!AH$163+DRE!AH$169),"") | N13: =IFERROR(FC!$N$133/(DRE!$AK$149+DRE!$AK$150-DRE!$AK$163+DRE!$AK$169),"") | O13: =IFERROR(AVERAGE(B13:M13),"")
A14: Saldo Final de Caixa | B14: =IFERROR(FC!B$135,"") -> 0 | C14: =IFERROR(FC!C$135,"") -> 0 | D14: =IFERROR(FC!D$135,"") -> 0 | E14: =IFERROR(FC!E$135,"") -> 0 | F14: =IFERROR(FC!F$135,"") -> 0 | G14: =IFERROR(FC!G$135,"") -> 0 | H14: =IFERROR(FC!H$135,"") -> 0 | I14: =IFERROR(FC!I$135,"") -> 0 | ... M14: =IFERROR(FC!M$135,"") -> 0 | N14: =IFERROR(FC!$N$135,"") -> 0 | O14: =IFERROR(AVERAGE(B14:M14),"") -> 0
A17: Indicadores Patrimoniais (Balanço Patrimonial)
A18: Indicador | B18: 2023 | C18: 2024 | D18: 2025 | E18: Fórmula | F18: Leitura
A19: Liquidez Corrente | B19: =IFERROR(BP!B$4/BP!B$32,"") | C19: =IFERROR(BP!C$4/BP!C$32,"") | D19: =IFERROR(BP!D$4/BP!D$32,"") | E19: AC / PC | F19: > 1,00 tende a indicar folga de curto prazo
A20: Capital de Giro | B20: =IFERROR(BP!B$4-BP!B$32,"") -> 0 | C20: =IFERROR(BP!C$4-BP!C$32,"") -> 0 | D20: =IFERROR(BP!D$4-BP!D$32,"") -> 0 | E20: AC - PC | F20: positivo indica estrutura de curto prazo mais saudável
A21: Endividamento Geral | B21: =IFERROR((BP!B$32+BP!B$39)/BP!B$28,"") | C21: =IFERROR((BP!C$32+BP!C$39)/BP!C$28,"") | D21: =IFERROR((BP!D$32+BP!D$39)/BP!D$28,"") | E21: (PC + PNC) / Ativo Total | F21: quanto menor, menor dependência de capital de terceiros
A22: Composição do Endividamento | B22: =IFERROR(BP!B$32/(BP!B$32+BP!B$39),"") | C22: =IFERROR(BP!C$32/(BP!C$32+BP!C$39),"") | D22: =IFERROR(BP!D$32/(BP!D$32+BP!D$39),"") | E22: PC / Dívida Total | F22: mostra peso da dívida de curto prazo
A23: Dívida / Patrimônio Líquido | B23: =IFERROR((BP!B$32+BP!B$39)/BP!B$43,"") | C23: =IFERROR((BP!C$32+BP!C$39)/BP!C$43,"") | D23: =IFERROR((BP!D$32+BP!D$39)/BP!D$43,"") | E23: Dívida Total / PL | F23: mede alavancagem financeira
A24: Liquidez Imediata | B24: =IFERROR(BP!B$5/BP!B$32,"") | C24: =IFERROR(BP!C$5/BP!C$32,"") | D24: =IFERROR(BP!D$5/BP!D$32,"") | E24: Caixa / PC | F24: mede capacidade imediata de pagamento
A25: Imobilização do PL | B25: =IFERROR(BP!B$8/BP!B$43,"") | C25: =IFERROR(BP!C$8/BP!C$43,"") | D25: =IFERROR(BP!D$8/BP!D$43,"") | E25: Ativo Não Circulante / PL | F25: mostra quanto do PL está preso no longo prazo
A28: Indicadores Integrados (Ano Corrente)
A29: Indicador | B29: Valor | C29: Fórmula | D29: Base | E29: Interpretação | F29: Observação
A30: ROE | B30: =IFERROR((DRE!$AK$149+DRE!$AK$150-DRE!$AK$163+DRE!$AK$169)/BP!$D$43,"") | C30: Resultado do Mês Total / PL 2025 | D30: DRE / FC / BP | E30: rentabilidade do capital próprio | F30: usa DRE total e PL do BP 2025
A31: Margem Líquida Total | B31: =IFERROR((DRE!$AK$149+DRE!$AK$150-DRE!$AK$163+DRE!$AK$169)/DRE!$AK$43,"") | C31: Resultado do Mês Total / Receita Líquida Total | D31: DRE / FC / BP | E31: mede ganho final sobre vendas | F31: ano corrente
A32: Conversão de Lucro em Caixa | B32: =IFERROR(FC!$N$133/(DRE!$AK$149+DRE!$AK$150-DRE!$AK$163+DRE!$AK$169),"") | C32: Geração de Caixa / Lucro Líquido | D32: DRE / FC / BP | E32: compara lucro contábil e caixa gerado | F32: ano corrente
A33: Caixa Final / Receita | B33: =IFERROR(FC!$N$135/DRE!$AK$43,"") | C33: Saldo Final de Caixa / Receita Líquida | D33: DRE / FC / BP | E33: mede liquidez acumulada ao fim do período | F33: ano corrente
A34: Capital de Giro 2025 | B34: =IFERROR(BP!$D$4-BP!$D$32,"") -> 0 | C34: AC 2025 - PC 2025 | D34: DRE / FC / BP | E34: folga financeira de curto prazo | F34: extraído do BP
A37: Observação: os indicadores foram estruturados para atualizar automaticamente a partir das abas FC, DRE e BP. Se desejar, na próxima etapa posso criar um painel executivo com semáforos e gráficos.
